Workbook

Sheet 00_Dashboard
A1: SLR Quellen-Workflow Dashboard
A3: Kennzahl | B3: Formel / Wert | D3: Arbeitsreihenfolge | E3: Ziel | F3: Ergebnis | G3: Excel-Blatt | H3: Status
A4: Identifizierte Kandidaten | B4: =COUNTA('02_Screening'!C2:C472) -> 223 | D4: 1 | E4: Alle identifizierten Treffer erfassen | F4: Kandidatenliste mit Herkunft | G4: 02_Screening | H4: done
A5: Eingeschlossen | B5: =COUNTIF('02_Screening'!L2:L472,"Include") -> 113 | D5: 2 | E5: Datenbank-/Snowballing-Suche dokumentieren | F5: Suchlog + Trefferzahlen | G5: 01_Search_Log | H5: done
A6: Ausgeschlossen | B6: =COUNTIF('02_Screening'!L2:L472,"Exclude") -> 72 | D6: 3 | E6: Titel/Abstract + Volltext screenen | F6: Include/Exclude/Background | G6: 02_Screening | H6: done
A7: Background / Kontext | B7: =COUNTIF('02_Screening'!L2:L472,"Background") -> 38 | D7: 4 | E7: Finale Primärstudien extrahieren | F7: vergleichbare Codierung | G7: 03_Extraction | H7: done
A8: Unklar / prüfen | B8: =COUNTIF('02_Screening'!L2:L472,"Unklar") + COUNTIF('02_Screening'!L2:L472,"Zu prüfen") -> 0 | D8: 5 | E8: Qualität bewerten | F8: Q1-Q8 + Score | G8: 04_Quality_Assessment | H8: done
A9: Volltext geprüft | B9: =COUNTIF('02_Screening'!K2:K472,"Ja") -> 89 | D9: 6 | E9: Je Dokument Slide 2 erstellen | F9: 1 Folie je Paper | G9: 06_Slide2_Template | H9: done
A10: Extraktionen angelegt | B10: =COUNTIF('03_Extraction'!D2:D493,"<>") -> 113 | D10: 7 | E10: Thematische Einordnung | F10: Synthese nach RQ | G10: 05_RQ_Synthesis | H10: done
A11: Qualitätsbewertungen angelegt | B11: =COUNTIF('04_Quality_Assessment'!B2:B478,"<>") -> 113 | D11: 8 | E11: Research Gap formulieren | F11: Überleitung Experiment | G11: 05_RQ_Synthesis | H11: done
A12: Durchschnitt Qualitätsscore | B12: =IFERROR(AVERAGEIF('04_Quality_Assessment'!B2:B478,"<>",'04_Quality_Assessment'!K2:K478),"") -> 7.0221239 | D12: 9 | E12: SLR-Kapitel aktualisieren | F12: Methodik + Ergebnisse | G12: Manuskript | H12: done
D13: 10 | E13: Hilfstools sauber dokumentieren | F13: nicht als Datenbanken aufführen | G13: 01_Search_Log / 02_Screening | H13: done

Sheet 00_ReadMe
A1: Dokumentation der Systematic Literature Review
A3: Diese Arbeitsmappe dokumentiert die im Rahmen der Masterarbeit durchgeführte Systematic Literature Review (SLR). Sie ergänzt die methodische Beschreibung im Haupttext und dient der Nachvollziehbarkeit der Literatursuche, Studienauswahl, Qualitätsbewertung, Datenextraktion und forschungsfragenorientierten Synthese.
A7: Übersicht der Tabellenblätter
A8: Tabellenblatt | B8: Inhalt | C8: Zweck
A9: 00_Dashboard | B9: Zusammenfassende Kennzahlen der SLR und Überblick über den abgeschlossenen Bearbeitungsstand. | C9: Kompakte Übersicht über Suchprozess, Studienauswahl, Qualitätsbewertung und Synthese.
A10: 00_ReadMe | B10: Erläuterung der Struktur, Begriffe und verwendeten Kodierungen der digitalen SLR-Dokumentation. | C10: Orientierung innerhalb der Arbeitsmappe und Abgrenzung der einzelnen Dokumentationsschritte.
A11: 01_Search_Log | B11: Dokumentation der systematischen Suchläufe sowie ergänzender Recherche-, Citation-Discovery- und Snowballing-Aktivitäten einschließlich Suchquelle, Suchstring, Trefferzahl und Sichtungsumfang. | C11: Nachvollziehbarkeit der Literaturidentifikation und des Umfangs der gesichteten Ergebnislisten.
A12: 02_Screening | B12: Dokumentation der identifizierten Publikationen und ihrer Einordnung als Include, Exclude oder Background einschließlich Screeninginformationen und Ausschlussgründen. | C12: Nachvollziehbarkeit der Studienauswahl und der Trennung zwischen Synthesekorpus und Hintergrundliteratur.
A13: 03_Extraction | B13: Standardisierte Extraktion der 113 eingeschlossenen Primärstudien entlang der SLR-Forschungsfragen. | C13: Vergleichbare Erfassung der für die Synthese relevanten Studienmerkmale, Methoden und Ergebnisse.
A14: 04_Quality_Assessment | B14: Qualitätsbewertung der 113 eingeschlossenen Primärstudien anhand von acht Kriterien. | C14: Einordnung der methodischen und berichtsbezogenen Qualität der berücksichtigten Evidenz.
A15: 05_RQ_Synthesis | B15: Forschungsfragenorientierte Evidenzeinträge mit Kernaussagen, Fundstellen und analytischer Zuordnung. | C15: Grundlage der quellenübergreifenden narrativen und deskriptiven Synthese.
A17: Hinweise zur Suchdokumentation
A18: Aspekt | B18: Dokumentation
A19: Systematische Suchquellen | B19: Die systematische Literatursuche wurde über IEEE Xplore, ACM Digital Library, SpringerLink und arXiv durchgeführt.
A20: Explorative und ergänzende Recherche | B20: Google Scholar, Litmaps, Elicit, SciSpace und Connected Papers wurden für die explorative Vorrecherche, Citation Discovery sowie das Backward und Forward Snowballing eingesetzt. Diese Werkzeuge wurden nicht als eigenständige systematische Datenbanken behandelt.
A21: Treffer_raw | B21: Gesamtzahl der von der jeweiligen Suchquelle für den dokumentierten Suchlauf angezeigten Treffer.
A22: Treffer_gesichtet | B22: Anzahl der Ergebnisse, die innerhalb der jeweiligen Ergebnisliste tatsächlich betrachtet wurden.
A23: Sichtungsumfang | B23: „vollständig“ bedeutet, dass die gesamte Ergebnisliste gesichtet wurde. Bei sehr großen Treffermengen kann eine dokumentierte, nach Relevanz sortierte Teilmenge gesichtet worden sein.
A24: Weiteres Screening | B24: Potenziell relevante Publikationen wurden anschließend in das mehrstufige Studienauswahlverfahren übernommen.
A26: Hinweise zum Screening
A27: Aspekt | B27: Dokumentation
A28: Vorgehen | B28: Das Screening erfolgte mehrstufig. Nach einer Prüfung von Titel, Abstract und Keywords wurden bei unklarer oder potenzieller Relevanz weitere Publikationsabschnitte berücksichtigt.
A29: Volltextprüfung | B29: Für eingeschlossene Studien wurden die für die jeweiligen Forschungsfragen relevanten Inhalte des Volltexts vertieft geprüft. Die Volltextprüfung ist nicht als lineare Lektüre jeder einzelnen Seite zu verstehen, sondern als gezielte Auswertung insbesondere der relevanten Abschnitte zu Methodik, Architektur, Planung, Validierung, Evaluation, Ergebnissen und Limitationen.
A30: Include | B30: Die Publikation ist Bestandteil des Synthesekorpus der SLR.
A31: Background | B31: Die Publikation dient der begrifflichen, theoretischen oder methodischen Einordnung, ist jedoch nicht Bestandteil des Primärstudienkorpus der Synthese.
A32: Exclude | B32: Die Publikation wurde nicht in das Synthesekorpus aufgenommen. Ausschlussgründe sind im Screening dokumentiert.
A34: Hinweise zur Datenextraktion und Synthese
A35: Aspekt | B35: Dokumentation
A36: Datenextraktion | B36: Die 113 eingeschlossenen Primärstudien wurden mithilfe einer standardisierten, an den SLR-Forschungsfragen ausgerichteten Extraktionsmatrix ausgewertet.
A37: Fehlende Angaben | B37: Nicht berichtete oder aus einer Publikation nicht eindeutig ableitbare Informationen wurden nicht durch eigene Annahmen ergänzt, sondern entsprechend gekennzeichnet.
A38: RQ-Synthese | B38: Eine Studie kann mehrere Syntheseeinträge aufweisen, wenn sie Evidenz zu unterschiedlichen Forschungsfragen oder thematischen Kategorien liefert.
A39: Fundstellen | B39: Quellenbezogene Kernaussagen wurden mit Fundstellen dokumentiert, um die Rückverfolgbarkeit der Synthese zu den jeweiligen Primärstudien zu gewährleisten.
A40: Analytische Einordnung | B40: Quellenbezogene Aussagen und eigene analytische Einordnungen wurden getrennt dokumentiert.
A42: Hinweise zur Qualitätsbewertung
A43: Aspekt | B43: Dokumentation
A44: Bewertungsumfang | B44: Alle 113 eingeschlossenen Primärstudien wurden anhand von acht Qualitätskriterien bewertet.
A45: Bewertungsskala | B45: Je Kriterium wurden 0 Punkte bei fehlender beziehungsweise nicht nachvollziehbarer Erfüllung, 0,5 Punkte bei teilweiser Erfüllung und 1 Punkt bei vollständiger Erfüllung vergeben.
A46: Verwendung | B46: Der Gesamtscore dient der Einordnung der methodischen und berichtsbezogenen Qualität. Die Qualitätsbewertung wurde nicht als automatisches Ausschlusskriterium verwendet.
A48: Abgrenzung der digitalen Dokumentation
A49: Aspekt | B49: Dokumentation
A50: Haupttext und digitaler Anhang | B50: Die methodische Begründung des Vorgehens, die Forschungsfragen, die Ein- und Ausschlusskriterien sowie die zusammengefassten Ergebnisse werden im Haupttext der Masterarbeit beschrieben. Diese Arbeitsmappe dient der detaillierten Nachvollziehbarkeit der einzelnen Such-, Auswahl-, Extraktions-, Bewertungs- und Syntheseschritte.
A51: Projektseiten und Repositories | B51: Referenzierte Projektseiten und offizielle GitHub-Repositories wurden ausschließlich zur Ergänzung von Architektur- und Implementierungsinformationen herangezogen und nicht als eigenständige Primärstudien behandelt.

Sheet 01_Search_Log
A1: Search_ID | B1: Datum | C1: Quelle_Typ | D1: Datenbank_Quelle | E1: Suchstring_oder_Methode | F1: Suchblock | G1: Filter | H1: Treffer_raw | I1: Treffer_gesichtet | J1: Screening_Umfang | K1: Screening_Regel | L1: Exportiert | M1: Duplikate_entfernt | N1: Golden_Set_gefunden | O1: Status | P1: Notizen
A2: IEEE-01 | B2: 46156 | C2: Datenbank | D2: IEEE Xplore | E2: (("LLM agent" OR "language agent" OR "large language model agent") AND ("planning" OR "reasoning" OR "tool use" OR "autonomous agent")) | F2: LLM-Agenten / Planung / Reasoning / Tool Use | G2: 2022–2026 | H2: 126 | I2: 126 | J2: vollständig | K2: Vollständige Sichtung der Ergebnisliste | L2: 18 | M2: 0 | N2: Teilweise | O2: Fertig | P2: Conferences: 102; Journals: 16; Early Access Articles: 5. Titel-/Abstract-Screening noch durchführen.
A3: IEEE-02 | B3: 46156 | C3: Datenbank | D3: IEEE Xplore | E3: (("web agent" OR "web automation" OR "web navigation") AND ("large language model" OR "LLM" OR "language agent")) | F3: Webagenten / Webnavigation / Webautomation | G3: 2022–2026 | H3: 7 | I3: 7 | J3: vollständig | K3: Vollständige Sichtung der Ergebnisliste | L3: 2 | M3: 1 | N3: Teilweise | O3: Fertig | P3: Conferences: 6; Journals: 1. Prüfen, ob der Filter 2022–2026 tatsächlich angewendet wurde.
A4: IEEE-03 | B4: 46156 | C4: Datenbank | D4: IEEE Xplore | E4: (("LLM agent" OR "language agent" OR "web agent") AND ("replanning" OR "reflection" OR "verification" OR "validation" OR "feedback")) | F4: Replanning / Reflection / Verification / Validation / Feedback | G4: 2022–2026 | H4: 87 | I4: 87 | J4: vollständig | K4: Vollständige Sichtung der Ergebnisliste | L4: 7 | M4: 3 | N4: Teilweise | O4: Fertig | P4: Conferences: 68; Journals: 12; Early Access Articles: 4. Titel-/Abstract-Screening noch durchführen.
A5: IEEE-04 | B5: 46156 | C5: Datenbank | D5: IEEE Xplore | E5: (("LLM agent" OR "web agent") AND ("success rate" OR "benchmark" OR "token cost" OR "latency" OR "runtime" OR "efficiency")) | F5: Evaluation / Benchmarks / Tokenkosten / Laufzeit / Effizienz | G5: 2022–2026 | H5: 101 | I5: 101 | J5: vollständig | K5: Vollständige Sichtung der Ergebnisliste | L5: 7 | M5: 6 | N5: Teilweise | O5: Fertig | P5: Conferences: 80; Journals: 16; Magazines: 3; Early Access Articles: 2. Titel-/Abstract-Screening noch durchführen.
A6: ACM-01 | B6: 46156 | C6: Datenbank | D6: ACM Digital Library | E6: (("LLM agent" OR "language agent" OR "large language model agent") AND ("planning" OR "reasoning" OR "tool use" OR "autonomous agent")) | F6: LLM-Agenten / Planung / Reasoning / Tool Use | G6: 2022–2026; Englisch; Volltext verfügbar | H6: 819 | I6: 500 | J6: effort-bounded | K6: Nach Relevanz sortierte Ergebnisliste, erste 500 Treffer gesichtet | L6: 20 | M6: 0 | N6: Teilweise | O6: Fertig | P6: Allgemeine Suche zu LLM-Agenten, Planung, Reasoning und Tool Use. Titel-/Abstract-Screening durchführen. --> ersten 150 wurden angesehen
A7: ACM-02 | B7: 46156 | C7: Datenbank | D7: ACM Digital Library | E7: (("web agent" OR "web automation" OR "web navigation") AND ("large language model" OR "LLM" OR "language agent")) | F7: Webagenten / Webnavigation / Webautomation | G7: 2022–2026; Englisch; Volltext verfügbar | H7: 184 | I7: 184 | J7: vollständig | K7: Vollständige Sichtung der Ergebnisliste | L7: 14 | M7: 5 | N7: Teilweise | O7: Fertig | P7: Spezifische Suche zu Webagenten, Webnavigation und Webautomation. Titel-/Abstract-Screening durchführen.
A8: ACM-03 | B8: 46156 | C8: Datenbank | D8: ACM Digital Library | E8: (("LLM agent" OR "language agent" OR "web agent") AND ("replanning" OR "reflection" OR "verification" OR "validation" OR "feedback")) | F8: Replanning / Reflection / Verification / Validation / Feedback | G8: 2022–2026; Englisch; Volltext verfügbar | H8: 847 | I8: 500 | J8: effort-bounded | K8: Nach Relevanz sortierte Ergebnisliste, erste 500 Treffer gesichtet | L8: 11 | M8: 19 | N8: Teilweise | O8: Fertig | P8: Suche zu Replanning, Reflection, Verification, Validation und Feedback. Titel-/Abstract-Screening durchführen.
A9: ACM-04 | B9: 46156 | C9: Datenbank | D9: ACM Digital Library | E9: (("LLM agent" OR "web agent") AND ("success rate" OR "benchmark" OR "token cost" OR "latency" OR "runtime" OR "efficiency")) | F9: Evaluation / Benchmarks / Tokenkosten / Laufzeit / Effizienz | G9: 2022–2026; Englisch; Volltext verfügbar | H9: 772 | I9: 500 | J9: effort-bounded | K9: Nach Relevanz sortierte Ergebnisliste, erste 500 Treffer gesichtet | L9: 6 | M9: 21 | N9: Teilweise | O9: Fertig | P9: Suche zu Evaluation, Benchmarking und Effizienzmetriken. Titel-/Abstract-Screening durchführen.
A10: ARXIV-01 | B10: 46156 | C10: Preprint | D10: arXiv | E10: (("LLM agent" OR "language agent" OR "large language model agent") AND ("planning" OR "reasoning" OR "tool use" OR "autonomous agent")) | F10: LLM-Agenten / Planung / Reasoning / Tool Use | G10: 2022–2026; Englisch; Preprints erlaubt | H10: 1754 | I10: 500 | J10: effort-bounded | K10: Nach Relevanz sortierte Ergebnisliste, erste 500 Treffer gesichtet | L10: 49 | M10: 25 | N10: Teilweise | O10: Fertig | P10: Allgemeine arXiv-Suche zu LLM-Agenten, Planung, Reasoning und Tool Use. Titel-/Abstract-Screening durchführen
A11: ARXIV-02 | B11: 46156 | C11: Preprint | D11: arXiv | E11: (("web agent" OR "web automation" OR "web navigation") AND ("large language model" OR "LLM" OR "language agent")) | F11: Webagenten / Webnavigation / Webautomation | G11: 2022–2026; Englisch; Preprints erlaubt | H11: 221 | I11: 221 | J11: vollständig | K11: Vollständige Sichtung der Ergebnisliste | L11: 14 | M11: 37 | N11: Teilweise | O11: Fertig | P11: Spezifische arXiv-Suche zu Webagenten, Webnavigation und Webautomation. Titel-/Abstract-Screening durchführen.
A12: ARXIV-03 | B12: 46156 | C12: Preprint | D12: arXiv | E12: (("LLM agent" OR "language agent" OR "web agent") AND ("replanning" OR "reflection" OR "verification" OR "validation" OR "feedback")) | F12: Replanning / Reflection / Verification / Validation / Feedback | G12: 2022–2026; Englisch; Preprints erlaubt | H12: 1229 | I12: 500 | J12: effort-bounded | K12: Nach Relevanz sortierte Ergebnisliste, erste 500 Treffer gesichtet | L12: 15 | M12: 41 | N12: Teilweise | O12: Fertig | P12: arXiv-Suche zu Replanning, Reflection, Verification, Validation und Feedback. Titel-/Abstract-Screening durchführen.
A13: ARXIV-04 | B13: 46156 | C13: Preprint | D13: arXiv | E13: (("LLM agent" OR "web agent") AND ("success rate" OR "benchmark" OR "token cost" OR "latency" OR "runtime" OR "efficiency")) | F13: Evaluation / Benchmarks / Tokenkosten / Laufzeit / Effizienz | G13: 2022–2026; Englisch; Preprints erlaubt | H13: 1864 | I13: 500 | J13: effort-bounded | K13: Nach Relevanz sortierte Ergebnisliste, erste 500 Treffer gesichtet | L13: 6 | M13: 62 | N13: Teilweise | O13: Fertig | P13: arXiv-Suche zu Evaluation, Benchmarks, Tokenkosten, Laufzeit und Effizienzmetriken. Titel-/Abstract-Screening durchführen.
... A17: SPRINGER-04 | B17: 46156 | C17: Datenbank | D17: Springer Nature Link / SpringerLink | E17: (("LLM agent" OR "web agent") AND ("success rate" OR "benchmark" OR "token cost" OR "latency" OR "runtime" OR "efficiency")) | F17: Evaluation / Benchmarks / Tokenkosten / Laufzeit / Effizienz | G17: 2022–2026; Englisch; Advanced Search; Keywords/All fields; Articles/Conference Papers/Chapters prüfen | H17: 451 | I17: 451 | J17: vollständig | K17: Vollständige Sichtung der Ergebnisliste | L17: 3 | M17: 6 | N17: Teilweise | O17: Fertig | P17: Suche zu Evaluation, Benchmarks, Tokenkosten, Laufzeit und Effizienzmetriken. Relevante/unklare Treffer in Screening übernehmen.
A18: CD-SB-01 | B18: 46156 | C18: Snowballing / Citation Discovery | D18: Litmaps / ResearchRabbit / Connected Papers | E18: Seed-basierte Citation Discovery ausgehend von relevanten Ausgangspaper(n); Forward-/Backward-Beziehungen und thematisch/zitationale Nähe geprüft | F18: Snowballing / Citation Discovery | G18: kein Datenbanktreffer; gleiche Ein-/Ausschlusskriterien wie übrige Kandidaten; genaue Tool-Herkunft einzelner Kandidaten nicht vollständig rekonstruierbar | H18: >1000 | I18: 200 | J18: effort-bounded | K18: nach Relevanz sortierte in den verschiedenen Quellen | L18: 7 | M18: 2 | N18: Teilweise | O18: Fertig | P18: Unterstützende Citation-Discovery- und Snowballing-Recherche über Google Scholar, Litmaps, Elicit, SciSpace und Connected Papers, überwiegend über Litmaps. Die Werkzeuge dienten der Identifikation verwandter sowie zitierter und zitierender Arbeiten und wurden nicht als eigenständige systematische Datenbanken behandelt. Alle identifizierten Publikationen wurden separat anhand derselben Ein- und Ausschlusskriterien geprüft. Im Rahmen dieser ergänzenden Recherche wurden unter anderem WebArena und BrowserGym berücksichtigt. Über dort referenzierte Projekt- beziehungsweise GitHub-Seiten wurde anschließend WebArena Verified identifiziert und als potenziell relevante Quelle separat geprüft.
A19: COT-01 | B19: 46156 | C19: Explorative Vorrecherche / Background | D19: CoT-/Reasoning-Literatur | E19: Gezielte ergänzende Recherche zu Chain-of-Thought, Reasoning und Prompting als theoretischer Hintergrund | F19: CoT / Reasoning / Planning Background | G19: keine Datenbanksuche; unterstützende Literatur; nur bei direktem Bezug zu Agenten, Planung oder Replanning als SLR-Kandidat berücksichtigt | H19: >200 | I19: 200 | J19: effort-bounded | K19: nach Relevanz sortierte in den verschiedenen Quellen | L19: 9 | N19: Teilweise | O19: Fertig | P19: CoT-/Reasoning-Quellen wurden vor allem zur theoretischen Einordnung von Reasoning, Chain-of-Thought und Planung genutzt. Sie werden nicht als Primärstudien der SLR behandelt, sofern kein direkter Bezug zu LLM-Agenten, Webagenten, Tool Use, Planungshorizonten oder Replanning besteht.

Sheet Übersicht der Extraktion
A3: Zeilenbeschriftungen | B3: Anzahl von Search_ID
A4: Background | B4: 38
A5: Exclude | B5: 72
A6: Include | B6: 113
A7: Gesamtergebnis | B7: 223
A15: Zeilenbeschriftungen | B15: Anzahl von Search_ID
A16: ACM-01 | B16: 20
A17: ACM-02 | B17: 14
A18: ACM-03 | B18: 11
A19: ACM-04 | B19: 6
A20: ARXIV-01 | B20: 49
A21: ARXIV-02 | B21: 14
A22: ARXIV-03 | B22: 15
A23: ARXIV-04 | B23: 6
A24: CD-SB-01 | B24: 7
A25: COT explizit | B25: 1
A26: COT-01 | B26: 8
A27: IEEE-01 | B27: 18
... A35: Gesamtergebnis | B35: 223

Sheet 02_Screening
A1: Candidate_ID | B1: Study_ID | C1: Titel | D1: Autor_Jahr | E1: Jahr | F1: Venue/Quelle | G1: DOI/URL | H1: Publikationstyp | I1: Herkunft | J1: Search_ID | K1: Volltext_geprüft | L1: Entscheidung | M1: Ausschlussgrund | N1: Relevanz_RQ | O1: Seed_Paper | P1: Snowballing_Typ | Q1: Duplikat_von | R1: Notizen | S1: Hilfstool_Hinweis | T1: Methodische_Einordnung | U1: Recherchetool_Typ
A2: C001 | B2: S001 | C2: Plan-and-Act: Improving Planning of Agents for Long-Horizon Tasks | D2: Erdogan et al. | E2: 2025 | F2: arXiv | G2: https://arxiv.org/abs/2503.09572 | H2: Preprint | I2: Datenbank / Preprint | J2: ARXIV-01 | K2: Ja | L2: Include | N2: RQ2; RQ3; RQ4; RQ5; Gap | T2: wissenschaftliche Datenbank
A3: C002 | B3: S002 | C3: Why Reasoning Fails to Plan: A Planning-Centric Analysis of Long-Horizon Decision Making in LLM Agents | D3: Wang et al. | E3: 2026 | F3: arXiv | G3: arXiv:2601.22311v1; https://arxiv.org/abs/2601.22311 | H3: Preprint | I3: Datenbank | J3: ARXIV-01 | K3: Ja | L3: Include | N3: RQ3; RQ4; RQ5; Gap | O3: Nein | T3: wissenschaftliche Datenbank
A4: C003 | B4: S003 | C4: Revealing the Barriers of Language Agents in Planning | D4: Xie et al. | E4: 2025 | F4: NAACL-HLT 2025, Volume 1: Long Papers | G4: https://doi.org/10.18653/v1/2025.naacl-long.93; https://aclanthology.org/2025.naacl-long.93/ | H4: Conference Paper | I4: Datenbank | J4: ARXIV-01 | K4: Ja | L4: Include | N4: RQ2; RQ3; RQ5; Gap; Methodik | O4: Nein | R4: - Sehr relevant für Planungsgrenzen von LLM-/Language-Agenten, insbesondere Long-Horizon-Planung. - Analysiert Planning-Module, Constraints, Questions sowie episodic und parametric memory updating. - Nutzt Permutation Feature Importance zur Diagnose: Constraints werden zu wenig berücksichtigt, Question-Einfluss sinkt mit Planungshorizont. - Evaluiert auf BlocksWorld und TravelPlanner; Forschungslücke: keine direkte Webagentenstudie, aber stark übertragbar auf Webagenten-Planung und Evaluationsmetriken. | T4: wissenschaftliche Datenbank
A5: C004 | B5: S004 | C5: TREE-PLANNER: Efficient Close-loop Task Planning with Large Language Models | D5: Hu et al. | E5: 2024 | F5: ICLR 2024 / OpenReview | G5: https://openreview.net/forum?id=Glcsog6zOe; arXiv:2310.08582; https://arxiv.org/abs/2310.08582 | H5: Conference Paper | I5: Datenbank | J5: ARXIV-03 | K5: Ja | L5: Include | N5: RQ1; RQ2; RQ3; RQ4; RQ5; Gap | O5: Nein | R5: - Sehr relevant für closed-loop LLM-Planung, Replanning und Effizienzmetriken. - Architektur: Plan Sampling, Action Tree Construction und Grounded Deciding als hybrider vorgeplanter Suchraum mit online Auswahl. - Validierung/Replanning erfolgt environment-grounded über Beobachtungen, Fehlermeldungen, Backtracking und Neuauswahl am letzten gültigen Fork. - Evaluiert auf VirtualHome mit EXEC, Success Rate, GCR, Tokenkosten/$COST und NO.EC; Forschungslücke: keine direkte Webagenten-Evaluation und keine systematische Variation von Validierungsintervallen. | T5: wissenschaftliche Datenbank
A6: C005 | B6: S005 | C6: LLMPC: Large Language Model Predictive Control | D6: Maher | E6: 2025 | F6: arXiv | G6: arXiv:2501.02486v2; https://arxiv.org/abs/2501.02486 | H6: Preprint | I6: Datenbank | J6: ARXIV-01 | K6: Ja | L6: Include | N6: RQ3; RQ4; RQ5; Gap | O6: Nein | R6: - Hoch relevant für LLM-Planung als receding-horizon / MPC-artiger Zyklus mit Plan-Sampling, externer Bewertung, Teil-Ausführung und Replanning. - Architektur/Methode: LLM generiert K Kandidatenpläne, externe Kosten-/Constraint-Funktion wählt den besten Plan, danach iterative Verbesserung mit aktualisiertem Feedback. - Validierung erfolgt constraint-based durch externe Evaluation unerfüllter Constraints, insbesondere in Trip- und Meeting-Planning-Aufgaben. - Evaluiert mit Objective Ratio und Success Rate; Forschungslücke: keine systematische Messung von Tokenkosten, Laufzeit, Replan-Anzahl oder Validierungsintervallen. | T6: wissenschaftliche Datenbank
A7: C006 | B7: S006 | C7: Token-Budget-Aware LLM Reasoning | D7: Han et al. | E7: 2025 | F7: arXiv | G7: arXiv:2412.18547v4; https://arxiv.org/abs/2412.18547 | H7: Preprint | I7: Datenbank | J7: ARXIV-01 | K7: Ja | L7: Background | N7: RQ5; Gap; Methodik | O7: Nein | R7: - Background-Quelle zu CoT, Reasoning-Budget und Tokenkosten; nicht direkt zu Webagenten oder agentischer Planung. - Methode: TALE-EP schätzt ein Reasoning-Tokenbudget und setzt es im Prompt; TALE-PT internalisiert Budgetbewusstsein per SFT/DPO. - Relevant für Effizienzmetriken, Accuracy-Cost-Trade-off und die Frage, ob längeres Reasoning immer nötig ist. - Keine Laufzeitvalidierung, kein Replanning, keine interaktive Umgebung; eher nützlich für Ausblick und Effizienz-Diskussion. | S7: Priorität: C-Background; reduzierte Extraction ausreichend; Snowballing optional zu CoT/Reasoning-Kosten
A8: C007 | B8: S007 | C8: Think-on-Graph: Deep and Responsible Reasoning of Large Language Model on Knowledge Graph | D8: Sun et al. (2024) | E8: 2024 | F8: ICLR 2024 / OpenReview | G8: https://openreview.net/forum?id=nnVO1PvbTv; arXiv:2307.07697; https://arxiv.org/abs/2307.07697 | H8: Conference Paper | I8: Datenbank | J8: ARXIV-04 | K8: Ja | L8: Include | N8: RQ2; RQ3; RQ4; RQ5; Gap; Methodik | O8: Nein | R8: - Relevant als B-Supporting-Include für agentische Architektur, strukturierte Exploration und tiefe Multi-Hop-Reasoning-Prozesse, aber keine direkte Webagentenstudie. - Methode: LLM⊗KG-Paradigma mit LLM-Agent, Knowledge-Graph-Exploration, Beam Search, Search/Prune-Schritten und iterativer Reasoning-Sufficiency-Prüfung. - Validierung/Fehlerbehandlung: explizite reasoning paths ermöglichen Traceability und Knowledge Correctability; LLM entscheidet nach Iterationen, ob genug Information vorhanden ist. - Evaluation auf 9 KGQA/Open-Domain/Fact-Checking-Datasets mit Hits@1; untersucht Suchbreite/-tiefe, Pruning-Tools und LLM-Call-Kosten; Forschungslücke: Übertragbarkeit auf Webagenten, Browserumgebungen und Replanning während realer Handlungsausführung bleibt offen.
A9: C008 | B9: S008 | C9: Plan-on-Graph: Self-Correcting Adaptive Planning of Large Language Model on Knowledge Graphs | D9: Chen et al. (2024) | E9: 2024 | F9: NeurIPS 2024 / arXiv | G9: arXiv:2410.23875; https://arxiv.org/abs/2410.23875; https://github.com/liyichen-cly/PoG | H9: Conference Paper | I9: Datenbank | J9: ARXIV-04 | K9: Ja | L9: Include | N9: RQ2; RQ3; RQ4; RQ5; Gap; Methodik | O9: Nein | R9: - Relevant als starkes B-Supporting-Include für adaptive Planung, Self-Correction, Reflection und Memory, aber keine direkte Webagentenstudie. - Methode: Plan-on-Graph mit Task Decomposition, adaptiver Path Exploration, Memory Updating und Evaluation/Reflection auf Knowledge Graphs. - Validierung/Replanning: Reflection prüft, ob Informationen ausreichen oder ob fehlerhafte Reasoning Paths per Backtracking korrigiert werden müssen. - Evaluation auf CWQ, WebQSP und GrailQA mit Hits@1 sowie LLM Calls, Input/Output Tokens, Total Tokens und Laufzeit; Forschungslücke: Übertragbarkeit auf Webagenten, Browserinteraktion und reale Tool-/UI-Ausführung bleibt offen.
A10: C009 | B10: S009 | C10: LATCH: latency-bounded latent lookahead for constraint-safe web agents | D10: Li et al. (2026) | E10: 2026 | F10: Research Square | G10: https://doi.org/10.21203/rs.3.rs-8912469/v1 | H10: Preprint | I10: Preprint-Suchquelle | J10: ARXIV-02 | K10: Ja | L10: Include | N10: RQ2; RQ3; RQ4; RQ5; Gap; Methodik | O10: Nein | R10: - Sehr relevantes A-Core-Include zu LLM-basierten Webagenten, Lookahead-Planung, Constraint-Sicherheit und Effizienz unter Interaktionsbudgets. - Architektur: Action Proposal Module, Encoder, Hybrid SSM+Attention Dynamics, Typed Entity Memory, kalibrierter Critic und Beam-/Horizon-basierter Planner. - Planung/Validierung: simulate-then-select in latent space, schema-valide Kandidaten, short-horizon rollouts, constraint propagation und shared validators zur Reduktion ungültiger Aktionen. - Evaluation auf WebShop, Mind2Web und WebArena mit TSR, CVR, IAR, Tokens, latent evaluations, wall-time und selection error; Forschungslücke: Preprint noch nicht peer-reviewed und Fokus auf textbasierte DOM-/Tool-Interfaces, nicht multimodale Webagenten. | S10: aus vorhandenen Notizen/PDF geprüft; Priorität: A-Core-Include; Preprint-Status beachten; Snowballing prüfen zu WebArena, Mind2Web, WebShop, ReAct, Tree-of-Thoughts, world models und BrowserGym | T10: Preprint-Suchquelle
A11: C010 | B11: S010 | C11: WebOperator: Action-Aware Tree Search for Autonomous Agents in Web Environment | D11: Dihan et al. (2025) | E11: 2025 | F11: arXiv | G11: arXiv:2512.12692v1; https://arxiv.org/abs/2512.12692; https://kagnlp.github.io/WebOperator/ | H11: Preprint | I11: Datenbank | J11: ARXIV-02 | K11: Ja | L11: Include | N11: RQ1; RQ2; RQ3; RQ4; RQ5; Gap; Methodik | O11: Nein | R11: - Sehr relevantes A-Core-Include zu LLM-basierten Webagenten, Tree Search, Backtracking und sicherer Webautomation. - Architektur: action-aware Best-First Search mit dynamischem Action Space, Action Validation, Context Variation, Action Merging, Reward Model und Search Tree. - Validierung/Replanning: speculative Backtracking mit Snapshot-Validierung, checkpoint-based state jumping sowie pre-/post-execution heuristics für destructive actions. - Evaluation auf WebArena und WebVoyager; berichtet Success Rate, Suchbudget, Backtracking-Verteilung, Ablationen und generierte Aktionen; Forschungslücke: Umgang mit hochdynamischen Websites, Destructive-Action-Heuristiken und Reward-Model-Abhängigkeit bleibt offen. | T11: aus vorhandenen Notizen/PDF geprüft; Priorität: A-Core-Include; Snowballing prüfen zu LM-TS, LATS, WebPilot, Branch-n-Browse, WebRollback, WebGuard, InferAct, WebArena und WebVoyager | U11: Preprint-Suchquelle
A12: C011 | B12: S011 | C12: PATHWAYS: Evaluating Investigation and Context Discovery in AI Web Agents | D12: Arman et al. (2026) | E12: 2026 | F12: arXiv | G12: arXiv:2602.05354v2; https://arxiv.org/abs/2602.05354 | H12: Benchmark Paper / Preprint | J12: ARXIV-04 | K12: Ja | L12: Include | N12: RQ1; RQ3; RQ4; RQ5; Gap; Methodik | O12: Nein | R12: - Sehr relevantes A-Core-Include / Benchmark Paper zu AI-Webagenten, investigativer Kompetenz, verstecktem Kontext und evidenzbasierter Entscheidung. - Methode: PATHWAYS benchmark mit 250 mehrstufigen Entscheidungsaufgaben in Shopping-Admin- und Reddit-Moderation-Domänen auf WebArena-Basis. - Validierung/Fehleranalyse: misst Navigation–Discovery Gap, Surface Contradiction, Investigative Hallucination, Evidence Integration und Entscheidung unter Informationsasymmetrie. - Evaluation mit Investigation Accuracy, Reasoning Accuracy, Decision Accuracy, Proven Success Rate, Investigative Efficiency und Evidence Quality; Forschungslücke: Agenten brauchen explizite Mechanismen für Unsicherheit, Informationssuffizienz, Evidenzsuche und Judgement Override.
A13: C012 | B13: S012 | C13: Limits of Self-Correction in LLMs: An Information-Theoretic Analysis of Correlated Errors | D13: Brilliant (2026) | E13: 2026 | F13: Preprints.org | G13: https://doi.org/10.20944/preprints202601.0892.v1 | H13: Preprint | I13: Preprint-Suchquelle | J13: ARXIV-01 | K13: Ja | L13: Background | N13: RQ4; Gap; Methodik | O13: Nein | R13: - Background-Quelle zu Grenzen von Self-Correction, Self-Evaluation und korrelierten Fehlern bei LLMs; keine direkte Webagentenstudie. - Methode: theoretisch-informationstheoretische Analyse von Generator-/Evaluator-Fehlerkopplung sowie Vorschlag von context-separated external selection. - Relevant für Validierungsdiskussion: erklärt, warum reine Self-Critique/Reflection ohne externe Signale fehlschlagen oder falsches Vertrauen verstärken kann. - Keine Evaluation auf Webagenten-Benchmarks, keine Planungsausführung, kein Replanning in interaktiven Umgebungen; daher nur optional für Ausblick/Grenzen von Reflection nutzen.
A14: C013 | B14: S013 | C14: Reasoning Models Struggle to Control their Chains of Thought | D14: Yueh-Han et al. (2026) | E14: 2026 | F14: arXiv | G14: arXiv:2603.05706v1; https://arxiv.org/abs/2603.05706 | H14: Preprint | I14: Preprint-Suchquelle | J14: ARXIV-01 | K14: Ja | L14: Background | N14: RQ4; RQ5; Gap; Methodik | O14: Nein | R14: - Background-Quelle zu CoT-Monitoring, CoT-Controllability und Grenzen kontrollierbarer Reasoning-Spuren; keine direkte Webagentenstudie. - Methode: CoT-Control Evaluation Suite mit 14.076 Instanzen aus QA- und agentischen Benchmarks; misst, ob Modelle ihr CoT gezielt steuern können. - Relevant für Validierung: zeigt, dass Reasoning-Modelle ihre CoT meist deutlich schlechter kontrollieren als finale Outputs; längeres Reasoning, höhere Schwierigkeit und mehr Reasoning-Effort reduzieren Controllability. - Keine Webnavigation, keine Browserumgebung, kein Replanning und keine Webagenten-spezifischen Effizienzmetriken; daher vor allem für Diskussion zu CoT, Monitoring, Prompting und Validierungsgrenzen nutzbar.
A15: C014 | B15: S014 | C15: Why Language Models Hallucinate | D15: Kalai et al. (2025) | E15: 2025 | F15: arXiv | G15: arXiv:2509.04664v1; https://arxiv.org/abs/2509.04664 | H15: Preprint | I15: Preprint-Suchquelle | J15: ARXIV-03 | K15: Ja | L15: Background | N15: RQ4; RQ5; Gap; Methodik | O15: Nein | R15: - Background-Quelle zu Halluzinationen, Unsicherheit und Evaluationsanreizen bei Sprachmodellen; keine direkte Webagentenstudie. - Methode: theoretische Analyse von Halluzinationen als generative Fehler bzw. Is-It-Valid-Klassifikationsproblem in Pretraining und Post-training. - Relevant für Validierung/Evaluation: zeigt, dass binäre Benchmarks Guessing belohnen und Unsicherheit/IDK bestrafen, wodurch plausible falsche Aussagen bestehen bleiben. - Keine Agentenarchitektur, keine Webnavigation, kein Replanning und keine Webagentenmetriken; nutzbar für Diskussion zu Fehlerquellen, Unsicherheitsmodellierung und Evaluationsdesign.
A16: C015 | B16: S015 | C16: When Chain of Thought is Necessary, Language Models Struggle to Evade Monitors | D16: Emmons et al. (2025) | E16: 2025 | F16: arXiv | G16: arXiv:2507.05246v1; https://arxiv.org/abs/2507.05246 | H16: Preprint | I16: Preprint-Suchquelle | J16: ARXIV-01 | K16: Ja | L16: Background | N16: RQ3; RQ4; RQ5; Gap; Methodik | O16: Nein | R16: - Background-Quelle zu CoT-Monitoring, Monitorability und Grenzen von CoT-Evasion; keine direkte Webagentenstudie. - Methode: konzeptueller Rahmen mit CoT-as-rationalization vs. CoT-as-computation sowie Stress-Tests gegen CoT-Monitore. - Relevant für Validierung: zeigt, dass CoT bei schwierigen Aufgaben eher notwendig und damit monitorierbar wird, während einfache Aufgaben unfaithful rationalizations erlauben. - Evaluation mit GPQA-, Stealth- und Math-Proxy-Settings; untersucht Task Success, Monitor Recall, False Positive Rate und Evasion-Performance; Forschungslücke: keine Webnavigation, keine Browserumgebung und keine direkten Replanning-/Webagentenmetriken.
A17: C016 | B17: S016 | C17: Beyond the Imitation Game: Quantifying and extrapolating the capabilities of language models | D17: Srivastava et al. (2023) | E17: 2023 | F17: arXiv | G17: arXiv:2206.04615v3; https://arxiv.org/abs/2206.04615 | H17: Benchmark Paper / Preprint | I17: Preprint-Suchquelle | J17: ARXIV-03 | K17: Ja | L17: Exclude | M17: Zu allgemeines LLM-Benchmarking; keine direkte Webagentenstudie, keine Agentenarchitektur, keine Webnavigation, keine Planung/Replanning-Ausführung und keine Webagenten-spezifischen Evaluationsmetriken. | N17: Methodik | O17: Nein | R17: - Großes allgemeines Benchmark-Paper zu Sprachmodellfähigkeiten und Skalierung, aber ohne direkten Bezug zu Webagenten. - BIG-bench untersucht diverse Sprachmodellaufgaben, jedoch keine Browserinteraktion, Webautomation oder agentische Trajektorien. - Für die SLR höchstens indirekt als Kontext zu Benchmarking, Kalibrierung und Multi-Step-Aufgaben nutzbar. - Aufgrund fehlender direkter Relevanz für Webagenten, Planung, Replanning und prozessbezogene Webagentenmetriken nicht weiter extrahieren.
A18: C017 | B18: S017 | C18: WebATLAS: An LLM Agent with Experience-Driven Memory and Action Simulation | D18: Cheng et al. (2025) | E18: 2025 | F18: NeurIPS 2025 Workshop LAW 2025 / arXiv | G18: arXiv:2510.22732v2; https://arxiv.org/abs/2510.22732 | H18: Workshop Paper / Preprint | I18: Preprint-Suchquelle | J18: ARXIV-01 | K18: Ja | L18: Include | N18: RQ1; RQ2; RQ3; RQ4; RQ5; Gap; Methodik | O18: Nein | R18: - Sehr relevantes A-Core-Include zu LLM-basierten Webagenten, Long-Horizon-Webnavigation, Memory, Planning, Look-ahead Simulation und dynamischem Replanning. - Architektur: modularer Planner-Actor-Critic-Agent mit Working Memory, Cognitive Map und Semantic Memory; Figure 1 zeigt den Flow aus Observation/Abstractor, Planner, Actor, Critic, Memory Construction und LAS. - Planung/Validierung/Replanning: Actor generiert Kandidaten, Critic simuliert zukünftige Zustände über Cognitive Map, bewertet Risiko/Recoverability/Plan-Konsistenz und löst Replanning bei Abweichung zwischen erwarteter und beobachteter Observation aus. - Evaluation auf WebArena-Lite mit 63,0 % Success Rate gegenüber 53,9 % vorherigem SOTA; Forschungslücke: Tokenkosten, Laufzeit, Replan-Anzahl, Fehlerpositionen und Validierungsintervalle werden kaum systematisch gemessen. | T18: aus vorhandenen Notizen/PDF geprüft; Priorität: A-Core-Include; Snowballing prüfen zu WebArena-Lite, AgentOccam, Plan-and-Act, WebRL, WebPilot, AWM, ReAct, Reflexion, Tree of Thoughts, World Models und BrowserGym
A19: C018 | B19: S018 | C19: WebAgent-R1: Training Web Agents via End-to-End Multi-Turn Reinforcement Learning | D19: Wei et al. (2025) | E19: 2025 | F19: EMNLP 2025 / ACL Anthology | G19: https://aclanthology.org/2025.emnlp-main.401/; arXiv:2505.16421; https://arxiv.org/abs/2505.16421; https://github.com/weizhepei/WebAgent-R1 | H19: Conference Paper | I19: Datenbank | J19: ARXIV-02 | K19: Ja | L19: Include | N19: RQ1; RQ2; RQ3; RQ5; Gap; Methodik | O19: Nein | R19: - Sehr relevantes A-Core-Include zu LLM-basierten Webagenten, Multi-Turn-RL, Long-Horizon-Webtasks und Evaluation auf WebArena-Lite. - Methode: Behavior Cloning als Warm-up, danach end-to-end Multi-Turn Reinforcement Learning mit M-GRPO, Dynamic Context Compression und Parallel Trajectory Rollout. - Planung/Validierung: keine explizite Planrepräsentation und kein separates Replanning; Entscheidungsverhalten wird implizit über komplette Web-Trajektorien und binäre End-Rewards gelernt. - Evaluation auf WebArena-Lite und WebVoyager-OOD mit Success Rate, Trajectory Length und Number of Interactions; Forschungslücke: Tokenkosten, Laufzeit, Zwischenvalidierung, Replan-Anzahl und Fehlerpositionen werden nicht systematisch untersucht.
A20: C019 | B20: S019 | C20: ColorBrowserAgent: Complex Long-Horizon Browser Agent with Adaptive Knowledge Evolution | D20: Wang et al. (2026) | E20: 2026 | F20: arXiv / Preprint under review | G20: arXiv:2601.07262v2; https://arxiv.org/abs/2601.07262; https://github.com/MadeAgents/browser-agent.git | H20: Preprint | I20: Preprint-Suchquelle | J20: ARXIV-01 | K20: Ja | L20: Include | N20: RQ1; RQ2; RQ3; RQ4; RQ5; Gap; Methodik | O20: Nein | R20: - Sehr relevantes A-Core-Include zu Long-Horizon-Browseragenten, Site-Heterogenität, Decision Drift und stabilisierter Webautomation. - Architektur: ColorBrowserAgent mit Adaptor, Summarizer, Operator und Adaptive Knowledge Base; kombiniert Offline Knowledge Adaptation mit Online Execution Loop. - Validierung/Stabilisierung: Knowledge-Aligned Progressive Summarization komprimiert Interaktionshistorie, prüft geplante Aktionen gegen abgerufenes Expertenwissen und injiziert korrigierende Guidance bei Abweichungen. - Evaluation auf WebArena, WebChoreArena und industriellem Deployment mit Success Rate und User Satisfaction; Forschungslücke: Tokenkosten, Laufzeit, Validierungsfrequenz, Replan-Anzahl und explizite Drift-/Recovery-Metriken werden nicht systematisch gemessen.
A21: C020 | B21: S020 | C21: Agentic Test-Time Scaling for WebAgents | D21: Lee et al. (2026) | E21: 2026 | F21: arXiv | G21: arXiv:2602.12276v1; https://arxiv.org/abs/2602.12276 | H21: Preprint | I21: Preprint-Suchquelle | J21: ARXIV-02 | K21: Ja | L21: Include | N21: RQ2; RQ3; RQ4; RQ5; Gap; Methodik | O21: Nein | R21: - Sehr relevantes A-Core-Include zu agentischem Test-Time Scaling, adaptiver Validierung und Effizienzmetriken bei Long-Horizon-Webagenten. - Methode: CATTS nutzt per-step Candidate Sampling, semantisches Action-Clustering, Majority Vote, LLM-Arbiter und vote-derived uncertainty über Entropie bzw. Top-1/Top-2-Margin. - Validierung/Compute-Steuerung: zusätzliche Arbiter-Prüfung wird nur bei unsicheren, kontroversen Entscheidungsschritten eingesetzt; bei hohem Konsens reicht Majority Vote und zusätzliche Validierung kann sogar schaden. - Evaluation auf WebArena-Lite und GoBrowse mit Success Rate und Tokenverbrauch; Forschungslücke: kein globales Planning/Replanning-Modul, keine systematische Analyse von Fehlerpositionen, Recovery oder Validierungsintervallen über mehrere Schritte.
A22: C021 | B22: S021 | C22: SkillRL: Evolving Agents via Recursive Skill-Augmented Reinforcement Learning | D22: Xia et al. (2026) | E22: 2026 | F22: arXiv | G22: arXiv:2602.08234v1; https://arxiv.org/abs/2602.08234; https://github.com/aiming-lab/SkillRL | H22: Preprint | I22: Preprint-Suchquelle | J22: ARXIV-03 | K22: Ja | L22: Include | N22: RQ2; RQ3; RQ4; RQ5; Gap; Methodik | O22: Nein | R22: - Relevantes B-Supporting-Include als alternative Architekturklasse zu Memory- und RL-basierten LLM-Agenten; nicht direkt WebArena-/Browseragenten-zentriert, aber mit WebShop und Long-Horizon-Agentenbezug. - Methode: SkillRL destilliert erfolgreiche und fehlgeschlagene Trajektorien in eine hierarchische SKILLBANK mit General Skills und Task-Specific Skills, die während der Ausführung retrieved werden. - Planung/Fehlerbehandlung: Skills unterstützen mehrstufige Entscheidungsstrategien; Failed Trajectories werden in Failure Lessons überführt und die Skill Library wird während RL rekursiv weiterentwickelt. - Evaluation auf ALFWorld, WebShop und Search-Augmented-QA mit Success Rate, Score und Kontext-/Promptlänge; Forschungslücke: keine direkte WebArena-/BrowserGym-Evaluation, kein explizites Replanning-Modul und keine systematische Analyse von Laufzeit, Validierungsintervallen oder Fehlerpositionen.
A23: C022 | B23: S022 | C23: SkillEvo: An Experience Learning Framework with Reinforcement Learning for Skill Evolution | D23: Xu et al. (2026) | E23: 2026 | F23: ICLR 2026 / OpenReview | G23: https://openreview.net/forum?id=S1cIE9pe3k | H23: Conference Paper | I23: wissenschaftliche Datenbank | J23: ARXIV-03 | K23: Ja | L23: Include | N23: RQ1; RQ2; RQ3; RQ4; RQ5; Gap; Methodik | O23: Nein | R23: - Relevantes Include als alternative Skill-Evolution- und RL-Ansatzklasse für LLM-basierte Webagenten; direkter Bezug zu Long-Horizon-Webtasks und WebArena-Lite. - Methode: SkillEvo kombiniert WebGRPO mit RXERM für Reasoning-/Execution-Rewards, Dual-Uncertainty-Based Active Learning und SkillGenesis zur Umwandlung von Trajektorien in wiederverwendbare Skills. - Planung/Validierung: Skills werden in einem Skill Path Graph organisiert, wiederverwendet und zu Composite Skills weiterentwickelt; Validierung erfolgt über Execution Reward, Reasoning Reward, Format Reward und Skill-Verifikation, aber ohne klassisches Online-Replanning-Modul. - Evaluation auf WebArena-Lite mit Success Rate und Ablationen zu RXERM, Uncertainty Filtering und Skill Evolution; Forschungslücke: hohe Trainingskosten, Reward-Abhängigkeit, fragile Skill-Komposition sowie fehlende systematische Analyse von Tokenkosten, Laufzeit, Fehlerpositionen und Replanning-/Validierungsintervallen.
A24: C023 | B24: S023 | C24: Self-Guided Hierarchical Exploration for Generalist Foundation Model Web Agents | D24: Yang et al. (2025) | E24: 2025 | F24: NeurIPS 2025 | G24: https://yanqval.github.io/SAGE/ | H24: Conference Paper | I24: Datenbank | J24: ARXIV-02 | K24: Ja | L24: Include | N24: RQ1; RQ2; RQ3; RQ4; RQ5; Gap; Methodik | O24: Nein | R24: - Sehr relevantes A-Core-Include zu generalistischen Webagenten, Long-Horizon-Webtasks, hierarchischer Exploration und autonomer Skill-Akquisition. - Methode: SAGE kombiniert Pre-Exploration zum Aufbau einer Website-Strukturkarte, Top-Level Exploration mit selbstadaptivem Task-Curriculum und Low-Level Exploration mit MCTS, Multi-Action Policy, Outcome Evaluator und Step-DPO. - Planung/Validierung: MCTS unterstützt strukturierte Aktionssequenzsuche; ein gelernter Outcome Evaluator bewertet Erfolg/Misserfolg und Stepwise Learning nutzt Divergenzpunkte zwischen erfolgreichen und fehlgeschlagenen Trajektorien. - Evaluation auf WebVoyager und WebArena mit Success Rate, Ablationen, Schwierigkeit nach Task-Länge und Error Analysis; Forschungslücke: keine systematische Analyse von Tokenkosten, Laufzeit, Online-Replanning-Frequenz oder Validierungsintervallen während der Ausführung.
A25: C024 | B25: S024 | C25: A Survey on the Optimization of Large Language Model-based Agents | D25: Du et al. (2026) | E25: 2026 | F25: ACM Computing Surveys | G25: https://doi.org/10.1145/3789261; https://github.com/YoungDubbyDu/LLM-Agent-Optimization | H25: Survey | I25: wissenschaftliche Datenbank | J25: ACM-01 | K25: Teilweise | L25: Include | N25: RQ1; RQ2; RQ3; RQ4; RQ5; Gap; Methodik | O25: Nein | R25: - Sehr relevante zentrale Background-/Survey-Quelle zur Optimierung von LLM-basierten Agenten; keine einzelne Primärstudie zu Webagenten, aber stark für Taxonomie und theoretische Einordnung. - Methode/Struktur: kategorisiert Agentenoptimierung in parameter-driven Ansätze wie Fine-Tuning, RL, Hybrid Optimization sowie parameter-free Ansätze wie Experience-, Feedback-, Tool-, Retrieval- und Multi-Agent-basierte Optimierung. - Relevanz für Planung/Validierung: behandelt Trajectory Construction, Reward Function Design, Preference Alignment, Self-Reflection, External Feedback, Model-/Environment-based Evaluation und langfristige Agentenadaption. - Evaluation/Gap: fasst Frameworks, Datasets, Evaluation und Herausforderungen zusammen; besonders nützlich zur Begründung von Forschungslücken bei Long-Horizon Planning, Feedback-Design, Replanning, Effizienz und Evaluation von LLM-Agenten.
A26: C025 | B26: S025 | C26: Self-evolving Agents with reflective and memory-augmented abilities | D26: 梁学辰 et al. (2026) | E26: 2025 | F26: Anonymous submission / Preprint | G26: https://arxiv.org/abs/2409.00872, https://dl.acm.org/doi/10.1016/j.neucom.2025.130470 | H26: Preprint | I26: Preprint-Suchquelle | J26: ARXIV-01 | K26: Teilweise | L26: Include | N26: RQ2; RQ3; RQ4; RQ5; Gap; Methodik | O26: Nein | R26: - Relevantes B-Supporting-Include zu Reflection, Memory-Augmentation und self-evolving LLM-Agenten; kein A-Core-Webagentenpaper, aber mit AgentBench-, WebShop- und Mind2Web-Bezug. - Architektur: SAGE nutzt User-, Assistant- und Checker-Agenten, iterative Feedbackschleifen, Short-Term Memory, Long-Term Memory, Reflection und MemorySyntax auf Basis der Ebbinghaus-Vergessenskurve. - Validierung/Replanning: Checker bewertet Outputs und liefert Feedback; Reflection speichert Fehler-/Verbesserungshinweise, wodurch spätere Entscheidungen angepasst werden können, aber kein explizites Online-Replanning-Modul wie bei WebATLAS/WebOperator. - Evaluation auf AgentBench-Domänen wie OS, DB, KG, ALFWorld, WebShop und Mind2Web sowie HotpotQA, TriviaQA und Code-/Long-Context-Tasks; Forschungslücke: unklare Übertragbarkeit auf komplexe Browsersteuerung, begrenzte Analyse von Tokenkosten, Laufzeit, Replan-Anzahl und Validierungsintervallen.
A27: C026 | B27: S026 | C27: Instruction Tuning for Large Language Models: A Survey | D27: Zhang et al. (2026) | E27: 2026 | F27: ACM Computing Surveys | G27: https://doi.org/10.1145/3777411 | H27: Survey | I27: wissenschaftliche Datenbank | J27: ACM-01 | K27: Teilweise | L27: Exclude | M27: Zu allgemeiner Survey zu Instruction Tuning von LLMs; behandelt Prompting/Instruction Following nur indirekt und nicht als agentische Prompt-Engineering-Strategie für Webagenten, Planung, Replanning oder Validierung. | N27: Methodik | O27: Nein | R27: - Allgemeiner Survey zu Instruction Tuning, Instruction-Datasets, SFT, instruction-finetuned Models und Evaluation, aber ohne direkten Webagentenfokus. - Prompt Engineering ist für die SLR grundsätzlich relevant, dieses Paper behandelt jedoch primär Training auf Instruction-Output-Paaren und nicht ReAct-/Reflection-/Planning-Prompts in Agenten. - Keine konkrete Agentenarchitektur, keine Browserumgebung, keine Webnavigation, kein Replanning und keine Webagenten-spezifischen Effizienzmetriken. - Für deine Fragestellung durch spezifischere Agenten- und Webagentenquellen besser abgedeckt; daher nicht weiter extrahieren.
A28: C027 | B28: S027 | C28: Agent-Pro: Learning to Evolve via Policy-Level Reflection and Optimization | D28: Zhang et al. (2024) | E28: 2024 | F28: ACL 2024 / Proceedings of the 62nd Annual Meeting of the Association for Computational Linguistics (Long Papers) | G28: https://aclanthology.org/2024.acl-long.292/; https://github.com/zwq2018/Agent-Pro | H28: Conference Paper | I28: wissenschaftliche Datenbank | J28: ARXIV-01 | K28: Ja | L28: Include | N28: RQ1; RQ2; RQ3; RQ4; RQ5; Gap; Methodik | O28: Nein | R28: - Sehr relevantes A-/B+ Supporting-Include zu Long-Horizon-Agenten, Policy-Level Reflection, Belief-aware Decision-Making und Strategie-Evolution; keine direkte Webagentenstudie, aber stark auf Webagenten übertragbar. - Architektur: Agent-Pro nutzt Self-Belief und World-Belief für Entscheidungen sowie Behavioral Guidelines und World Modeling als optimierbare Policy-Bestandteile im Prompt. - Planung/Validierung/Replanning: reflektiert ganze Trajektorien, Beliefs und Endresultate statt einzelner Aktionen; prüft Korrektheit, Konsistenz und Rationalität von Beliefs und optimiert Policies über Verification und DFS-basierte Policy Evolution. - Evaluation auf Blackjack und Limit Texas Hold’em mit Win Rate, Chip Counts, Policy Payoff und Ablationen gegen Vanilla LLM, ReAct und Reflexion; Forschungslücke: keine Web-/Browserumgebung, Übertragbarkeit auf Webagenten, DOM-Aktionen, Tool-Feedback, Tokenkosten und Laufzeit bleibt offen.
A29: C028 | B29: S028 | C29: WebArena: A Realistic Web Environment for Building Autonomous Agents | D29: Zhou et al. (2024) | E29: 2024 | F29: ICLR 2024 | G29: arXiv:2307.13854; https://arxiv.org/abs/2307.13854; https://webarena.dev/ | H29: Conference Paper / Benchmark Paper | I29: wissenschaftliche Datenbank | J29: ARXIV-01 | K29: Ja | L29: Include | N29: RQ1; RQ2; RQ3; RQ4; RQ5; Gap; Methodik | O29: Nein | R29: - Zentrales A-Core-Include und Benchmark-Grundlagenpaper für LLM-basierte Webagenten, realistische Webumgebungen und Long-Horizon-Webtasks. - Methode/Umgebung: WebArena stellt self-hostbare Websites aus E-Commerce, Forum, GitLab/Softwareentwicklung und CMS bereit, ergänzt durch Tools wie Map, Calculator, Scratchpad und Knowledge Resources. - Planung/Validierung: Aufgaben sind high-level, mehrschrittig und funktional zu lösen; Evaluation prüft funktionale Korrektheit statt bloßer Aktionssequenz-Ähnlichkeit und umfasst auch unachievable tasks sowie Stop-/Failure-Verhalten. - Evaluation mit 812 Webtasks, End-to-End Task Success Rate und Human Baseline; GPT-4 erreicht nur 14,41 % gegenüber 78,24 % Human Performance; Forschungslücke: Bedarf an besserer Planung, Exploration, State Tracking, Failure Recovery, Replanning und Effizienzmetriken wie Tokenkosten/Laufzeit.
A30: C029 | B30: S029 | C30: Agentic Context Engineering: Evolving Contexts for Self-Improving Language Models | D30: Zhang et al. (2026) | E30: 2026 | F30: ICLR 2026 / arXiv | G30: arXiv:2510.04618v2; https://arxiv.org/abs/2510.04618; https://github.com/ace-agent/ace | H30: Conference Paper / Preprint | I30: Preprint-Suchquelle | J30: ARXIV-01 | K30: Ja | L30: Include | N30: RQ2; RQ3; RQ4; RQ5; Gap; Methodik | O30: Nein | R30: - Sehr relevantes B+/A-Supporting-Include zu agentischem Context Engineering, Memory, Reflection und Test-Time Adaptation; kein klassisches Webbrowser-Agentenpaper, aber stark relevant für selbstverbessernde Agenten. - Architektur: ACE nutzt Generator, Reflector und Curator, um aus Trajektorien, Execution Feedback und Fehlern strukturierte Context Playbooks mit Delta Context Items aufzubauen. - Validierung/Replanning: Reflector extrahiert Lessons aus Erfolgen und Fehlern; Curator integriert sie inkrementell, wodurch spätere Agentenausführungen besser gesteuert werden, ohne Modellgewichte zu ändern. - Evaluation auf AppWorld sowie Finanzbenchmarks mit Task Goal Completion, Scenario Goal Completion, Accuracy, Rollouts, Tokenkosten und Adaptation Latency; Forschungslücke: Übertragbarkeit auf echte Web-/Browseragenten, DOM-Aktionen, Replanning-Zeitpunkte und Feedbackqualität bleibt weiter zu prüfen.
A31: C030 | B31: S030 | C31: The Illusion of Diminishing Returns: Measuring Long Horizon Execution in LLMs | D31: Sinha et al. (2026) | E31: 2026 | F31: ICLR 2026 / arXiv | G31: arXiv:2509.09677v3; https://arxiv.org/abs/2509.09677 | H31: Conference Paper / Preprint | I31: Preprint-Suchquelle | J31: ARXIV-01 | K31: Teilweise | L31: Include | N31: RQ1; RQ3; RQ4; RQ5; Gap; Methodik | O31: Nein | R31: - Sehr relevantes A-/B+ Supporting-Include zu Long-Horizon Execution, Planungshorizonten und Fehlerfortpflanzung bei LLMs; keine direkte Webagentenstudie, aber stark übertragbar auf lange Webagenten-Trajektorien. - Methode: trennt Planning, Knowledge und Execution, indem Wissen und Plan explizit vorgegeben werden und nur die zuverlässige Ausführung über viele Schritte gemessen wird. - Validierung/Fehlermechanismus: zeigt Self-Conditioning, bei dem frühere Modellfehler im Kontext spätere Fehler wahrscheinlicher machen; Thinking/CoT kann diesen Effekt teilweise mindern und längere Ausführung ermöglichen. - Evaluation mit Step Accuracy, Turn Accuracy, Task Accuracy und Horizon Length; Forschungslücke: synthetisches Setting, keine direkte Browser-/DOM-Umgebung, aber sehr relevant für Metriken zu Long-Horizon-Webtasks, Fehlerpositionen, Recovery und Replanning.
A32: C031 | B32: S031 | C32: Measuring AI Ability to Complete Long Software Tasks | D32: Kwa et al. (2026) | E32: 2026 | F32: arXiv / METR Preprint | G32: arXiv:2503.14499v3; https://arxiv.org/abs/2503.14499 | H32: Preprint | I32: Preprint-Suchquelle | J32: ARXIV-01 | K32: Teilweise | L32: Include | N32: RQ1; RQ3; RQ4; RQ5; Gap; Methodik | O32: Nein | R32: - Sehr relevantes A-Supporting-Include als zentrale Methodikquelle für Long-Horizon-Evaluation, Taskdauer und agentische Zuverlässigkeit; keine direkte Webagentenstudie, aber stark übertragbar auf lange Webagenten-Tasks. - Methode: führt den Task Completion Time Horizon ein, insbesondere den 50 %-Time-Horizon als menschliche Bearbeitungszeit von Aufgaben, die KI-Agenten mit 50 % Erfolgswahrscheinlichkeit lösen. - Evaluation/Validierung: kombiniert HCAST, RE-Bench und SWAA mit Human Baselines, Agent Success Rates, logistischer Modellierung und qualitativer Fehleranalyse zu Planung/Tool Choice, Premature Abandonment und Repeating Failed Actions. - Forschungslücke: Webagenten-Benchmarks sollten nicht nur Success Rate, sondern auch Aufgabenlänge, menschliche Zeitäquivalente, Zuverlässigkeit bei längeren Tasks, Recovery-Fähigkeit und externe Validität messen.
A33: C032 | B33: S032 | C33: In-context Learning and Induction Heads | D33: Olsson et al. (2022) | E33: 2022 | F33: Transformer Circuits Thread / Anthropic | G33: https://transformer-circuits.pub/2022/in-context-learning-and-induction-heads/ | H33: Research Article / Technical Report | I33: Datenbank | J33: ARXIV-03 | K33: Teilweise | L33: Background | N33: RQ1; RQ3; Gap; Methodik | O33: Nein | R33: - Wichtige Background-Quelle zum mechanistischen Verständnis von In-Context Learning in Transformer-Modellen; keine direkte Webagentenstudie. - Methode/Beitrag: untersucht Induction Heads als mögliche Mechanismen, mit denen Transformer Muster im Kontext erkennen und fortsetzen können. - Relevanz indirekt für Agenten: erklärt, warum Prompting, Few-shot-Beispiele, Kontextverläufe und Memory-ähnliche Informationen Agentenverhalten beeinflussen können. - Keine direkte Behandlung von Webnavigation, Agentenarchitekturen, Planning, Replanning oder Webagenten-Evaluationsmetriken; daher nur als theoretischer Hintergrund nutzen.
A34: C033 | B34: S033 | C34: The Illusion of Thinking: Understanding the Strengths and Limitations of Reasoning Models via the Lens of Problem Complexity | D34: Shojaee et al. (2025) | E34: 2025 | F34: arXiv / Apple | G34: arXiv:2506.06941v3; https://arxiv.org/abs/2506.06941 | H34: Preprint | I34: Preprint-Suchquelle | J34: ARXIV-03 | K34: Teilweise | L34: Include | N34: RQ3; RQ4; RQ5; Gap; Methodik | O34: Nein | R34: - Relevantes B-Supporting-Include zu Grenzen von Large Reasoning Models, Chain-of-Thought/Thinking, Planning-Komplexität und Reasoning Collapse; keine direkte Webagentenstudie. - Methode: kontrollierbare Puzzle-Umgebungen wie Tower of Hanoi, Checker Jumping, River Crossing und Blocks World erlauben systematische Variation von Problemkomplexität und Analyse von Reasoning Traces. - Validierung/Fehleranalyse: zeigt Overthinking bei einfachen Aufgaben, spätes Finden korrekter Lösungen bei mittlerer Komplexität und Accuracy Collapse mit Fixierung auf frühe Fehler bei hoher Komplexität; explizite Algorithmen verbessern die Ausführung kaum. - Evaluation mit Accuracy, Pass@k, Inference Compute Budget, Thinking Tokens und Position korrekter/inkorrekter Lösungen im Thought Trace; Forschungslücke: Übertragbarkeit auf Webagenten, Browseraktionen, DOM-Zustände, Recovery und echtes Replanning bleibt offen.
A35: C034 | B35: S034 | C35: Chain of Thoughtlessness? An Analysis of CoT in Planning | D35: Stechly et al. (2025) | E35: 2025 | F35: NeurIPS 2024 / arXiv | G35: arXiv:2405.04776v3; https://arxiv.org/abs/2405.04776 | H35: Conference Paper / Preprint | I35: Preprint-Suchquelle | J35: ARXIV-01 | K35: Teilweise | L35: Background | N35: RQ3; RQ4; Gap; Methodik | O35: Nein | R35: - Relevante Background-Quelle zu Chain-of-Thought und Grenzen von CoT bei Planning-Aufgaben; keine direkte Webagentenstudie. - Methode: untersucht CoT-Prompting in Blocksworld sowie skalierbaren Varianten von CoinFlip, LastLetterConcatenation und mehrstufiger Arithmetik. - Relevanz für Planung: zeigt, dass CoT-Verbesserungen stark von sehr spezifischen Prompts abhängen und bei größeren bzw. leicht veränderten Instanzen schnell einbrechen. - Forschungslücke: CoT allein reicht nicht für robuste Long-Horizon-Planung, Validierung oder Replanning; Webagenten benötigen zusätzliche Mechanismen wie State Tracking, Tool-Feedback und explizite Fehlerprüfung.
A36: C035 | B36: S035 | C36: How Language Model Hallucinations Can Snowball | D36: Zhang et al. (2023) | E36: 2023 | F36: arXiv | G36: arXiv:2305.13534v1; https://arxiv.org/abs/2305.13534 | H36: Preprint | I36: Preprint-Suchquelle | J36: ACM-03 | K36: Teilweise | L36: Include | N36: RQ3; RQ4; RQ5; Gap; Methodik | O36: Nein | R36: - Relevantes B-Supporting-Include zu Fehlerfortpflanzung, Hallucination Snowballing und Konsistenzdruck in Sprachmodellen; keine direkte Webagentenstudie, aber stark auf Long-Horizon-Agenten übertragbar. - Methode: konstruiert QA-Datasets zu Primality Testing, Senator Search und Graph Connectivity, bei denen Modelle früh eine Antwort committen und anschließend falsche Begründungen erzeugen können. - Validierung/Fehlermechanismus: zeigt, dass Modelle viele eigene falsche Folgebehauptungen isoliert erkennen können, sie aber im Kontext einer vorherigen falschen Antwort dennoch erzeugen; relevant für Zwischenprüfung, Backtracking und Replanning. - Evaluation mit Error Rate, Snowballed Hallucination Rate und separaten Verification Questions; Forschungslücke: Übertragung auf Webagenten, DOM-Zustände, Tool-Feedback, Aktionsfehler und prozessbezogene Recovery-Metriken bleibt offen.
A37: C036 | B37: S036 | C37: Generalizable Long-Horizon Manipulations with Large Language Models | D37: Zhou et al. (2023) | E37: 2023 | F37: arXiv | G37: arXiv:2310.02264v1; https://arxiv.org/abs/2310.02264; https://object814.github.io/Task-Condition-With-LLM/ | H37: Preprint | I37: Preprint-Suchquelle | J37: ARXIV-01 | K37: Ja | L37: Include | N37: RQ2; RQ3; RQ4; RQ5; Gap; Methodik | O37: Nein | R37: - Relevantes B-Supporting-Include aus der Robotik zu Long-Horizon-Manipulation, Task Conditions und strukturierter Ausführung; keine direkte Webagentenstudie, aber methodisch gut übertragbar. - Architektur: LLM generiert und generalisiert primitive Task Conditions mit relevanten Objekten, Pre-conditions, Post-conditions und erlaubten Kollisionen; DMPs erzeugen Low-Level-Trajektorien. - Planung/Validierung/Replanning: rekursive Precondition Satisfaction erzeugt notwendige Zwischentasks; während der Ausführung werden Umweltzustände und Kollisionen geprüft und Trajektorien bei unerwünschten Kollisionen angepasst. - Evaluation in PyBullet und Real-World-Setup mit Success Rates für primitive Tasks, Long-Horizon Tasks sowie Generalisierung auf neue Objekte und neue primitive Tasks; Forschungslücke: domänenspezifisch für Robotik, keine Web-/DOM-Umgebung, keine Tokenkosten/Laufzeit und keine Webagenten-spezifischen Recovery-Metriken.
A38: C037 | B38: S037 | C38: GSM-∞: How Do your LLMs Behave over Infinitely Increasing Reasoning Complexity and Context Length? | D38: Zhou et al. (2025) | E38: 2025 | F38: ICML 2025 / PMLR 267 | G38: https://infini-ai-lab.github.io/gsm_infinite/ | H38: Conference Paper / Benchmark Paper | I38: wissenschaftliche Datenbank | J38: ARXIV-01 | K38: Teilweise | L38: Include | N38: RQ1; RQ3; RQ5; Gap; Methodik | O38: Nein | R38: - Sehr relevantes A-/B+ Supporting-Include als Methodik- und Benchmark-Quelle zu Long-Context Reasoning, Reasoning-Komplexität und Evaluationsskalierung; keine direkte Webagentenstudie. - Methode: GSM-∞ generiert kontrollierbare mathematische Reasoning-Probleme über Computational Graphs mit variabler Operationsanzahl, Kontextlänge und schwer unterscheidbarem Noise. - Relevanz für Planungshorizont/Evaluation: trennt Long-Context-Fähigkeit von tatsächlicher mehrschrittiger Reasoning-Komplexität und zeigt Performance-Abfall mit zunehmender Komplexität und Kontextlänge. - Evaluation mit Accuracy, AUC über Operationsanzahl, Kontextlängen 0/8K/16K/32K, Noise-Ablationen, RAG-Vergleich und repeated sampling; Forschungslücke: Übertragbarkeit auf Webagenten, Browserzustände, Tool-Feedback, Replanning und prozessbezogene Fehler-/Recovery-Metriken bleibt offen.
A39: C041 | B39: S038 | C39: Dynamic Cheatsheet: Test-Time Learning with Adaptive Memory | D39: Suzgun et al. (2026) | E39: 2026 | F39: EACL 2026 / Proceedings of the 19th Conference of the European Chapter of the Association for Computational Linguistics | G39: https://github.com/suzgunmirac/dynamic-cheatsheet | H39: Conference Paper | I39: wissenschaftliche Datenbank | J39: ARXIV-01 | K39: Teilweise | L39: Include | N39: RQ2; RQ3; RQ4; RQ5; Gap; Methodik | O39: Nein | R39: - Sehr relevantes A-/B+ Supporting-Include zu adaptiver Memory, Test-Time Learning und selbstkuratierter Strategie-Speicherung; keine direkte Webagentenstudie, aber stark auf LLM-Agenten übertragbar. - Architektur: Dynamic Cheatsheet nutzt Generator, Memory Curator und optional Retriever; DC-Cu kuratiert kumulative Memory, DC-RS kombiniert Retrieval historischer Beispiele mit Memory-Synthese. - Planung/Validierung: speichert kompakte, wiederverwendbare Strategien, Code-Snippets und Fehlerhinweise statt vollständiger Transkripte; fehlerhafte oder ineffiziente Memory-Einträge können überarbeitet oder entfernt werden. - Evaluation auf AIME, Game of 24, GPQA-Diamond, Math Equation Balancer und MMLU-Pro mit Accuracy-Vergleichen gegen Baseline, Empty Memory, Full History und Dynamic Retrieval; Forschungslücke: Übertragung auf Webagenten, Browser-/DOM-Zustände, Replanning, Tool-Feedback, Tokenkosten und prozessbezogene Fehlerindikatoren bleibt offen.
... A48: C050 | B48: S047 | C48: Exploring LLM-Based Agents for Root Cause Analysis | D48: Roy et al. (2024) | E48: 2024 | F48: FSE Companion 2024 / Companion Proceedings of the 32nd ACM International Conference on the Foundations of Software Engineering | G48: https://doi.org/10.1145/3663529.3663841 | H48: Conference Paper / Empirical Study | I48: wissenschaftliche Datenbank | J48: ACM-01 | K48: Teilweise | L48: Include | N48: RQ2; RQ3; RQ4; RQ5; Gap; Methodik | O48: Nein | R48: - Sehr relevantes B+/A-Supporting-Include zu ReAct-basierten LLM-Agenten, dynamischer Informationssuche, Tool Use und Root Cause Analysis; keine direkte Webagentenstudie, aber stark auf agentische Diagnose- und Validierungsprozesse übertragbar. - Architektur: ReAct-Agent mit Planner, Incident-Details-Tool, Historical-Incidents-Retrieval, KBA Q/A Tool, KBA Planning Tool, Database Query Tool und Human Interaction Tool; Tools liefern Observations für weitere Reasoning-Schritte. - Validierung/Replanning: Agent nutzt Tool-Feedback und Fehlermeldungen zur Korrektur fehlgeschlagener Queries; Human-in-the-loop erlaubt Intervention, manuelle Verifikation und Guardrails; Paper betont Bedarf an Reflection, Long-Term Memory und Multi-Trial-Workflows für komplexe Fälle. - Evaluation auf Microsoft-Produktionsincident-Daten mit BLEU, ROUGE-L, METEOR, BERTScore sowie manueller Fehlerkodierung nach Correctness, Hallucination, Insufficient Evidence, Reasoning Error und Retrieval Error; Forschungslücke: keine Web-/Browserumgebung, aber sehr relevant für Prozessmetriken, Tool-Fehler, Fehlerfortpflanzung und simulierte Agentenumgebungen.
A49: C051 | B49: S048 | C49: Conversational Agents: From RAG to LTM | D49: Zhang et al. (2025) | E49: 2025 | F49: SIGIR-AP 2025 / ACM | G49: https://doi.org/10.1145/3767695.3769671 | H49: Tutorial | I49: wissenschaftliche Datenbank | J49: ACM-03 | K49: Teilweise | L49: Exclude | M49: Zu allgemeines Tutorial zu RAG und Long-Term Memory in conversational agents; keine direkte Webagentenstudie, keine Browsernavigation, kein konkretes Planning-/Replanning-System und keine Webagenten-spezifische Evaluation oder Effizienzmetrik. | O49: Nein | R49: - Behandelt RAG, Long-Term Memory, Memory-Architekturen, Memory Operations und Benchmarks wie LoCoMo/ZH-4O, aber primär als Tutorial/Überblick. - Relevanz für die SLR nur indirekt über Memory, Kontextretention und langfristige conversational agents; keine direkte Webautomation oder Webagentenarchitektur. - Keine zentrale Primärstudie mit eigenem Agentensystem, Browserumgebung, Replanning-Mechanismus oder Webagenten-Metriken. - Durch spezifischere Quellen zu Memory, Reflection, Agentenevaluation und Effizienz bereits besser abgedeckt; daher keine weitere Extraction nötig.
A50: C052 | B50: S049 | C50: A Large Language Model Enhanced Conversational Recommender System | D50: Feng et al. (2023) | E50: 2023 | F50: arXiv / Preprint | G50: arXiv:2308.06212 | H50: Preprint | I50: Preprint-Suchquelle | J50: ARXIV-01 | K50: Teilweise | L50: Exclude | M50: Zu domänenspezifisches Paper zu conversational recommender systems; keine direkte Webagentenstudie, keine Browsernavigation, keine Webautomation, kein Long-Horizon-Webtask und kein explizites Replanning oder Webagenten-spezifische Effizienzmetrik. | N50: RQ2; RQ3; RQ5 | O50: Nein | R50: - Behandelt LLMCRS als conversational recommender system mit LLM als Controller, Sub-Task Detection, Model Matching, Expert Model Execution und Response Generation. - Relevanz für die SLR nur indirekt über agentenähnliche Aufgabenzerlegung und LLM-Controller-/Expert-Model-Architektur; keine Web-/Browserumgebung. - Keine konkrete Validierungs-, Fehlererkennungs- oder Replanning-Schleife während einer interaktiven Webaufgabe. - Evaluation auf GoRecDial und TG-ReDial mit HIT, MRR, NDCG, BLEU und Distinct; für Webagentenmetriken wie Success Rate, Tokenkosten, Laufzeit, Toolfehler oder Prozessfehler nur begrenzt nutzbar.
A51: C053 | B51: S050 | C51: Tool Learning in the Wild: Empowering Language Models as Automatic Tool Agents | D51: Shi et al. (2025) | E51: 2025 | F51: WWW 2025 / Proceedings of the ACM Web Conference 2025 | G51: https://doi.org/10.1145/3696410.3714825 | H51: Conference Paper | I51: wissenschaftliche Datenbank | J51: ARXIV-01 | K51: Teilweise | L51: Include | N51: RQ2; RQ3; RQ4; RQ5; Gap; Methodik | O51: Nein | R51: - Sehr relevantes B+/A-Supporting-Include zu Tool Learning, Tool-Use-Architektur und automatischer Tool-Integration; keine direkte Webagentenstudie, aber stark übertragbar auf toolbasierte Webagenten. - Architektur: AutoTools transformiert Tool-Dokumentationen automatisch in callable functions, prüft Syntax und Runtime-Korrektheit und baut daraus eine wiederverwendbare Function Library. - Planung/Validierung: LLM nutzt Tool Programming, um mehrere Funktionen über ausführbare Programme zu kombinieren; Integration Verification prüft Input-Output-Abhängigkeiten zwischen Tools, Fehler werden über Execution Feedback sichtbar. - Evaluation auf RestBench, ToolBench und AutoTools-Eval mit Success Rate, Path Rate, Precision, Pass Rate, Tokenverbrauch und Fehlerkategorien wie Selection Error, Argument Error und Parse Error; Forschungslücke: keine Browser-/DOM-Umgebung, aber sehr relevant für robuste Tool-Nutzung, Effizienz und dynamische Tool-Orchestrierung in Webagenten.
A52: C054 | B52: S051 | C52: Long Term Memory: The Foundation of AI Self-Evolution | D52: Jiang et al. (2025) | E52: 2025 | F52: arXiv | G52: arXiv:2410.15665v4; https://arxiv.org/abs/2410.15665 | H52: Preprint / Technical Report | I52: Preprint-Suchquelle | J52: ARXIV-01 | K52: Teilweise | L52: Include | N52: RQ1; RQ2; RQ3; RQ4; RQ5; Gap; Methodik | O52: Nein | R52: - Relevantes B-Supporting-Include zu Long-Term Memory, AI Self-Evolution, personalisierten Agenten und Multi-Agent-Collaboration; keine direkte Webagentenstudie, aber stark relevant für Memory-basierte Agentenarchitekturen. - Architektur/Ansatz: diskutiert LTM als dynamisches Gedächtnis über Interaktionsdaten, RAG/ICL, LoRA/SFT, parameterisierte Memory, externe Knowledge Bases und das multi-agentische OMNE-Framework. - Planung/Validierung/Replanning: relevant durch Self-Correction, kontinuierliche Anpassung, Erfahrungsspeicherung und Nutzung früherer Interaktionen zur Verbesserung späterer Entscheidungen; keine konkrete Browser-Replanning-Methode. - Evaluation/Gap: OMNE wird auf GAIA evaluiert und nutzt u. a. Web Surfer, Search, File Reader und Logic Expert; Forschungslücke bleibt bei direkter Übertragung auf Webagenten, DOM-/UI-Zustände, Prozessmetriken, Tokenkosten und kontrollierter Replanning-Evaluation.
A53: C055 | B53: S052 | C53: ELHPlan: Efficient Long-Horizon Task Planning for Multi-Agent Collaboration | D53: Ling et al. (2026) | E53: 2026 | F53: arXiv | G53: arXiv:2509.24230v2; https://arxiv.org/abs/2509.24230 | H53: Preprint | I53: Preprint-Suchquelle | J53: ARXIV-01 | K53: Teilweise | L53: Include | N53: RQ2; RQ3; RQ4; RQ5; Gap; Methodik | O53: Nein | R53: - Sehr relevantes A-/B+ Supporting-Include zu effizienter Long-Horizon-Planung, Multi-Agent-Koordination und tokenbewusster Agentenarchitektur; keine direkte Webagentenstudie, aber stark übertragbar. - Architektur: ELHPlan nutzt Memory Module, Planning Module und Validation-Refinement Module; zentrale Planungsprimitive sind Action Chains, also mehrschrittige Aktionssequenzen mit expliziter Sub-Goal-Intention. - Planung/Validierung/Replanning: validiert Action Chains vor Ausführung auf Feasibility und Inter-Agent-Konflikte; nutzt Chain Refinement, Chain Insertion und Conflict Resolution statt teurem vollständigem Replanning. - Evaluation auf TDW-MAT und C-WAH mit Transport Rate, Move Distance, Simulation Steps, Token Consumption und Inference Time; berichtet vergleichbare Task Performance bei nur ca. 30–40 % der Tokenkosten gegenüber State-of-the-Art-Methoden; Forschungslücke: Übertragung auf Webagenten, DOM-/Browserzustände und Web-spezifische Prozessfehler bleibt offen.
A54: C056 | B54: S053 | C54: Scalable Multi-Robot Collaboration with Large Language Models: Centralized or Decentralized Systems? | D54: Chen et al. (2024) | E54: 2024 | F54: ICRA 2024 / IEEE International Conference on Robotics and Automation | G54: https://doi.org/10.1109/ICRA57147.2024.10610676 | H54: Conference Paper | I54: wissenschaftliche Datenbank | J54: IEEE-01 | K54: Teilweise | L54: Include | N54: RQ2; RQ3; RQ4; RQ5; Gap; Methodik | O54: Nein | R54: - Relevantes B-Supporting-Include zu LLM-basierter Multi-Agent-Planung, zentralisierten/dezentralisierten/hybriden Agentenarchitekturen und Skalierbarkeit; keine direkte Webagentenstudie, aber methodisch gut übertragbar. - Architektur: vergleicht DMAS, CMAS, HMAS-1 und HMAS-2; besonders HMAS-2 kombiniert zentralen LLM-Planer mit lokalen LLM-Agenten, die zugewiesene Aktionen prüfen und Feedback geben. - Planung/Validierung/Replanning: Planung erfolgt iterativ mit State-Action-History; syntaktischer Verifier prüft Ausgaben und liefert Feedback zum Re-Prompting; lokale Agenten können Kollisionsrisiken oder unpassende Aktionen melden. - Evaluation auf BoxNet1, BoxNet2, Warehouse, BoxLift und 3D-PyBullet-Simulationen mit Success Rate, Steps per Plan, API Calls und Tokenverbrauch; Forschungslücke: Robotikdomäne, keine Web-/DOM-Umgebung, aber relevant für tokeneffiziente Multi-Agent-Koordination und Kontextfensterprobleme.
A55: C057 | B55: S054 | C55: Optimizing Sequential Multi-Step Tasks with Parallel LLM Agents | D55: Zhang et al. (2025) | E55: 2025 | F55: ICML 2025 / PMLR 267; arXiv | G55: arXiv:2507.08944; https://arxiv.org/abs/2507.08944 | H55: Conference Paper / Preprint | I55: wissenschaftliche Datenbank | J55: ARXIV-01 | K55: Teilweise | L55: Include | N55: RQ2; RQ3; RQ4; RQ5; Gap; Methodik | O55: Nein | R55: - Sehr relevantes A-Supporting-Include zu sequenziellen Multi-Step-Tasks, parallelen LLM-Agenten, GAIA-Evaluation, Latenz und Kosten; keine reine Webagentenstudie, aber mit WebSurfer/Tool-Agenten stark anschlussfähig. - Architektur: M1-Parallel baut auf Magentic-One auf und nutzt parallele Multi-Agent-Teams mit Orchestrator, WebSurfer, FileSurfer, Coder und ComputerTerminal; Teams bearbeiten alternative Pläne gleichzeitig. - Planung/Validierung/Replanning: mehrere Lösungspfade werden parallel ausgeführt; Early Stopping reduziert End-to-End-Latenz, Aggregation kombiniert mehrere Antworten/Logs; Failure Recovery nutzt globale Memory fehlgeschlagener Pläne und Logs für Retry. - Evaluation auf GAIA mit solved tasks, wall-clock latency und monetary cost; zeigt bis zu ca. 2.2× Speedup mit Early Termination sowie höhere Task Completion durch Aggregation; Forschungslücke: Kosten-/Latenz-Trade-offs, Aggregationsqualität und Übertragung auf konkrete Web-/Browseragenten mit Prozessfehlern bleiben weiter relevant.
A56: C058 | B56: S055 | C56: Pre-Act: Multi-Step Planning and Reasoning Improves Acting in LLM Agents | D56: Rawat et al. (2025) | E56: 2025 | F56: arXiv | G56: arXiv:2505.09970v2; https://arxiv.org/abs/2505.09970 | H56: Preprint | I56: Preprint-Suchquelle | J56: ARXIV-01 | K56: Teilweise | L56: Include | N56: RQ2; RQ3; RQ4; RQ5; Gap; Methodik | O56: Nein | R56: - Sehr relevantes A-/B+ Supporting-Include zu Multi-Step Planning, ReAct-Erweiterung und agentischer Ausführung; keine direkte Webagentenstudie, aber stark übertragbar auf Webagenten mit mehrschrittigen Aktionen. - Architektur/Methode: Pre-Act erzeugt vor der Handlung einen mehrschrittigen Plan mit Reasoning, integriert frühere Actions und Observations und revidiert den Plan nach jedem Tool-/Action-Output. - Validierung/Replanning: Planrevision nach Beobachtungen unterstützt Anpassung bei Abweichungen oder Fehlern; relevant als leichtgewichtiger Mechanismus zwischen CoT, ReAct und explizitem Replanning. - Evaluation mit Turn-Level-Metriken wie Action Recall, Tool-F1, Parameter Match und Final-Answer-Similarity sowie End-to-End-Metriken wie Goal Completion und Progress Rate; Forschungslücke: keine Browser-/DOM-Umgebung, aber sehr nützlich für Planungs-/Ausführungsmetriken und agentische Evaluation.
A57: C059 | B57: S056 | C57: Plan-Then-Execute: An Empirical Study of User Trust and Team Performance When Using LLM Agents As A Daily Assistant | D57: He et al. (2025) | E57: 2025 | F57: CHI 2025 / ACM Conference on Human Factors in Computing Systems | G57: https://doi.org/10.1145/3706598.3713218 | H57: Conference Paper / Empirical Study | I57: wissenschaftliche Datenbank | J57: ACM-01 | K57: Teilweise | L57: Include | N57: RQ1; RQ2; RQ3; RQ4; RQ5; Gap; Methodik | O57: Nein | R57: - Sehr relevantes B+/A-Supporting-Include zu Plan-Then-Execute-Agenten, Human-in-the-loop-Kontrolle, Nutzervertrauen und Team Performance; keine direkte Webagentenstudie, aber stark übertragbar auf agentische Webaufgaben mit riskanten Aktionen. - Architektur: LLM-Agent erzeugt zunächst einen hierarchischen step-wise Plan und übersetzt danach einzelne Primary Steps in konkrete Aktionen/API-Calls innerhalb einer Simulationsumgebung. - Validierung/Replanning: Nutzer können Pläne editieren, Schritte hinzufügen/löschen/splitten, vorhergesagte Aktionen prüfen, Feedback geben, Aktionen manuell überschreiben und Ausführungsschritte erneut versuchen. - Evaluation mit Plan Quality, Action Sequence Accuracy, Execution Accuracy, Calibrated Trust, subjektivem Vertrauen und Cognitive Load; Forschungslücke: keine Browser-/DOM-Umgebung, aber sehr relevant für Transparenz, Zwischenprüfung, Nutzerkontrolle und Validierung vor riskanter Agentenausführung.
A58: C060 | B58: S057 | C58: On the Planning Abilities of Large Language Models: A Critical Investigation | D58: Valmeekam et al. (2023) | E58: 2023 | F58: NeurIPS 2023 | G58: https://github.com/karthikv792/LLMs-Planning | H58: Conference Paper | I58: wissenschaftliche Datenbank | J58: ARXIV-01 | K58: Teilweise | L58: Include | N58: RQ1; RQ3; RQ4; RQ5; Gap; Methodik | O58: Nein | R58: - Sehr relevantes B+/A-Supporting-Include zu Planning-Fähigkeiten von LLMs, Grenzen autonomer Planerzeugung und Nutzen externer Planner/Verifier; keine direkte Webagentenstudie, aber zentral für Planungs- und Validierungsargumentation. - Methode/Architektur: vergleicht autonome LLM-Planung mit heuristischem Modus, in dem LLM-generierte Pläne als Seed/Heuristik für sound planners wie LPG oder als Kandidaten für externe Verifier wie VAL genutzt werden. - Planung/Validierung/Replanning: zeigt, dass autonome LLM-Pläne oft nicht ausführbar sind, aber durch externe Planvalidierung, Fehlerfeedback und Backprompting deutlich verbessert werden können; relevant für Replanning und LLM-Modulo-Architekturen. - Evaluation auf klassischen Planning-Domains wie Blocksworld, Logistics und Mystery Blocksworld mit Success Rate, Plan Correctness, Search Steps, Plan Length, Levenshtein Distance und Backprompting-Runden; Forschungslücke: Übertragung auf Webagenten, DOM-/UI-Aktionen, Tool-Feedback und prozessbezogene Webagenten-Metriken bleibt offen.
A59: C061 | B59: S058 | C59: Position: LLMs Can’t Plan, But Can Help Planning in LLM-Modulo Frameworks | D59: Kambhampati et al. (2024) | E59: 2024 | F59: ICML 2024 / PMLR 235 | G59: https://proceedings.mlr.press/v235/kambhampati24a.html | H59: Position Paper / Conference Paper | I59: wissenschaftliche Datenbank | J59: ARXIV-01 | K59: Teilweise | L59: Include | N59: RQ1; RQ2; RQ3; RQ4; RQ5; Gap; Methodik | O59: Nein | R59: - Sehr relevantes A-Supporting-Include zu LLM-Modulo, Planning-Limitations, Prompting/Backprompting und robuster Agentenarchitektur; keine direkte Webagentenstudie, aber zentral für die methodische Begründung. - Architektur: beschreibt ein Generate-Test-Critique-Framework mit LLM als Kandidatenplan-Generator, Plan Blackboard, Meta-/Backprompt-Controller, Reformulatoren sowie Hard/Soft Critics bzw. externen Verifiern. - Planung/Validierung/Replanning: argumentiert, dass LLMs autonom nicht zuverlässig planen oder sich selbst verifizieren können; robuste Planung entsteht durch externe Kritiker, Feedbackschleifen, Backprompting und model-based Verification. - Evaluation/Bezug: diskutiert PlanBench, Blocksworld, Mystery Blocksworld und TravelPlanner; berichtet Verbesserungen durch LLM-Modulo/Verifier-Feedback gegenüber reinen Prompting-Ansätzen wie CoT oder ReAct; Forschungslücke: Übertragung auf Webagenten, DOM-/Browserzustände, Tool-Feedback und prozessbezogene Fehler-/Recovery-Metriken bleibt offen.
A60: C062 | B60: S059 | C60: Building Cooperative Embodied Agents Modularly with Large Language Models | D60: Zhang et al. (2024) | E60: 2024 | F60: ICLR 2024 / arXiv | G60: arXiv:2307.02485v2; https://vis-www.cs.umass.edu/Co-LLM-Agents/ | H60: Conference Paper | I60: wissenschaftliche Datenbank | J60: ARXIV-01 | K60: Teilweise | L60: Include | N60: RQ2; RQ3; RQ4; RQ5; Gap; Methodik | O60: Nein | R60: - Sehr relevantes B+/A-Supporting-Include zu modularer LLM-Agentenarchitektur, Multi-Agent-Kooperation, Memory, Kommunikation und Planning; keine direkte Webagentenstudie, aber stark übertragbar auf agentische Web-/Tool-Umgebungen. - Architektur: CoELA besteht aus Perception, Memory, Communication, Planning und Execution; Memory ist in Semantic, Episodic und Procedural Memory gegliedert, während das LLM vor allem Communication und High-Level Planning steuert. - Planung/Validierung/Ausführung: Planning Module wählt High-Level-Pläne auf Basis von Memory, Action List, Task Progress und Agent State; Execution Module übersetzt diese Pläne in robuste primitive Aktionen und reduziert dadurch Low-Level-Fehler und LLM-Inferenzkosten. - Evaluation auf TDW-MAT und C-WAH mit Transport Rate, Average Steps und Efficiency Improvement sowie Human-Agent-Studie zu Kommunikation, Vertrauen und Kooperation; Forschungslücke: Embodied-/Robotikdomäne, keine Browser-/DOM-Umgebung, aber sehr relevant für modulare Webagentenarchitektur, Memory, Planung und prozessbezogene Effizienzmetriken.
A61: C063 | B61: S060 | C61: Multi-LLM Agent Collaborative Intelligence: The Path to Artificial General Intelligence | D61: Chang (2025) | E61: 2025 | F61: Stanford University / CS372 / Book PDF | G61: uploaded PDF; SocraSynth.com | H61: Buch / Monographie / Technical Book | I61: Manuell | J61: ACM-01 | K61: Teilweise | L61: Background | N61: RQ1; RQ2; RQ3; RQ4; RQ5; Gap; Methodik | O61: Nein | R61: - Relevante Background- und Methodikquelle zu Multi-LLM-Agenten, kollaborativer Intelligenz, Prompting, persistentem Memory, Planung und Validierung; keine direkte Webagenten-Primärstudie. - Architektur/Ansatz: MACI beschreibt modulare Multi-Agent-Systeme mit spezialisierten Rollen, Socratic Dialogue, CRIT, SocraSynth, EVINCE, ALAS und SagaLLM als Bausteine für kollaboratives Reasoning. - Planung/Validierung/Replanning: besonders relevant sind ALAS für Multi-Agent-Planning und SagaLLM für persistenten Kontext, Constraint Validation, Fehlererkennung, Rollback und transaction-like guarantees in langen Workflows. - Evaluation/Gap: enthält Fallstudien und Experimente zu Planning-Szenarien wie Thanksgiving Dinner, Wedding Gathering und Travel Planning, aber keine Web-/Browserumgebung, keine WebArena/Mind2Web-Evaluation und keine standardisierte Webagenten-Metrik; daher eher selektiv als Hintergrund nutzen.
A62: C064 | B62: S061 | C62: Devil’s Advocate: Anticipatory Reflection for LLM Agents | D62: Wang et al. (2024) | E62: 2024 | F62: arXiv | G62: arXiv:2405.16334v4; https://arxiv.org/abs/2405.16334 | H62: Preprint | I62: Preprint-Suchquelle | J62: ARXIV-01 | K62: Teilweise | L62: Include | N62: RQ2; RQ3; RQ4; RQ5; Gap; Methodik | O62: Nein | R62: - Sehr relevantes A-Core-Include zu LLM-Webagenten, WebArena, anticipatory reflection, Backtracking und Replanning; direkte Primärstudie für Webagenten in realistischen Webumgebungen. - Architektur: Agent zerlegt Tasks in Subtasks, nutzt Plan Generation, Action Generation, Objective-/Subtask-Completion Checks, Alignment Checks und Remedy Generation als Devil’s-Advocate-Mechanismus. - Validierung/Replanning: vor jeder Aktion antizipiert der Agent mögliche Fehler und alternative Remedy Actions; nach Aktionen prüft er Alignment mit dem Subtask, kann backtracken und bei Planfehlern eine Plan Revision ausführen. - Evaluation auf WebArena mit Success Rate, Anzahl Aktionen pro Trial und Anzahl Plan Revisions; berichtet 23.5 % Success Rate und ca. 45 % weniger Planrevisionen gegenüber Vergleichsmethoden; Forschungslücke: sequentielle Planung reicht für komplexe Webtasks mit Loops, wiederverwendbaren Funktionen und dynamischem Problem Solving noch nicht aus.
... A70: C072 | B70: S069 | C70: WebDART: Dynamic Decomposition and Re-planning for Complex Web Tasks | D70: Yang et al. (2025) | E70: 2025 | F70: arXiv | G70: arXiv:2510.06587v1; https://github.com/UCSB-NLP-Chang/WebDART | H70: Preprint | I70: Preprint-Suchquelle | J70: ARXIV-02 | K70: Teilweise | L70: Include | N70: RQ2; RQ3; RQ4; RQ5; Gap; Methodik | O70: Nein | R70: - Sehr relevantes A-Core-Include zu komplexen LLM-Webagenten, dynamischer Task-Decomposition, Replanning, WebChoreArena und WebArena; direkte Primärstudie für Webagenten. - Architektur: WebDART zerlegt komplexe Webtasks modular in Navigation, Information Extraction und Execution; zusätzlich Fast-Path-Routing für Aufgaben, die nicht alle Module benötigen. - Planung/Validierung/Replanning: initial konservative Decomposition wird während der Navigation dynamisch angepasst, wenn neue Webelemente wie Filter, Sortierung oder direkte Links entdeckt werden; dadurch werden fehlerhafte oder ineffiziente Pläne korrigiert. - Evaluation auf WebChoreArena und WebArena mit Success Rate und Average Navigation Steps; berichtet Verbesserungen gegenüber SteP, BrowserGym, AWM und AgentOccam sowie bis zu 14.7 weniger Navigationsschritte durch Dynamic Replanning; Forschungslücke: weitere Prüfung von Robustheit, Extraktionsfehlern, multimodalen Umgebungen und Kosten-/Tokenmetriken bleibt relevant.
A71: C073 | B71: S070 | C71: Motion Planner With Fixed-Horizon Constrained Reinforcement Learning for Complex Autonomous Driving Scenarios | D71: Lin et al. (2024) | E71: 2024 | F71: IEEE Transactions on Intelligent Vehicles | G71: https://doi.org/10.1109/TIV.2023.3273857 | H71: Journal Article | I71: wissenschaftliche Datenbank | J71: IEEE-01 | K71: Teilweise | L71: Background | M71: Domänenspezifisches Paper zu autonomem Fahren und constrained reinforcement learning; keine LLM-basierte Agentenarchitektur, keine Webagenten, keine Browsernavigation, keine DOM-/UI-Umgebung und kein agentisches Replanning im Sinne der SLR. | N71: RQ3; RQ5; Methodik | O71: Nein | R71: - Behandelt Motion Planning für autonomes Fahren mit constrained A* für lane-level global routing und fixed-horizon constrained RL für Sicherheit und Komfort. - Relevanz für die SLR nur sehr indirekt über Planungshorizonte, Constraints und Zielkonflikte zwischen Goal Completion, Safety und Comfort. - Keine LLMs, keine Tool-/Webagentenarchitektur, keine Reflection-/Validation-Schleife und keine Webagenten-spezifische Evaluation. - Evaluation nutzt autonome-Fahren-Metriken wie Total Reward, Safety Cost, Comfort Cost, Time, Speed und Target Reach; für Webagentenmetriken wie Success Rate, Tokenkosten, Navigation Steps oder Prozessfehler nicht direkt nutzbar.
A72: C074 | B72: S071 | C72: Accelerating Long-Horizon Planning with Affordance-Directed Dynamic Grounding of Abstract Strategies | D72: Elimelech et al. (2024) | E72: 2024 | F72: ICRA 2024 / IEEE International Conference on Robotics and Automation | G72: https://doi.org/10.1109/ICRA57147.2024.10610486 | H72: Conference Paper | I72: wissenschaftliche Datenbank | J72: IEEE-01 | K72: Teilweise | L72: Include | N72: RQ2; RQ3; RQ4; RQ5; Gap; Methodik | O72: Nein | R72: - Relevantes B-Supporting-Include zu Long-Horizon Task Planning, abstrakten Strategien, dynamic grounding und Planning-Effizienz; keine direkte Webagenten- oder LLM-Agentenstudie, aber methodisch gut übertragbar. - Architektur/Methode: nutzt eine Strategy Library mit abstract strategies, abstraction keys, strategy-augmented domains und strategy-actions als wiederverwendbare Planungsabkürzungen. - Planung/Validierung: Affordance Scores steuern, welche Strategie in welchem Zustand sinnvoll anwendbar ist; lazy strategy refinement prüft erst nach High-Level-Planung, ob die gewählte abstrakte Strategie in konkrete Aktionen verfeinert werden kann. - Evaluation im Blocksworld-/Object-Rearrangement-Setting mit Success Rate, Planning Time, Timeout, Anzahl genutzter Strategien und Atomic Actions; Forschungslücke: keine Web-/DOM-Umgebung und keine LLM-basierte Agentenarchitektur, aber relevant für effiziente Long-Horizon-Planung, Strategiekomposition und Wiederverwendung von Planungserfahrung.
A73: C075 | B73: S072 | C73: LLaMAR: Long-Horizon Planning for Multi-Agent Robots in Partially Observable Environments | D73: Nayak et al. (2024) | E73: 2024 | F73: NeurIPS 2024 / arXiv | G73: arXiv:2407.10031v2; https://github.com/nsidn98/LLaMAR | H73: Conference Paper / Preprint | I73: wissenschaftliche Datenbank | J73: ARXIV-01 | K73: Teilweise | L73: Include | N73: RQ2; RQ3; RQ4; RQ5; Gap; Methodik | O73: Nein | R73: - Sehr relevantes B+/A-Supporting-Include zu LM-basiertem Long-Horizon Multi-Agent Planning, Partial Observability, Failure Correction und Self-Verification; keine direkte Webagentenstudie, aber stark übertragbar auf komplexe Webagenten. - Architektur: LLaMAR nutzt eine modulare kognitive Plan-Act-Correct-Verify-Architektur mit Planner, Actor, Corrector, Verifier, Memory, Open Subtasks und Completed Subtasks. - Planung/Validierung/Replanning: Planner erzeugt feasible subtasks, Actor wählt High-Level-Actions für alle Agenten, Corrector analysiert fehlgeschlagene Aktionen anhand von Execution Feedback, und Verifier prüft Subtask Completion ohne Oracle-/Simulator-Privilegien. - Evaluation auf MAP-THOR und Search-&-Rescue-Tasks mit Success Rate, Transport Rate, Coverage, Balance und Average Steps; berichtet ca. 30 % höhere Success Rate gegenüber anderen LM-basierten Multi-Agent-Plannern; Forschungslücke: keine Web-/DOM-Umgebung, aber sehr relevant für Fortschrittsprüfung, Fehlerkorrektur, Multi-Agent-Koordination und robuste Long-Horizon-Agentenarchitekturen.
A74: C076 | B74: S073 | C74: Large Language Models for Planning: A Comprehensive and Systematic Survey | D74: Cao et al. (2025) | E74: 2025 | F74: arXiv | G74: arXiv:2505.19683v1; https://arxiv.org/abs/2505.19683; https://github.com/Quester-one/Awesome-LLM-Planning | H74: Survey / Preprint | I74: Preprint-Suchquelle | J74: ARXIV-01 | K74: Teilweise | L74: Include | N74: RQ1; RQ2; RQ3; RQ4; RQ5; Gap; Methodik | O74: Nein | R74: - Sehr relevantes A-Supporting-Include zu LLM-based Planning, Definitionen, Methoden, Evaluation und Forschungslücken; keine Primärstudie zu einem konkreten Webagenten, aber direkt nützlich zur Strukturierung aller RQs. - Taxonomie: unterscheidet External Module Augmented Methods, Finetuning-based Methods und Searching-based Methods; zusätzlich klare Kategorien wie MDP/POMDP, High-Level/Low-Level Planning und Open-/Closed-Loop Planning. - Planung/Validierung/Replanning: behandelt Planner-Enhanced Methods, Memory-Enhanced Methods, Feedback-based Methods, Decomposition, iterative Planung, Exploration, MCTS/A*, World Models, Reward Models und externe Verifier/Feedback-Schleifen. - Evaluation/Gap: systematisiert Datasets, Metriken und Performance-Vergleiche für digitale, embodied, everyday und vertical planning tasks; relevant für Webnavigation, Agentenplanung, Effizienz, Robustheit und fehlende standardisierte Evaluation.
A75: C077 | B75: S074 | C75: Position: The Real Barrier to LLM Agent Usability is Agentic ROI | D75: Liu et al. (2026) | E75: 2026 | F75: arXiv / ICML 2026 submission | G75: arXiv:2505.17767v2; https://arxiv.org/abs/2505.17767 | H75: Position Paper / Preprint | I75: Preprint-Suchquelle | J75: ARXIV-03 | K75: Teilweise | L75: Include | N75: RQ1; RQ3; RQ4; RQ5; Gap; Methodik | O75: Nein | R75: - Relevantes B+/A-Supporting-Include zu nutzerzentrierter Agentenevaluation, Agentic ROI, Usability Gap und realem Nutzen von LLM-Agenten; keine direkte Webagenten-Primärstudie, aber sehr relevant für Evaluation und Methodik. - Methode/Konzept: definiert Agentic ROI als Information Gain × Time Savings / Cost und verschiebt die Bewertung von reiner Performance zu nutzerbezogener Utility, Kosten und Interaktionsaufwand. - Planung/Validierung: diskutiert Long-Horizon Reasoning, State Persistence, Self-Correction, proactive interaction und proactive verification als notwendige Fähigkeiten für nützliche Agenten in mehrschrittigen Aufgaben. - Evaluation/Gap: zeigt, dass hohe Modellfähigkeit nicht automatisch hohe Usability bedeutet; wichtige Metriken sind Information Gain, Time Savings, Agent Interaction Time, Cost und reale Nutzerakzeptanz; Forschungslücke: Webagenten sollten stärker nach ROI, Prozesskosten, Verifikationsaufwand und menschlicher Zeitersparnis bewertet werden.
A76: C078 | B76: S075 | C76: Evolutionary Perspectives on the Evaluation of LLM-Based AI Agents: A Comprehensive Survey | D76: Zhu et al. (2025) | E76: 2025 | F76: arXiv | G76: arXiv:2506.11102v1; https://arxiv.org/abs/2506.11102 | H76: Survey / Preprint | I76: Preprint-Suchquelle | J76: ARXIV-03 | K76: Teilweise | L76: Include | N76: RQ1; RQ2; RQ3; RQ4; RQ5; Gap; Methodik | O76: Nein | R76: - Sehr relevantes A-Supporting-Include zu LLM-basierten AI Agents, Agentenevaluation, Benchmark-Auswahl und Webagenten-Evaluation; keine Primärstudie zu einem einzelnen Webagenten, aber direkt nützlich für die Strukturierung aller RQs. - Definition/Taxonomie: grenzt AI Agents von LLM-Chatbots über fünf Aspekte ab: komplexe Umgebung, multi-source instructor, dynamic feedback, multimodal perception und advanced capability. - Architektur/Fähigkeiten: systematisiert Agent Capabilities wie Planning, Self-Reflection, Interaction, Memory und General Evaluation; relevant für Planungs-, Validierungs- und Replanning-Mechanismen. - Evaluation/Gap: ordnet Benchmarks nach Environment-Typen wie Code, Web, OS, Mobile, Scientific und Game Environments ein; Webteil umfasst u. a. MiniWoB, WebShop, Mind2Web, WebVoyager, WebArena, VisualWebArena, WorkArena, Online-Mind2Web und OmniAct; Forschungslücke: Agentenevaluation muss dynamischer, multimodaler, stateful, multi-turn, feingranularer und stärker effizienzorientiert werden.
A77: C079 | B77: S076 | C77: AgentSynth: Scalable Task Generation for Generalist Computer-Use Agents | D77: Xie et al. (2026) | E77: 2026 | F77: ICLR 2026 | G77: arXiv:2506.14205v2; https://github.com/sunblaze-ucb/AgentSynth | H77: Conference Paper / Benchmark Paper | I77: Preprint-Suchquelle | J77: ARXIV-03 | K77: Teilweise | L77: Include | N77: RQ2; RQ3; RQ4; RQ5; Gap; Methodik | O77: Nein | R77: - Sehr relevantes A-Core-Include zu generalistischen Computer-Use Agents, Long-Horizon-GUI-Aufgaben, synthetischer Task-/Trajectory-Generierung und agentischer Evaluation; nicht nur Webagenten, aber stark angrenzend durch Web-, OS-, Office-, Coding- und Research-Tasks. - Architektur/Methode: AgentSynth nutzt mehrere LLM-basierte Rollen wie Task Proposer, Executor, Verifier, Reviser, Follow-up Task Proposer und Summarizer; komplexe Aufgaben entstehen durch Chaining einfacher, überprüfter Subtasks. - Planung/Validierung/Replanning: Difficulty wird über die Anzahl zusammengefasster Subtasks gesteuert; Verifier prüft vollständige Trajektorien, Reviser erzeugt angepasste Aufgabenbeschreibungen bei partieller Ausführung; Failure Modes zeigen Probleme bei UI-Grounding, State Tracking und Recovery. - Evaluation mit über 6.000 Aufgaben, OSWorld-ähnlicher Desktopumgebung, Success Rate nach Difficulty Level, Horizon, Memory Span, Anzahl Apps/App Switches, Human Performance und Kosten pro Trajectory; berichtet starken Performanceabfall aktueller Agenten von ca. 18 % auf Level 1 auf ca. 4 % auf Level 6; Forschungslücke: robuste Long-Horizon-Planung, Fehlererholung, visuelles Grounding und skalierbare Evaluation bleiben offen.
A78: C080 | B78: S077 | C78: MIRAGE-Bench: LLM Agent is Hallucinating and Where to Find Them | D78: Zhang et al. (2025) | E78: 2025 | F78: arXiv | G78: arXiv:2507.21017v1; https://github.com/sunblaze-ucb/mirage-bench.git | H78: Benchmark Paper / Preprint | I78: Preprint-Suchquelle | J78: ARXIV-03 | K78: Teilweise | L78: Include | N78: RQ1; RQ2; RQ3; RQ4; RQ5; Gap; Methodik | O78: Nein | R78: - Sehr relevantes A-Core-Include zu agentischen Halluzinationen, Faithfulness, Risk Settings und Evaluation interaktiver LLM-Agenten; direkte Relevanz für Web-/Computer-Use-Agenten durch WebArena, WorkArena, OSWorld, SWE-Bench, TheAgentCompany und τ-Bench. - Taxonomie/Methode: unterscheidet Halluzinationen als Unfaithfulness gegenüber Task Instructions, Interaction History oder Environment Observations; grenzt hallucinated actions klar von allgemein falschen Aktionen ab. - Validierung/Replanning: MIRAGE-Bench isoliert kritische Entscheidungspunkte über contextual snapshots und prüft, ob Agenten bei riskanten Situationen wie out-of-scope queries, unexpected environmental transitions, unachievable goals, ill-specified instructions, flawed history oder pop-up distractions kontexttreu handeln. - Evaluation mit LLM-as-a-Judge, risk-aware prompts, Utility Score und Hallucination Rate; zeigt, dass auch starke proprietäre Modelle weiterhin substanzielle Halluzinationsraten haben; Forschungslücke: Webagenten brauchen prozessbezogene Faithfulness-, Risk-, Hallucination- und Recovery-Metriken statt nur Task Success Rate.
A79: C081 | B79: S078 | C79: Empowering Real-World: A Survey on the Technology, Practice, and Evaluation of LLM-driven Industry Agents | D79: Tang et al. (2025) | E79: 2025 | F79: arXiv | G79: arXiv:2510.17491v1 | H79: Survey / Preprint | I79: Preprint-Suchquelle | J79: ARXIV-03 | K79: Teilweise | L79: Include | N79: RQ1; RQ2; RQ3; RQ4; RQ5; Gap; Methodik | O79: Nein | R79: - Sehr relevantes A-Supporting-Include zu LLM-driven Industry Agents, Agentenarchitektur, Memory, Planning, Tool Use, Praxisanwendungen und Evaluation; keine Primärstudie zu einem einzelnen Webagenten, aber stark nützlich für die Strukturierung der SLR. - Architektur/Taxonomie: entwickelt ein fünfstufiges Capability-Maturity-Framework von L1 Process Execution System über L2 Interactive Problem-Solving und L3 End-to-End Autonomous System bis L4 Collaborative Intelligent System und L5 Adaptive Social System. - Planung/Validierung/Replanning: systematisiert Planning von Linear Planning über Reactive Planning bis Global/Collaborative/Autonomous Goal Planning; behandelt ReAct, DEPS, LLM+P, ToT, LLM-MCTS, World Models, Reflexion, CRITIC, Self-Correction, Tool Failure Handling und Rollback-ähnliche Mechanismen. - Evaluation/Gap: ordnet Benchmarks für Memory, Planning und Tool Use sowie Industry-Domain-Evaluation ein, u. a. AgentBench, TheAgentCompany, WebArena, VisualWebArena, MMInA, ST-WebAgentBench und WebCanvas; Forschungslücke: reale Industrieagenten brauchen authentischere, sicherere, domänenspezifischere und prozessbezogene Evaluation statt nur generischer Agentenmetriken.
A80: C082 | B80: S079 | C80: Agent Data Protocol: Unifying Datasets for Diverse, Effective Fine-tuning of LLM Agents | D80: Song et al. (2026) | E80: 2026 | F80: ICLR 2026 | G80: arXiv:2510.24702v2; https://agentdataprotocol.com | H80: Conference Paper / Dataset & Protocol Paper | I80: Preprint-Suchquelle | J80: ARXIV-04 | K80: Teilweise | L80: Include | N80: RQ2; RQ3; RQ5; Gap; Methodik | O80: Nein | R80: - Sehr relevantes A-Supporting-Include zu LLM-Agenten, Agentendaten, Trajektorienstandardisierung, Fine-Tuning und Cross-Domain-Evaluation; keine reine Webagenten-Primärstudie, aber direkt relevant für web-, tool-, coding- und software-agentische Systeme. - Architektur/Methode: Agent Data Protocol standardisiert heterogene Agentendatasets in Trajectory-Objekte aus Actions und Observations; unterstützt API Actions, Code Actions, Message Actions sowie Text und Web Observations. - Planung/Training: relevant für multi-step Agentenverhalten, weil ADP unterschiedliche Trajektorienformate aus Web Browsing, Tool Use, Coding und Software Engineering vereinheitlicht und in SFT-Formate für OpenHands, SWE-Agent und AgentLab übersetzt. - Evaluation/Gap: vereinheitlicht 13 bestehende Agentendatasets mit ca. 1.3M Trainingstrajektorien und evaluiert auf SWE-Bench Verified, WebArena, AgentBench und GAIA; berichtet durchschnittlich ca. 20 % Performancegewinn gegenüber Basismodellen; Forschungslücke: Agententraining leidet weniger an Datenmangel als an fragmentierten Formaten, fehlender Standardisierung und schwieriger Vergleichbarkeit.
A81: C083 | B81: S080 | C81: WebSurfer: Enhancing LLM Agents with Web-Wise Feedback for Web Navigation | D81: Hu et al. (2025) | E81: 2025 | F81: ICASSP 2025 / IEEE | G81: https://doi.org/10.1109/ICASSP49660.2025.10889961 | H81: Conference Paper | I81: wissenschaftliche Datenbank | J81: IEEE-01 | K81: Ja | L81: Include | N81: RQ2; RQ3; RQ4; RQ5; Gap; Methodik | O81: Nein | R81: - Sehr relevantes A-Core-Include zu LLM-Webagenten, Webnavigation, Web-Wise Feedback, Memory und Mind2Web; direkte Primärstudie für webbasierte Agenten. - Architektur: WebSurfer kombiniert task-oriented state filtering zur Reduktion redundanter HTML-/DOM-Informationen, retrieval-based exemplar selection and ordering für In-Context Learning sowie Short-Term und Long-Term Memory mit einem Web-Wise Insight Manager. - Planung/Validierung/Replanning: nutzt vorherige Aktionen, aktuelle Webbeobachtung, Expert Exemplars und praktische Insights aus fehlgeschlagenen Trials, um web-spezifische Strategien zu verfeinern und Fehlerakkumulation in Long-Horizon-Webtasks zu reduzieren. - Evaluation auf Mind2Web mit Cross-Task, Cross-Website und Cross-Domain Settings sowie Element Accuracy, Step Success Rate und Success Rate; WebSurfer verbessert gegenüber MindAct, ReAct, Synapse und TRAD vor allem Element Accuracy und Step Success Rate, während die absolute Task Success Rate weiterhin niedrig bleibt.
A82: C084 | B82: S081 | C82: WebNav: An Intelligent Agent for Voice-Controlled Web Navigation | D82: Srinivasan & Patapasti (2025) | E82: 2025 | F82: arXiv | G82: arXiv:2503.13843v2 | H82: Preprint / System Paper | I82: Preprint-Suchquelle | J82: ARXIV-04 | K82: Ja | L82: Include | N82: RQ2; RQ3; RQ4; Gap; Methodik | O82: Nein | R82: - Relevantes B-Supporting-Include zu LLM-basierten Webagenten, Voice-Controlled Web Navigation, multimodaler UI-Wahrnehmung und modularer Agentenarchitektur; direkte Webagentenstudie, aber eher Prototyp/Systembeschreibung als starke empirische Benchmark-Studie. - Architektur: WebNav kombiniert Speech/Text Input, Screenshot-Modul, dynamische DOM-Labeling-Browserextension, Controller LLM für High-Level-Strategie und Assistant LLM für strukturierte JSON-Aktionsformulierung. - Planung/Execution: trennt strategisches „what to do“ vom konkreten „how to execute“; Controller plant den nächsten Schritt anhand von Ziel, Screenshot und Action History, Assistant übersetzt diesen Schritt in ausführbare Aktionen via pyautogui. - Validierung/Gap: aktuelles System ist weitgehend open-loop und nimmt an, dass Aktionen erfolgreich sind; Closed-loop Verification, Self-Correction, intelligentes Scrolling, Memory und robuste Browsersteuerung über CDP werden als zukünftige Arbeit genannt. Keine standardisierte Evaluation auf Mind2Web/WebArena; daher für RQ5 nur begrenzt nutzbar.
A83: C085 | B83: S082 | C83: Build the web for agents, not agents for the web | D83: Lù et al. (2025) | E83: 2025 | F83: arXiv | G83: arXiv:2506.10953v1 | H83: Position Paper / Preprint | I83: Preprint-Suchquelle | J83: ARXIV-02 | K83: Ja | L83: Include | N83: RQ1; RQ2; RQ3; RQ4; RQ5; Gap; Methodik | O83: Nein | R83: - Sehr relevantes A-Supporting-Include zu Webagenten, Agentic Web Interfaces, Webagentenarchitektur, Sicherheit, Standardisierung und Effizienz; keine Primärstudie mit neuem Agenten oder Benchmark, aber zentral für Gap und Methodik. - Kernargument: Webagenten sollten nicht weiter primär an menschliche Browser-UIs, Screenshots, DOM-Bäume oder Entwickler-APIs angepasst werden; stattdessen braucht es Agentic Web Interfaces, die speziell für Agenten entworfen sind. - Architektur/Planung: AWIs sollen standardisierte, agentengerechte Observationen und High-Level-Actions bieten, wodurch Planung, Search, Exploration, Generalisierung und Reward-/Success-Signale robuster und effizienter werden könnten. - Validierung/Sicherheit/Effizienz: diskutiert Access Control, Guardrails, Human Confirmation, progressive information transfer, agentic task queues, Datenschutz, Ressourcenmanagement und geringere Token-/Hostingkosten; Forschungslücke: Webagenten brauchen nicht nur bessere Modelle, sondern bessere, sichere und standardisierte Webschnittstellen.
... A97: C100 | B97: S096 | C97: Why Do LLM-based Web Agents Fail? A Hierarchical Planning Perspective | D97: Aghzal et al. (2026) | E97: 2026 | F97: arXiv | G97: arXiv:2603.14248v1 | H97: Preprint / WebAgent Failure Analysis & Planning Evaluation Paper | I97: Preprint-Suchquelle | J97: ARXIV-02 | K97: Teilweise | L97: Include | N97: RQ2; RQ3; RQ4; RQ5; Gap; Methodik | O97: Nein | R97: - Sehr relevantes A-Core-Include zu LLM-basierten Webagenten, hierarchischer Planung, Failure Analysis, PDDL, Low-Level Execution, Postcondition Checking und Replanning; direkte Webagentenstudie auf Mind2Web-Live. - Architektur/Methode: zerlegt Webagentenleistung in drei Ebenen: High-Level Planning, Low-Level Execution und Replanning; nutzt High-Level Planner LLM, Low-Level Planner LLM, Postcondition Checker LLM und Replanner LLM. - Planung: vergleicht Natural-Language-Pläne mit strukturierten PDDL-Plänen; PDDL erzeugt kompaktere, stärker goal-directed und besser human-aligned Pläne als NL, reduziert Over-Decomposition und unmatched/redundante Schritte. - Validierung/Replanning: Postcondition Checker prüft, ob ein Subgoal nach den Low-Level-Aktionen erfüllt wurde; bei Fehlschlag wird Replanning ausgelöst, entweder als lokale Anpassung oder globales Replanning; eine Replanning-Runde verbessert Subgoal Completion, Plan Completion und Success Rate deutlich. - Evaluation/Failure Modes: nutzt Mind2Web-Live mit 104 Live-Webtasks und human-aligned High-Level-Plänen aus Expert-Key-Nodes; Metriken umfassen Perfect Match, Partial, Missing, Decomposed, Unmatched, Matched Rate, Subgoal Completion, Plan Completion, Plan Efficiency, Success Rate, Hallucination Rate, Repetitions, Redundant Actions, Hallucinated Links und Out-of-Domain Links; zentrale Erkenntnis: Low-Level Execution und perceptual grounding sind der dominante Bottleneck, nicht nur High-Level Reasoning.
A98: C103 | B98: S099 | C98: The BrowserGym Ecosystem for Web Agent Research | D98: Le Sellier De Chezelles et al. (2025) | E98: 2025 | F98: arXiv | G98: arXiv:2412.05467v4 | H98: Preprint / WebAgent Benchmarking & Evaluation Infrastructure Paper | I98: Preprint-Suchquelle | J98: ARXIV-02 | K98: Teilweise | L98: Include | N98: RQ1; RQ2; RQ4; RQ5; Gap; Methodik | O98: Webarena Git Repo | P98: Forward | R98: - Sehr relevantes A-Core-Include zu Webagentenforschung, BrowserGym, AgentLab, Benchmark-Unification, standardisierter Evaluation, Reproduzierbarkeit und Trace Analysis; direkte Webagenten-Methodikquelle. - Architektur/Infrastruktur: BrowserGym stellt eine einheitliche gymartige Web-Agent-Umgebung bereit, modelliert die Interaktion als POMDP und bietet Observation Spaces mit Task Goal/Chat, offenen Tabs, DOM, AXTree, Screenshot, Element-IDs, Bounding Boxes, Visibility, Set-of-Marks und Error Feedback. - Action/Execution: unterstützt raw Python/Playwright-Aktionen sowie eingeschränkte High-Level-Action-Primitives über Action Mapping; dadurch relevant für Action-Space-Design, Sicherheit, Vergleichbarkeit und robuste Browsersteuerung. - Evaluation/Methodik: vereinheitlicht Benchmarks wie MiniWoB, WebArena, VisualWebArena, WorkArena L1–L3, WebLINX und AssistantBench unter derselben API; AgentLab unterstützt parallele Experimente, Reproducibility Journal, Leaderboard, AgentXRay und Analyse einzelner Agententraces. - Ergebnisse/Gap: führt eine large-scale Multi-Benchmark-Evaluation mehrerer LLMs/VLMs durch und zeigt weiterhin niedrige Success Rates auf komplexen Webagentenbenchmarks; zentrale Forschungslücke: Webagentenforschung leidet unter fragmentierten Benchmark-Codes, inkonsistenten Evaluationspraktiken, Reproduzierbarkeitsproblemen und fehlender cross-benchmark Vergleichbarkeit.
A99: C104 | B99: S100 | C99: GPT-4V(ision) is a Generalist Web Agent, if Grounded | D99: Zheng et al. (2024) | E99: 2024 | F99: ICML 2024 | G99: https://osu-nlp-group.github.io/SeeAct; https://github.com/OSU-NLP-Group/SeeAct | H99: Conference Paper / Multimodal WebAgent Paper | I99: wissenschaftliche Datenbank | J99: ARXIV-02 | K99: Teilweise | L99: Include | N99: RQ1; RQ2; RQ3; RQ4; RQ5; Gap; Methodik | O99: Nein | R99: - Sehr relevantes A-Core-Include zu generalistischen multimodalen Webagenten, GPT-4V, SEEACT, visuellem Webverständnis, Action Generation, Element Grounding und Online-Evaluation; direkte Webagenten-Primärstudie. - Architektur/Methode: SEEACT nutzt Large Multimodal Models wie GPT-4V zur visuellen Wahrnehmung gerenderter Webseiten und trennt den Prozess in textuelle Action Generation und anschließendes Action Grounding auf HTML-Element, Operation und Wert; evaluiert Grounding via Element Attributes, Textual Choices, Image Annotation und Oracle Grounding. - Planung/Grounding: zeigt, dass GPT-4V starke textuelle Aktionsbeschreibungen und teilweise speculative planning, world-model-artiges Webseitenverständnis sowie Error-Correction-Awareness besitzt, aber die Umsetzung in konkrete UI-/HTML-Aktionen weiterhin der zentrale Bottleneck ist. - Evaluation: nutzt Mind2Web bzw. Multimodal Mind2Web mit Cross-Task, Cross-Website und Cross-Domain sowie Element Accuracy, Operation F1, Step Success Rate und Whole Task Success Rate; zusätzlich neue Online-Evaluation auf Live-Websites mit Playwright. - Ergebnisse/Gap: GPT-4V mit Oracle Grounding erreicht online 51.1 % Task Success und SEEACTChoice 37.8 %, während GPT-4 und FLAN-T5 deutlich niedriger liegen; Grounding-Strategien bleiben 20–32 Prozentpunkte hinter Oracle Grounding zurück; Forschungslücke: robuste Webagenten brauchen bessere visuell-textuelle Grounding-Methoden, Online-Evaluation und Sicherheitskontrollen für reale Webaktionen.
A100: C105 | B100: S101 | C100: Process Evaluation for Agentic Systems | D100: Gritta et al. (2026) | E100: 2026 | F100: Findings of ACL: EACL 2026 | G100: https://github.com/deepsynth/process_eval | H100: Position Paper / Evaluation Method Paper | I100: wissenschaftliche Datenbank | J100: ARXIV-03 | K100: Ja | L100: Include | N100: RQ1; RQ2; RQ4; RQ5; Gap; Methodik | O100: Nein | R100: - Sehr relevantes A-Supporting-Include zu Process Evaluation, Compliance Checklists, Compliance Score, Tool-Use-Verification und ganzheitlicher Evaluation agentischer Systeme; keine spezifische Webagenten-Primärstudie, aber methodisch sehr stark für Webagenten-Evaluation übertragbar. - Kernargument: Outcome Accuracy und Partial Correctness reichen für Agenten nicht aus, weil Agenten richtige Antworten durch riskante Prozesse erreichen können, z. B. durch Step Skipping, Hallucinated Tool Use, veraltetes parametrisches Wissen, Shortcut Taking oder unvollständige Informationsbeschaffung. - Methode: schlägt Compliance Checklists vor, die den empfohlenen Prozess einer Agententrajektorie prüfen; ein LLM-as-a-Judge bewertet vollständige Trajectories inklusive User/Assistant Turns, Tool Calls und Tool Outputs mit YES/NO-Fragen; daraus entsteht ein ungewichteter oder gewichteter Compliance Score. - Evaluation/Validierung: kleine Machbarkeitsstudie mit GAIA- und neu erstellten unseen Aufgaben; vergleicht GPT-4.1, GPT-4.1-mini und o3-mini nach Answer Accuracy, Weighted/Unweighted Compliance und Judge Alignment; zeigt, dass Accuracy und Compliance unterschiedliche Agentenqualitäten messen. - Gap: fordert holistic agent evaluation mit Answer Accuracy, Partial Accuracy, Judging the Judge, Real-World Questions und Process Evaluation; besonders relevant für kritische Anwendungen und für Webagenten, bei denen Tool-Nutzung, Quellenprüfung, Browseraktionen, Replanning und Prozess-Faithfulness auditiert werden müssen.
A101: C106 | B101: S102 | C101: TWOSTEP: Multi-agent Task Planning using Classical Planners and Large Language Models | D101: Bai et al. (2025) | E101: 2025 | F101: arXiv | G101: arXiv:2403.17246v2 | H101: Preprint / Hybrid Planning & Multi-Agent Paper | I101: Preprint-Suchquelle | J101: ARXIV-01 | K101: Teilweise | L101: Include | N101: RQ2; RQ3; RQ4; RQ5; Gap; Methodik | O101: Nein | R101: - Relevantes B-Supporting-Include zu LLM-gestützter Multi-Agent Task Planning, klassischer PDDL-Planung, Subgoal Decomposition und formalen Ausführungsgarantien; keine direkte Webagentenstudie, aber methodisch relevant für Planungs- und Validierungsmechanismen. - Methode: TWOSTEP nutzt ein LLM, um ein globales Ziel in teilweise unabhängige Helper-Subgoals zu zerlegen und diese anschließend in PDDL-Zielbedingungen zu übersetzen; die eigentliche Planung wird durch einen klassischen PDDL-Planner durchgeführt. - Planung/Validierung: kombiniert commonsense-basierte LLM-Zerlegung mit symbolischer Planung, sodass Subgoal-Pläne formal ausführbar sind; bei fehlerhaften Subgoals kann das System auf Single-Agent-Planung zurückfallen und dadurch Execution Success erhalten. - Evaluation: evaluiert auf symbolischen PDDL-Domänen wie Barman, Blocksworld, Termes, Tyreworld und Grippers sowie in AI2-THOR/AlfWorld; Metriken sind Planning Time und Execution Length; Ergebnisse zeigen kürzere Planungszeiten gegenüber Multi-Agent-PDDL und teilweise kürzere parallele Ausführung. - Gap: zeigt, dass reine LLM-Planung keine Erfolgsgarantien bietet, während reine Multi-Agent-PDDL-Planung durch explodierende Suchräume teuer wird; robuste agentische Planung kann daher von hybriden LLM+symbolic-planning-Ansätzen profitieren.
A102: C107 | B102: S103 | C102: A survey on large language model based autonomous agents | D102: Wang et al. (2024) | E102: 2024 | F102: Frontiers of Computer Science | G102: DOI: 10.1007/s11704-024-40231-1 | H102: Survey / Journal Article | I102: wissenschaftliche Datenbank | J102: SPRINGER-01 | K102: Teilweise | L102: Include | N102: RQ1; RQ2; RQ3; RQ4; RQ5; Background; Methodik | O102: Nein | R102: - Relevantes A-/B+-Supporting-Include zu LLM-basierten autonomen Agenten, Agentenarchitektur, Memory, Planning, Action, Tool Use, Capability Acquisition und Evaluation; keine spezifische Webagenten-Primärstudie, aber sehr nützlich als Grundlagen- und Taxonomiequelle. - Architektur: schlägt ein vereinheitlichtes Agentenframework aus Profiling Module, Memory Module, Planning Module und Action Module vor; besonders relevant zur begrifflichen Strukturierung von LLM-Agenten und ihrer Komponenten. - Planung: unterscheidet Planning without Feedback und Planning with Feedback; behandelt Single-Path Reasoning, Multi-Path Reasoning, External Planner, Environmental Feedback, Human Feedback und Model Feedback; diskutiert u. a. CoT, ToT, ReAct, RAP, LLM+P, Reflexion und Self-Refine. - Memory/Action: beschreibt Short-Term/Long-Term Memory, Hybrid Memory, Memory Reading/Writing/Reflection sowie Action Goals, Action Production, Action Space, Tool Use, APIs, Datenbanken, externe Modelle und interne LLM-Fähigkeiten. - Evaluation/Gap: bietet breiten Überblick über Anwendungen und Evaluationsstrategien von LLM-Agenten; für Webagenten vor allem als theoretische Grundlage geeignet, da WebShop, Mind2Web und Web-Agenten erwähnt werden, aber nicht im Fokus stehen.
A103: C108 | B103: S104 | C103: Taming Uncertainty via Automation: Observing, Analyzing, and Optimizing Agentic AI Systems | D103: Moshkovich & Zeltyn (2025) | E103: 2025 | F103: IEEE/ACM ASE 2025 | G103: DOI: 10.1109/ASE63991.2025.00327 | H103: Position Paper / AgentOps Paper | I103: wissenschaftliche Datenbank | J103: IEEE-01 | K103: Ja | L103: Exclude | N103: RQ5; Gap | O103: Nein | R103: - Nur indirekt relevant für agentische Systeme allgemein; Fokus liegt auf AgentOps, Observability, Monitoring, Metric Collection, Issue Detection, Root Cause Analysis, Optimization Recommendations und Runtime Automation, nicht auf Webagenten, Webnavigation, Planning oder Replanning. - Kein Webagenten-Benchmark, keine Mind2Web/WebArena/WebShop/BrowserGym-Evaluation, keine konkrete Browser-/DOM-/UI-Agentenarchitektur und keine empirische Analyse von Webagenten-Trajektorien. - Kann höchstens als randständige Background-/Future-Work-Quelle genutzt werden, um zu erwähnen, dass deployed Agenten zusätzlich zu Benchmark-Evaluation auch Trace Observability, Root Cause Analysis und Self-Healing benötigen.
A104: C109 | B104: S105 | C104: A survey on LLM-based multi-agent systems: workflow, infrastructure, and challenges | D104: Li et al. (2024) | E104: 2024 | F104: Vicinagearth | G104: DOI: 10.1007/s44336-024-00009-2 | H104: Survey / Multi-Agent Systems Review | I104: wissenschaftliche Datenbank | J104: SPRINGER-01 | K104: Teilweise | L104: Exclude | N104: RQ1; RQ2; RQ3; Background; Gap | O104: Nein | R104: - Breiter Survey zu LLM-basierten Multi-Agent-Systemen; behandelt allgemeine MAS-Workflows, Infrastruktur und Herausforderungen, aber keine spezifische Webagenten-Primärstudie. - Nützlich als Hintergrundquelle für Multi-Agent-Taxonomie: Profile, Perception, Self-Action, Mutual Interaction und Evolution; außerdem relevant für allgemeine Begriffe wie Agentenrollen, Kommunikation, Memory, Reasoning, Planning und Self-Reflection. - Für die Kern-SLR nur begrenzt relevant, da kein Fokus auf Webnavigation, Browserumgebungen, DOM/UI-Grounding, Mind2Web, WebArena oder trajectory-level Webagent Evaluation liegt. - Aufgrund starker Redundanz mit anderen Agenten-/Planning-Surveys und deutlich spezifischeren Webagentenquellen eher nicht in die Hauptanalyse aufnehmen; optional nur kurz im Background verwenden, wenn Multi-Agent-Architekturen allgemein eingeführt werden.
A105: C110 | B105: S106 | C105: Case Studies - wohlinCaseStudies2024 | D105: Wohlin et al. (2024) | E105: 2024 | F105: Experimentation in Software Engineering / Springer | G105: DOI: 10.1007/978-3-662-69306-3_7 | H105: Book Chapter / Methodology | I105: wissenschaftliche Datenbank | J105: SPRINGER-01 | K105: Ja | L105: Exclude | N105: Methodik allgemein | O105: Nein | R105: - Methodikquelle zu Case-Study-Forschung in Software Engineering; definiert Case Studies als empirische Untersuchungen realer Fälle mit mehreren Datenquellen und real-life context. - Keine Webagentenstudie, keine LLM-Agentenarchitektur, keine Planning-/Replanning-Methode, keine Agenten-Evaluation und kein Benchmark. - Höchstens nützlich im Methodikteil, wenn abgegrenzt werden soll, was eine echte Case Study ist und warum kleine Demonstrationen oder Toy-Examples nicht als Case Study gelten.
A106: C111 | B106: S107 | C106: Generative AI | D106: Feuerriegel et al. (2024) | E106: 2024 | F106: Business & Information Systems Engineering | G106: DOI: 10.1007/s12599-023-00834-7 | H106: Conceptual / Catchword Article | I106: wissenschaftliche Datenbank | J106: SPRINGER-01 | K106: Teilweise | L106: Background | N106: Background; RQ1; Gap | O106: Nein | R106: - Allgemeiner Überblick zu Generative AI aus Information-Systems-/BISE-Perspektive; behandelt Modell-, System- und Anwendungsebene, Transformer, LLMs, RLHF, Prompt Learning, Foundation Models sowie sozio-technische Implikationen. - Inhaltlich nur randständig relevant für die SLR, da keine spezifische Webagentenstudie, keine Browser-/DOM-/UI-Interaktion, kein WebArena/Mind2Web/WebShop-Benchmark, keine konkrete Planning-/Replanning-Architektur und keine agentische Trajectory-Evaluation behandelt werden. - Kann höchstens im Background genutzt werden, um Generative AI allgemein zu definieren oder Limitationen wie Halluzinationen, Bias, Copyright und Umweltkosten kurz einzuordnen. - Aufgrund starker Redundanz mit spezifischeren Agenten-, Planning- und Webagentenquellen besser aus dem Kernkontext ausschließen.
A107: C112 | B107: S108 | C107: Generative artificial intelligence | D107: Banh & Strobel (2023) | E107: 2023 | F107: Electronic Markets | G107: DOI: 10.1007/s12525-023-00680-1 | H107: Fundamentals / Conceptual Article | I107: wissenschaftliche Datenbank | J107: SPRINGER-01 | K107: Teilweise | L107: Exclude | N107: Background; RQ1; Gap | O107: Nein | R107: - Allgemeines Grundlagenpaper zu Generative AI; behandelt Abgrenzung von AI, Machine Learning, Deep Learning und Generative AI sowie Deep Generative Models wie GANs, VAEs, Transformer/LLMs und Latent Diffusion Models. - Nützlich für allgemeine Begriffe wie Generativity, Variance, Prompting, probabilistische Output-Erzeugung, generative vs. discriminative AI sowie Model Layer, Connection Layer und Application Layer. - Für die Kern-SLR nur randständig relevant, da keine Webagentenstudie, keine Browser-/DOM-/UI-Interaktion, kein WebArena/Mind2Web/WebShop-Benchmark, keine Planning-/Replanning-Methode und keine agentische Trajectory-Evaluation behandelt werden. - Inhaltlich stark redundant zu Feuerriegel et al. 2024 und anderen allgemeineren GenAI-/LLM-Grundlagenquellen; daher besser aus dem Kernkontext ausschließen und höchstens für kurze Background-Definitionen verwenden.
A108: C113 | B108: S109 | C108: Large Language Model Agents | D108: Mathew & Rossi (2025) | E108: 2025 | F108: Engineering Information Systems with Large Language Models / Springer | G108: DOI: 10.1007/978-3-031-92285-5_8 | H108: Book Chapter / LLM-Agent Overview | I108: wissenschaftliche Datenbank | J108: SPRINGER-01 | K108: Teilweise | L108: Exclude | N108: RQ1; RQ2; RQ3; Background; Methodik | O108: Nein | R108: - Allgemeines Lehrbuch-/Übersichtskapitel zu LLM Agents und Multi-Agent-Systemen; behandelt Memory, Planning, Tools, Task Decomposition, Multiple Plan Selection, External Planners, Reflection/Refinement, ReAct, LangChain, LangGraph, CrewAI und OpenAI Swarm. - Inhaltlich als Background brauchbar, aber keine Webagenten-Primärstudie, keine Browser-/DOM-/UI-Interaktion, kein WebArena/Mind2Web/WebShop-Benchmark und keine eigenständige empirische Evaluation von Webagenten-Trajektorien. - Viele zentrale Inhalte sind in spezifischeren und stärkeren Quellen bereits abgedeckt, z. B. ReAct für Thought-Action-Observation, Planning Survey für Planning-Kategorien, Wang et al. 2024 für Agentenarchitektur und BrowserGym/WebPilot/Mind2Web für Webagenten. - Daher nicht in den Kernkorpus aufnehmen; höchstens als didaktische Background-Quelle für die allgemeine Agentenstruktur Memory + Planning + Tools oder für eine kurze Einführung in LLM-Agenten verwenden.
A109: C114 | B109: S110 | C109: Generative AI: A Review on Models and Applications | D109: Kaswan et al. (2023) | E109: 2023 | F109: ICCSAI 2023 / IEEE | G109: DOI: 10.1109/ICCSAI59793.2023.10421601 | H109: Review Paper / Generative AI Models & Applications | I109: wissenschaftliche Datenbank | J109: IEEE-01 | K109: Ja | L109: Exclude | N109: Background | O109: Nein | R109: - Allgemeines Review zu Generative AI, generativen Modellen und Anwendungen; behandelt GANs, VAEs, Flow-based Models, Generative Reinforcement Learning, Hybrid Architectures, Image Synthesis, Text Generation, Music, Drug Discovery, Healthcare sowie allgemeine Evaluationsmetriken und ethische Herausforderungen. - Für die SLR zu Webagenten und agentischer Planung nicht spezifisch genug: keine LLM-Webagenten, keine Browser-/DOM-/UI-Interaktion, kein WebArena/Mind2Web/WebShop-Benchmark, keine Planning-/Replanning-Architektur und keine agentische Trajectory-Evaluation. - Inhaltlich redundant zu allgemeineren und stärkeren GenAI-Grundlagenquellen wie Feuerriegel et al. 2024 oder Banh & Strobel 2023; zentrale Aussagen zu probabilistischer Generierung, Modellen, Bias und Evaluation sind im bestehenden Kontext bereits ausreichend abgedeckt. - Daher aus dem Kernkorpus ausschließen; höchstens als sehr allgemeiner Background zu Generative-AI-Modellfamilien nutzbar, aber nicht notwendig.
A110: C115 | B110: S111 | C110: The rise and potential of large language model based agents: a survey | D110: Xi et al. (2025) | E110: 2025 | F110: Science China Information Sciences | G110: DOI: 10.1007/s11432-024-4222-0 | H110: Survey / LLM-Based Agents | I110: wissenschaftliche Datenbank | J110: SPRINGER-01 | K110: Teilweise | L110: Include | N110: RQ1; RQ2; RQ3; RQ4; RQ5; Background; Gap | O110: Nein | R110: - Relevanter A-/B+-Supporting-Include zu LLM-based Agents; umfassender Survey zu Konstruktion, Anwendungen, Multi-Agent-Systemen, Human-Agent Interaction, Agent Societies, Evaluation, Risiken und offenen Problemen. - Architektur/Definition: schlägt ein allgemeines Framework aus Brain, Perception und Action vor; Brain umfasst Knowledge, Memory, Reasoning, Planning, Transferability und Generalization; Perception erweitert Agenten auf multimodale Inputs; Action umfasst Text, Tool Use und Embodied Actions. - Planung/Validierung: behandelt Reasoning, CoT, Self-Consistency, Self-Refine, Plan Formulation, Task Decomposition, hierarchische Planung, Plan Reflection, Feedback aus Modellen, Menschen und Umgebungen sowie Tool Use zur Erweiterung des Action Space. - Webagentenbezug: diskutiert Web Navigation als task-oriented deployment; nennt Webtasks wie Formulare, Online-Shopping und E-Mail sowie Ansätze mit HTML-Verständnis, Mind2Web, WebGum und multimodaler GUI-/Webseiteninteraktion. - Einschränkung: keine Webagenten-Primärstudie und keine eigene WebArena/Mind2Web/BrowserGym-Evaluation; daher nicht als A-Core-Webagentenpaper codieren, sondern als allgemeine Agenten-/Architektur-/Background-Quelle nutzen.
... A112: C117 | B112: S113 | C112: PlanAgent: A Multi-modal Large Language Agent for Closed-loop Vehicle Motion Planning | D112: Zheng et al. (2026) | E112: 2026 | F112: IEEE Transactions on Cognitive and Developmental Systems | G112: DOI: 10.1109/TCDS.2026.3664120 | H112: LLM-Agent / Autonomous Driving Planning Paper | I112: wissenschaftliche Datenbank | J112: IEEE-01 | K112: Teilweise | L112: Include | N112: RQ2; RQ3; RQ4; RQ5; Gap | O112: Nein | R112: - Methodisch relevantes Paper zu multimodalen LLM-Agenten, closed-loop motion planning, hierarchical chain-of-thought, planner code generation, Reflection, Simulation & Scoring und safety-oriented validation; keine Webagenten-Primärstudie. - Architektur: PlanAgent nutzt Environment Transformation zur Umwandlung der Umgebung in BEV Map und lane-graph-basierte Textbeschreibung, einen Reasoning Engine mit hierarchical CoT für Scene Understanding, Motion Instruction und Planner Generation sowie ein Reflection-Modul zur Simulation und Bewertung generierter Planner. - Planung/Validierung: relevant für RQ3/RQ4, weil das System nicht nur plant, sondern generierte Planner vor Ausführung simuliert, bewertet und bei zu niedrigem Score ein Rethinking/Replanning auslöst; dadurch wird Unsicherheit des MLLM reduziert. - Evaluation: evaluiert auf nuPlan Val14 und Test14-hard mit closed-loop Metriken NR-CLS und R-CLS; zeigt bessere bzw. konkurrenzfähige Ergebnisse gegenüber rule-based, learning-based und LLM-basierten Baselines; für Webagenten aber nur analog übertragbar. - Einschränkung: kein Browser, kein DOM/UI-Grounding, keine Webnavigation, kein WebArena/Mind2Web/WebShop/BrowserGym; daher nicht als A-Core-Webagentenpaper codieren, sondern höchstens als B-Supporting-Methodikquelle für closed-loop planning, Reflection und Safety Validation nutzen.
A113: C118 | B113: S114 | C113: LightVA: Lightweight Visual Analytics With LLM Agent-Based Task Planning and Execution | D113: Zhao et al. (2025) | E113: 2025 | F113: arXiv | G113: arXiv:2411.05651v2 | H113: Preprint / LLM-Agent Visual Analytics Paper | I113: Preprint-Suchquelle | J113: IEEE-01 | K113: Teilweise | L113: Exclude | N113: RQ2; RQ3; RQ4; Methodik | O113: Nein | R113: - LLM-Agent-basiertes Visual-Analytics-Paper mit Task Planning, Task Recommendation, Task Execution, Task Decomposition, Planner/Executor/Controller-Architektur, Human-Agent Collaboration, Visualisierungsgenerierung und Insight Discovery. - Methodisch interessant für allgemeine agentische Planung, weil LightVA High-Level-Analyseziele in ausführbare Tasks übersetzt, Tasks bei unvollständigen Ergebnissen on-demand decomposed und Fehler über Prompting, Self-Reflection, Catching/Feedback und User-Side Handling behandelt. - Für die Kern-SLR zu Webagenten jedoch nur indirekt relevant: keine Browser-/DOM-/UI-Interaktion, keine Webnavigation, kein WebArena/Mind2Web/WebShop/BrowserGym-Benchmark, keine Webtask-Trajectories und kein spezifisches Webagenten-Grounding. - Aufgrund fehlender Webagenten-Spezifität und Redundanz mit stärkeren Planning-/Webagentenquellen besser aus dem Kernkorpus ausschließen; höchstens als Background/Analogie für Planner-Executor-Controller, on-demand Task Decomposition und Human-Agent Collaboration nutzbar. | T113: aus vorhandenem PDF teilweise geprüft; Entscheidung: Exclude aus Kern-SLR, optional Background; stärkere Quellen für deine Analyse sind WebPilot, BrowserGym, Mind2Web, SeeAct, AI Planning Framework for Web Agents, Process Evaluation und Why Do LLM-based Web Agents Fail? | U113: Preprint-Suchquelle | V113: Background
A114: C119 | B114: S115 | C114: AKP: Actionable Knowledge-Augmented Agent Planning with Large Language Models | D114: Yu et al. | E114: 2025 | F114: IEEE | G114: DOI: 10.1109/INDIN64977.2025.11279013 | H114: Conference Paper / LLM-Agent | I114: wissenschaftliche Datenbank | J114: IEEE-01 | K114: Teilweise | L114: Include | N114: RQ3; RQ4; RQ5; Gap; Methodik | R114: Relevantes B-Supporting-Include zu LLM-Agent Planning, Long-Horizon Planning, MCTS, Lookahead, Backtracking, Verifier/Rewarder und actionable knowledge; keine Webagenten-Primärstudie, aber methodisch relevant für alternative Planning- und Validierungsmechanismen. - Methode: AKP erweitert LLM-basierte Agentenplanung um eine knowledgeable policy GVR, bestehend aus Generator, Verifier und Rewarder; der Generator schlägt mögliche nächste Aktionen vor, der Verifier prüft die Korrektheit/Ausführbarkeit von Aktionen, und der Rewarder bewertet längerfristig erfolgversprechende Aktionspfade. - Planung/Validierung: integriert GVR in Monte Carlo Tree Search, sodass nicht nur greedy der nächste Schritt generiert wird, sondern mögliche Aktionspfade über Selection, Expansion, Simulation und Backpropagation durchsucht, verglichen und iterativ verbessert werden; dadurch werden halluzinierte, widersprüchliche oder nicht ausführbare Action-Sequenzen reduziert. - Evaluation: evaluiert auf embodied/language-agent Umgebungen wie Put Block in Bowl, Tower of Hanoi und BabyAI mit Success Rate; AKP übertrifft IO, CoT, CoT-SC und ToT-Baselines, insbesondere bei längeren Aktionssequenzen und komplexeren Planungsaufgaben. - Einschränkung: kein Webagentenpaper, keine Browser-/DOM-/UI-Interaktion, keine WebArena/Mind2Web/WebShop/BrowserGym-Evaluation; daher nicht als A-Core-Webagentenpaper codieren, sondern als methodische Quelle für RQ3/RQ4 zu nicht-greedy Planning, Search, Verifikation und Replanning nutzen. aus vorhandenem PDF geprüft; Entscheidung: Include als B-Supporting Planning-Paper, weil MCTS-basiertes Lookahead/Backtracking und Verifier-/Rewarder-basierte Prüfung eine wichtige Alternative zu reinem greedy Action Generation, CoT oder ReAct darstellen; besonders für Diskussion zu Planning-Hallucination, Executability, Search-based Planning und Validierung von Aktionspfaden relevant; Snowballing prüfen zu Tree of Thoughts, LATS, RAP, KnowAgent, PlanGEN, MCTS für Language Agents, ReAct und Webagenten mit Tree Search/Verifier-Modulen wissenschaftliche Datenbank Datenbank
A115: C120 | B115: S116 | C115: LLM-Based Multi-Agent Framework for Automated Optical Network Optimization and Planning | D115: Li et al. (2025) | E115: 2025 | F115: 2025 Asia Communications and Photonics Conference (ACP) / IEEE | G115: https://doi.org/10.1109/ACP66871.2025.11350739 | H115: Conference Paper | I115: wissenschaftliche Datenbank | J115: IEEE-01 | K115: Teilweise | L115: Exclude | M115: Domänenspezifisches Paper zu optischer Netzwerkoptimierung und Netzwerkplanung; keine Webagentenstudie, keine Browser-/DOM-/UI-Interaktion, kein WebArena/Mind2Web/WebShop/BrowserGym-Benchmark, kein Long-Horizon-Webtask und kein explizites Replanning oder trajectory-level Webagent Evaluation. | N115: RQ2; RQ3; RQ5; Methodik | O115: Nein
A116: C121 | B116: S117 | C116: Engineering Critical Analysis Software Services: A Graph-RAG and Self-learning Large Language Model Agent Services Approach | D116: Yu et al. (2025) | E116: 2025 | F116: IEEE International Conference on Service-Oriented System Engineering (SOSE 2025) | G116: https://doi.org/10.1109/SOSE67019.2025.00005 | H116: Conference Paper | I116: wissenschaftliche Datenbank | J116: IEEE-01 | K116: Teilweise | L116: Exclude | M116: Zu domänenspezifisches Graph-RAG-/LLM-Service-Paper für aviation safety analytics; keine Webagentenstudie, keine Browser-/DOM-/UI-Interaktion, kein WebArena/Mind2Web/WebShop/BrowserGym-Benchmark, kein Long-Horizon-Webtask und kein explizites Planning/Replanning im Sinne der SLR. | N116: RQ2; RQ4; RQ5; Gap; Methodik | O116: Nein | R116: - Behandelt ein Graph-RAG- und Self-learning-LLM-Agent-Services-Framework für strukturierte kritische Analyse von AAIB-Air-Accident-Reports; methodisch interessant, aber nicht webagentenspezifisch. - Architektur: nutzt mehrere Edge-LLM-Services für Chunking/Vectorization, Knowledge Retrieval/Graph Construction und Response Generation sowie eine Corporate Knowledge Graph Memory zur dynamischen Wissensspeicherung. - Validierung/Evaluation: adressiert Halluzinationen über graphbasierte Konsistenzprüfung, Confidence Scoring und Fact Verification; evaluiert mit Precision@5, Fact Verification Score, Latency und Memory Usage. - Für die SLR nur randständig relevant als Background zu Graph-RAG, Knowledge-Graph-Memory, strukturierter Retrieval-Validierung und Halluzinationsreduktion; spezifischere Webagentenquellen decken Planning, Replanning, Prozessmetriken und Webtask-Evaluation deutlich besser ab.
A117: C122 | B117: S118 | C117: RRdE: A Decision Making Framework for Language Agents in Interactive Environments | D117: Zhou et al. (2024) | E117: 2024 | F117: IJCNN 2024 / IEEE International Joint Conference on Neural Networks | G117: https://doi.org/10.1109/IJCNN60899.2024.10650094 | H117: Conference Paper | I117: wissenschaftliche Datenbank | J117: IEEE-01 | K117: Teilweise | L117: Include | N117: RQ2; RQ3; RQ4; RQ5; Gap; Methodik | O117: Nein | R117: - Relevantes B+/A-Supporting-Include zu Language Agents in interaktiven Umgebungen, Long-Horizon Decision Making, Subgoal Decomposition, Replanning, World Graph, Memory und Reflection; keine direkte Webagentenstudie, aber methodisch stark übertragbar. - Architektur: RRdE nutzt einen World Graph zur Speicherung von Umweltinformationen wie Räumen, Items und Verbindungen, einen Memory Pool mit Trajectory/Experience sowie Planning/Replanning-, Reasoning- und Action-Generation-Schritte. - Planung/Validierung/Replanning: High-Level-Tasks werden zunächst in konkrete Subgoals zerlegt; während der Exploration prüft der Agent, ob Subgoals angepasst, rekonstruiert oder zurückgesetzt werden müssen, wodurch Goal Forgetting, Hallucination und Fehler durch lange Trajectories reduziert werden. - Evaluation auf AlfWorld und ScienceWorld mit Success Rate, Average Score, Estimated Tokens per Action und Ablationen zu Graph Use sowie Subgoal Decomposition/Replanning; berichtet 132/134 gelöste AlfWorld-Tasks und 82.16 Average Score auf ScienceWorld sowie deutlich geringere Tokenkosten pro Aktion gegenüber ReAct. - Forschungslücke: zeigt, dass interaktive Long-Horizon-Agenten strukturierte Umweltrepräsentation, explizite Subgoals und Replanning benötigen; Übertragung auf Webagenten wäre DOM/Accessibility-Tree als World Graph, Webtask-Subgoals, Memory und Replanning bei fehlgeschlagenen Browseraktionen.
A118: C123 | B118: S119 | C118: Multi-Agent Task Planning Method with Personalized Task Guidance in Power Systems | D118: Luan et al. (2025) | E118: 2025 | F118: Chinese Control Conference / IEEE | H118: Conference Paper | I118: wissenschaftliche Datenbank | J118: IEEE-01 | K118: Teilweise | L118: Exclude | M118: Domänenspezifisches Paper zu LLM-basierter Multi-Agent-Taskplanung und personalisierter Aufgabenführung in Power Systems; keine Webagentenstudie, keine Browser-/DOM-/UI-Interaktion, kein WebArena/Mind2Web/WebShop/BrowserGym-Benchmark, kein Long-Horizon-Webtask und kein explizites Replanning oder trajectory-level Webagent Evaluation. | N118: RQ2; RQ3; Methodik | O118: Nein | R118: - Behandelt ein Multi-Agent-Task-Planning-Framework für Power-System-Operationen mit LLM-basierter Task Decomposition, Agent Personas, Task Allocation und Perplexity-basierter Anpassung der Detailtiefe von Aufgabenbeschreibungen. - Methodisch nur indirekt relevant, weil es zeigt, wie Aufgaben an individuelle Profile, Expertise und Verständnisniveau angepasst werden können; dies ist eher Personalized Task Guidance als autonome Webagentenplanung. - Evaluation auf 100 Power-System-Taskbeschreibungen mit manueller Bewertung von Dekomposition, Allokation und Beschreibungskorrektheit sowie Recall; keine Webagentenmetriken wie Success Rate, Step Success Rate, Navigation Steps, Recovery Rate, Element Accuracy oder Token-/Kostenanalyse. - Für die SLR zu Webagenten bringt das Paper wenig zusätzlichen Mehrwert, da Task Decomposition, Agentenrollen und Planning bereits durch deutlich passendere Quellen wie WebDART, WebPilot, Aghzal et al. 2026, BrowserGym und AI Planning Framework for Web Agents abgedeckt sind.
A119: C124 | B119: S120 | C119: Leveraging Collective Intelligence in Agile Sprint Planning: A Comparative Study of LLM Architectures | D119: Muneer (2025) | E119: 2025 | F119: International Conference on Smart & Sustainable Technology (INCSST) / IEEE | G119: https://doi.org/10.1109/INCSST64791.2025.11210277 | H119: Conference Paper | I119: wissenschaftliche Datenbank | J119: IEEE-01 | K119: Ja | L119: Exclude | M119: Zu domänenspezifisch auf Agile Sprint Planning und Projektmanagement fokussiert; keine Webagentenstudie, keine Browser-/DOM-/UI-Interaktion, kein WebArena/Mind2Web/WebShop/BrowserGym-Benchmark, kein Long-Horizon-Webtask und keine trajectory-level Webagent Evaluation. | N119: RQ2; RQ3; Methodik | O119: Nein | R119: - Vergleicht drei LLM-Architekturen für agile Sprintplanung: Single LLM Agent, ReAct Agent und Multi-Agent-System mit spezialisierten Rollen wie Scrum Master, Lead Developer, QA Specialist und Product Owner. - Methodisch nur indirekt relevant durch Rollenverteilung, kollektive Multi-Agent-Entscheidungsfindung, ReAct-inspirierte Reflexion und Memory-basierte Interaktion. - Evaluation nutzt SMART-Kriterien wie Specificity, Measurability, Achievability, Relevance und Time-Boundedness, bewertet durch LLM-Judges; keine Webagentenmetriken wie Task Success Rate, Step Success Rate, Element Accuracy, Recovery Rate, Navigation Steps oder Token-/Kostenanalyse. - Für die SLR zu Webagenten bringt das Paper wenig zusätzlichen Erkenntnisgewinn, da Multi-Agent-Rollen, Planning, ReAct und prozessbezogene Evaluation bereits durch spezifischere und stärkere Quellen abgedeckt sind.
A120: C125 | B120: S121 | C120: H2R: Hierarchical Hindsight Reflection for Multi-Task LLM Agents | D120: Ye et al. (2025) | E120: 2025 | F120: IEEE International Conference on Agentic AI (ICA) | G120: https://doi.org/10.1109/ICA67499.2025.00030 | H120: Conference Paper | I120: wissenschaftliche Datenbank | J120: IEEE-01 | K120: Ja | L120: Include | N120: RQ2; RQ3; RQ4; RQ5; Gap; Methodik | O120: Nein | R120: - Relevantes B+/A-Supporting-Include zu LLM-Agenten, hierarchischer Memory-Architektur, Hindsight Reflection, Multi-Task Knowledge Transfer, Planning-/Execution-Trennung und Erfahrungswiederverwendung; keine direkte Webagentenstudie, aber methodisch stark übertragbar. - Architektur: H2R trennt High-Level Planning Memory und Low-Level Execution Memory; High-Level-Memory speichert Task Description, realisierte Subgoal-Sequenzen und Planning Insights, während Low-Level-Memory einzelne Subgoals, Subtrajectories und Execution Insights speichert. - Planung/Validierung: Planner nutzt High-Level-Memory zur Subgoal-Planung; Executor nutzt Low-Level-Memory zur konkreten Action-Ausführung und kann Subgoals als completed oder invalid markieren, wodurch neue Planung ausgelöst wird. - Evaluation: evaluiert auf AlfWorld und PDDLGame gegen ReAct und ExpeL; H2R erreicht 75.9 % Success Rate auf AlfWorld und 80.5 % auf PDDLGame; Ablation zeigt deutliche Performanceverluste ohne High-Level- oder Low-Level-Memory. - Forschungslücke: zeigt, dass grobe episodische Memory-Einheiten irrelevante Subgoals übertragen und Agenten ablenken können; robuste Agenten brauchen feingranulare, hierarchische und kontextbezogene Memory-Retrieval-Mechanismen.
A121: C126 | B121: S122 | C121: AgentPbD: Interactive Agentic Workflow Generation from User Demonstration on Web Browsers | D121: Li et al. (2025) | E121: 2025 | F121: IEEE VL/HCC 2025 | G121: https://doi.org/10.1109/VL-HCC65237.2025.00064 | H121: Demo / HCI & Web Automation Paper | I121: wissenschaftliche Datenbank | J121: IEEE-01 | K121: Ja | L121: Exclude | M121: Kein klassisches Webagenten-Evaluationspaper, sondern ein HCI-/Programming-by-Demonstration-System zur Generierung editierbarer agentischer Workflows aus Browser-Demonstrationen; direkte Webbrowser-Relevanz, aber keine autonome Webtask-Ausführung, kein WebArena/Mind2Web/WebShop/BrowserGym-Benchmark und keine starke empirische Evaluation. | N121: RQ2; RQ3; Methodik; Background | O121: Nein | R121: - Behandelt AgentPbD, ein System, das einzelne User-Demonstrationen im Webbrowser aufzeichnet und daraus task-level agentic workflows erzeugt. - Architektur: sammelt Browseraktionen wie Klicks, Texteingaben, Form Submissions und URL Navigationen plus DOM-Kontextdaten; ein Multi-Agent-Backend aus Action Agent, Context Agent, Synthesizer Agent und Evaluator Agent erzeugt daraus einen strukturierten Workflow im JSON-Format. - Methodisch relevant für Workflow-Induktion, Web Automation, User Intent Inference, Human-in-the-loop Editing und die Abstraktion von Low-Level-Browseraktionen zu High-Level-Subtasks. - Einschränkung: Das Paper demonstriert vor allem Workflow-Generation und Interface-Design; Workflow-Ausführung und User Study werden als nächste Schritte genannt, sodass keine belastbare Webagenten-Performance-Evaluation, kein Replanning und keine trajectory-level Metriken vorliegen.
A122: C127 | B122: S123 | C122: Towards Responsible Generative AI: A Reference Architecture for Designing Foundation Model Based Agents | D122: Lu et al. (2024) | E122: 2024 | F122: arXiv Preprint | G122: arXiv:2311.13148v3 | H122: Reference Architecture / Responsible AI & FM-based Agents | I122: Preprint-Suchquelle | J122: IEEE-01 | K122: Teilweise | L122: Exclude | M122: Allgemeines Reference-Architecture-Paper für Foundation-Model-based Agents; keine Webagentenstudie, keine Browser-/DOM-/UI-Interaktion, kein WebArena/Mind2Web/WebShop/BrowserGym-Benchmark und keine konkrete Webtask- oder trajectory-level Evaluation. | N122: RQ2; RQ4; RQ5; Gap; Background | O122: Nein | R122: - Behandelt eine pattern-orientierte Referenzarchitektur für FM-/LLM-basierte Agenten mit Interaction Engineering, Memory, Planning, Execution Engine, Multi-Agent Cooperation, Tool/Agent Selection und Responsible-AI-Plugins. - Methodisch interessant für allgemeine Agentenarchitektur und Responsible AI, insbesondere durch Guardrails, Continuous Risk Assessor, Black Box Recorder, Explainer, AIBOM Registry und Co-Versioning Registry. - Für die Kern-SLR zu Webagenten aber nur indirekt relevant, da keine autonome Webnavigation, kein DOM-/UI-Grounding, keine Webagentenbenchmarks und keine empirische Analyse von Webtask-Trajectories behandelt werden. - Der Beitrag ist eher Architektur-/Governance-Background; konkrete Konzepte zu Planning, Replanning, Evaluation und Prozessmetriken werden durch spezifischere Quellen wie WebPilot, WebDART, BrowserGym, Process Evaluation und AI Planning Framework for Web Agents besser abgedeckt.
A123: C128 | B123: S124 | C123: PWA: Process-Level Web Agent Reinforcement Learning | D123: Fu et al. (2026) | E123: 2026 | F123: ICASSP 2026 / IEEE | G123: https://doi.org/10.1109/ICASSP55912.2026.11460752 | H123: Conference Paper / WebAgent RL Paper | I123: wissenschaftliche Datenbank | J123: IEEE-02 | K123: Ja | L123: Include | N123: RQ2; RQ3; RQ4; RQ5; Gap; Methodik | O123: Nein | R123: - Sehr relevantes A-Core-Include zu Webagenten, WebArena-Lite, Reinforcement Learning, Process Reward Models, step-level reward supervision und value-free Web RL; direkte Webagenten-Primärstudie. - Problemstellung: Bestehende Webagent-RL-Methoden wie DigiRL und WebRL nutzen überwiegend finale Outcome Rewards, wodurch Webtasks mit langen Trajectories unter sparse rewards und ungenauer Credit Assignment leiden; korrekte Zwischenschritte in fehlgeschlagenen Trajectories werden dadurch falsch bewertet. - Methode: PWA konstruiert ein webbasiertes Process Reward Model über Reward Shaping mit binary feedback; das PRM bewertet einzelne Aktionen anhand von HTML-State, Action History und Instruction mit YES/NO bzw. YES-Wahrscheinlichkeit. - Training: führt ein value-free Web-RL-Verfahren ein, das normalisierte step-level Q-Werte aus PRM- und ORM-Signalen nutzt, ohne separat ein Value Model zu trainieren; dadurch sollen Value-Bias und Trainingsaufwand reduziert werden. - Evaluation: evaluiert auf WebArena-Lite mit Websites wie Reddit, GitLab, CMS, OpenStreetMap/MAP und OSS; PWA übertrifft SFT, DigiRL und WebRL im Durchschnitt und zeigt weniger stuck trajectories; PRM stimmt stärker mit Human Labels überein als GPT-4o-basierte Prozessbewertungen. - Forschungslücke: zeigt, dass reine Enderfolgsmetriken und outcome-only RL für Webagenten nicht ausreichen; robuste Webagenten benötigen step-level Prozessbewertung, feinere Credit Assignment und prozessbezogene Trainingssignale.
A124: C129 | B124: S125 | C124: WebRouter: Query-Specific Router via Variational Information Bottleneck for Cost-Sensitive Web Agent | D124: Li et al. (2026) | E124: 2026 | F124: ICASSP 2026 / IEEE | G124: https://doi.org/10.1109/ICASSP55912.2026.11464950 | H124: Conference Paper / Cost-Sensitive WebAgent Routing | I124: wissenschaftliche Datenbank | J124: IEEE-02 | K124: Ja | L124: Include | N124: RQ2; RQ5; Gap; Methodik | O124: Nein | R124: - Relevantes A-/B+-Include zu cost-sensitive Web Agents, LLM Routing, WebVoyager, Webagent-Kostenreduktion und Efficiency Evaluation; direkte Webagentenstudie, aber kein primäres Planning-/Replanning-Paper. - Problemstellung: LLM-brained Web Agents nutzen komplexe Prompts aus User Goal, Action History und Web State; leistungsstarke Modelle erhöhen Kosten stark, während Accuracy-Gewinne oft begrenzt sind. - Methode: WebRouter lernt einen query-spezifischen Router mit cost-aware Variational Information Bottleneck, der redundante Promptinformationen komprimiert und pro Webagent-Query ein geeignetes LLM auswählt. - Evaluation: evaluiert auf fünf WebVoyager-Websites wie Apple, Arxiv, Coursera, Google und Huggingface; misst Accuracy, Preis, Schritte und Laufzeit; WebRouter senkt Kosten gegenüber GPT-4o stark bei nur geringem Accuracy-Verlust. - Forschungslücke: zeigt, dass Webagenten-Evaluation neben Task Success auch operational cost, token costs, runtime und model-routing decisions berücksichtigen sollte; besonders relevant für skalierbare reale Webagenten-Deployments.
A125: C131 | B125: S126 | C125: Self-Reflection in Large Language Model Agents: Effects on Problem-Solving Performance | D125: Renze & Guven (2024) | E125: 2024 | F125: FLLM 2024 / IEEE | G125: https://doi.org/10.1109/FLLM63129.2024.10852426 | H125: Conference Paper / Self-Reflection Evaluation | I125: wissenschaftliche Datenbank | J125: IEEE-03 | K125: Teilweise | L125: Exclude | M125: Allgemeines Self-Reflection-Paper zu LLM-Agenten auf Multiple-Choice-Problemen; keine Webagentenstudie, keine Browser-/DOM-/UI-Interaktion, kein WebArena/Mind2Web/WebShop/BrowserGym-Benchmark, keine Tool-Nutzung und keine echte multi-step trajectory-level Agentenevaluation. | N125: RQ4; Gap; Background | O125: Nein | R125: - Untersucht acht Typen von Self-Reflection bei LLM-Agenten, darunter Retry, Keywords, Advice, Explanation, Instructions, Solution und Composite, und misst deren Effekt auf Multiple-Choice-Question-Answering. - Methodisch interessant als allgemeiner Beleg, dass Self-Reflection nach Fehlerfeedback die Problem-Solving-Accuracy von LLMs verbessern kann; besonders informationsreiche Reflexionen wie Explanation, Solution und Composite wirken stärker als einfache Retry-/Keyword-Varianten. - Für die Kern-SLR zu Webagenten aber nur indirekt relevant, weil die Experimente single-step MCQA-Aufgaben nutzen und keine interaktive Webumgebung, keine Browseraktionen, kein Replanning während einer Task, keine Tool-Fehler und keine Webagent-Trajectories untersuchen. - Der Beitrag ist redundant zu stärkeren agentischen und webnäheren Quellen zu Reflection, Feedback, Replanning und Prozessbewertung, z. B. Reflexion, H2R, RRdE, Process Evaluation, PWA und Webagent-Failure-Analysen.
A126: C132 | B126: S127 | C126: TGPO: Tree-Guided Preference Optimization for Robust Web Agent Reinforcement Learning | D126: Chen et al. (2026) | E126: 2026 | F126: ICASSP 2026 / IEEE | G126: https://doi.org/10.1109/ICASSP55912.2026.11464574 | H126: Conference Paper / WebAgent RL Paper | I126: wissenschaftliche Datenbank | J126: IEEE-03 | K126: Teilweise | L126: Exclude | M126: Das Paper ist direkt webagentenbezogen, fokussiert jedoch primär auf Offline Reinforcement Learning und Preference Optimization für Webagenten. Da Reinforcement Learning nicht im Fokus der SLR steht, wird das Paper nicht in den Kernkorpus aufgenommen. Die für die Arbeit relevanten Aspekte — step-level Feedback, Prozessreward, Credit Assignment und Reduktion redundanter Aktionen — werden bereits durch passendere Quellen abgedeckt. RL kann in der Synthese lediglich als häufiger Trainingsansatz für Webagenten erwähnt werden. | N126: RQ4; RQ5; Gap | O126: Nein | R126: - Behandelt Tree-Guided Preference Optimization für Webagenten-RL mit tree-structured trajectory representation, Process Reward Model, Preference Pairs und dynamischer Gewichtung kritischer Entscheidungspunkte. - Methodisch relevant für step-level credit assignment, Reward Sparsity, Label-Konflikte und redundante Aktionen in Webagent-Trajectories. - Evaluiert auf Online-Mind2Web und C-WebShop mit Browser-use und SeeAct; berichtet höhere Success Rates und weniger redundante Steps gegenüber SFT, KTO, KTO-Tree und DPO. - Für die vorliegende SLR jedoch eher auszuschließen, wenn Reinforcement Learning nicht untersucht wird; die relevanten Punkte zu Prozessbewertung und Step-Level Feedback werden durch PWA, Process Evaluation, BrowserGym und Webagent-Failure-Analysen ausreichend und passender abgedeckt.
A127: C133 | B127: S128 | C127: Enhancing Cognitive Digital Twin Interaction using an LLM Agent | D127: Šturm et al. (2024) | E127: 2024 | F127: MIPRO 2024 / IEEE | G127: https://doi.org/10.1109/MIPRO60963.2024.10569919 | H127: Conference Paper / Conceptual LLM-Agent Architecture | I127: wissenschaftliche Datenbank | J127: IEEE-03 | K127: Teilweise | L127: Exclude | M127: Konzeptuelles Paper zu LLM-Agenten für Cognitive Digital Twins; keine Webagentenstudie, keine autonome Browser-/DOM-/UI-Interaktion, kein WebArena/Mind2Web/WebShop/BrowserGym-Benchmark, kein Long-Horizon-Webtask und keine trajectory-level Evaluation. | N127: RQ2; RQ4; Background | O127: Nein | R127: - Behandelt eine konzeptuelle Architektur für die Interaktion mit Cognitive Digital Twins über einen LLM-Agenten, inklusive Query Enrichment, Data Source Selection, Data Retrieval/Aggregation, Antwortgenerierung und User Feedback. - Methodisch nur am Rand relevant durch Web Crawling, Datenquellenauswahl, Quellenbezug, Transparenz/Erklärbarkeit und Feedback Loop. - Kein Fokus auf autonome Webagenten, Browseraktionen, Element Grounding, Planning/Replanning oder Webtask-Ausführung; die Web-Komponente dient primär der Datenbeschaffung aus Webseiten. - Für die SLR zu Webagenten bringt das Paper wenig zusätzlichen Erkenntnisgewinn, da die relevanten Aspekte zu Agentenarchitektur, Prozessbewertung und Webinteraktion durch spezifischere Quellen besser abgedeckt sind.
A128: C134 | B128: S129 | C128: Master-Agent Orchestrated Multi-Agent Systems: An Automated Framework for Task-Driven Dynamic Agent Creation | D128: Roy et al. (2025) | E128: 2025 | F128: ICECET 2025 / IEEE | G128: https://doi.org/10.1109/ICECET63943.2025.11472254 | H128: Conference Paper / Generic Multi-Agent Framework | I128: wissenschaftliche Datenbank | J128: IEEE-03 | K128: Teilweise | L128: Exclude | M128: Generisches Multi-Agent-Orchestration-Paper mit dynamischer Agentenerstellung; keine Webagentenstudie, keine Browser-/DOM-/UI-Interaktion, kein WebArena/Mind2Web/WebShop/BrowserGym-Benchmark, kein Long-Horizon-Webtask und keine trajectory-level Webagent Evaluation. | N128: RQ2; RQ3; Background | O128: Nein | R128: - Behandelt ein Master-Agent-orchestriertes Multi-Agent-Framework, in dem ein Master Agent Aufgaben plant, Subtasks verteilt, vorhandene Worker Agents auswählt und bei Bedarf neue Agents dynamisch über einen Prompter Agent erstellt. - Methodisch am Rand relevant für allgemeine Agentenarchitektur, Task Decomposition, Agent Selection, dynamische Agent Creation und rollenbasierte Multi-Agent-Orchestrierung. - Die Evaluation besteht aus domänenspezifischen Use Cases wie Code Debugging, AP Helpdesk Automation und Sentiment Analysis; Metriken sind Agent Allocation Accuracy, Response Accuracy und Latency, aber keine Webagenten- oder Trajectory-Metriken. - Für die SLR zu Webagenten bringt das Paper wenig zusätzlichen Erkenntnisgewinn, da Planning, Rollenverteilung und Multi-Agent-Orchestrierung bereits durch spezifischere und webnähere Quellen besser abgedeckt sind.
A129: C135 | B129: S130 | C129: Agentic Recommender Systems: A Systematic Literature Review | D129: da Silva Portugal et al. (2026) | E129: 2026 | F129: IEEE Transactions on Software Engineering | G129: https://doi.org/10.1109/TSE.2026.3657900 | H129: Systematic Literature Review / Agentic Recommender Systems | I129: wissenschaftliche Datenbank | J129: IEEE-03 | K129: Teilweise | L129: Exclude | M129: Survey zu agentischen Recommender-Systemen; keine Webagenten-Primärstudie, keine Browser-/DOM-/UI-Interaktion, kein WebArena/Mind2Web/WebShop/BrowserGym-Benchmark, kein Long-Horizon-Webtask und keine trajectory-level Webagent Evaluation. | N129: RQ1; RQ2; RQ5; Background | O129: Nein | R129: - Umfangreicher SLR zu Agentic Recommender Systems mit Fokus auf LLM-Agenten in Empfehlungssystemen, Agentenrollen, Agentenbeziehungen, Prompt-Strukturen, Integrationen, Use Cases, Recommendation Strategies und Evaluation. - Methodisch am Rand relevant durch Rollen wie Manager, Recommender, Interpreter, Goal Planner, User Agent, Item Agent, Searcher, Reflector, Responder und Feedback Agent sowie durch Diskussion von ICL, RAG, Fine-Tuning, Tools und Prompt Engineering. - Für die SLR zu Webagenten jedoch nur indirekt relevant, da die Domäne Recommender Systems ist und keine autonome Webnavigation, DOM-/UI-Grounding, Webtask-Ausführung, Planning/Replanning in Browserumgebungen oder Webagenten-Benchmarks untersucht werden. - Evaluation fokussiert typische Recommender-System-Metriken wie nDCG@k und Recall@k, nicht Webagentenmetriken wie Task Success Rate, Step Success Rate, Element Accuracy, Navigation Steps, Recovery Rate oder trajectory-level Prozessqualität.
...

Sheet 03_Extraction
A1: Study_ID | B1: Candidate_ID | C1: BibTeX_Key | D1: Titel | E1: Autor_Jahr | F1: Publikationstyp | G1: Peer_reviewed | H1: Benchmark/Umgebung | I1: Domäne | J1: Agententyp | K1: Architektur/Komponenten | L1: Planung_vorhanden | M1: Planungsform | N1: Planungshorizont | O1: Subgoals/Hierarchie | P1: Validierung_vorhanden | Q1: Validierungsart | R1: Replanning_vorhanden | S1: Replanning_Intervall/Trigger | T1: Feedbackquelle | U1: Metriken_Erfolg | V1: Metriken_Kosten | W1: Metriken_Zeit | X1: Prozessmetriken | Y1: Zentrale_Befunde | Z1: Limitationen | AA1: Research_Gap | AB1: Relevanz_Thesis | AC1: RQ1 | AD1: RQ1_Begründung | AE1: RQ2 | AF1: RQ2_Begründung | AG1: RQ3 | AH1: RQ3_Begründung | AI1: RQ4 | AJ1: RQ4_Begründung | AK1: RQ5 | AL1: RQ5_Begründung | AM1: Nutzbar_für | AN1: Seiten/Zitate | AO1: Notizen
A2: S001 | B2: C001 | C2: erdoganPLANANDACTImprovingPlanning2025 | D2: Plan-and-Act: Improving Planning of Agents for Long-Horizon Tasks | E2: Erdogan et al. 2025 | F2: / ACM | G2: Ja | H2: WebArena-Lite; WebArena; WebVoyager; web navigation mit HTML-Observationen; diverse Websites wie OpenStreetMap, Reddit, GitLab, CMS, OneStopShop | I2: Webnavigation; digitale Long-Horizon-Aufgaben | J2: LLM-basierter Webagent; dualer Planner-Executor-Agent | K2: PLANNER erzeugt strukturierte High-Level-Pläne; EXECUTOR übersetzt Pläne in konkrete umgebungsspezifische Aktionen; Environment/HTML-Observation; CoT-Reasoning vor Plan-/Action-Generierung; synthetische Datenpipeline mit Action Trajectory Generation, Grounded Plan Generation, Synthetic Plan Expansion und Targeted Augmentation; ORM-Filter für erfolgreiche Trajektorien | L2: Ja | M2: Explizite High-Level-Planung vor Ausführung; strukturierte Schrittpläne; dynamisches Replanning nach Ausführungsschritten; CoT als vorgelagertes Reasoning | N2: Nicht als fixer numerischer Horizon definiert; komplexe multi-step / long-horizon Webaufgaben | O2: Ja; User Goal wird in Subgoals/Steps zerlegt; klare Trennung von High-Level-Plan und Low-Level-Aktion | P2: Teilweise | Q2: Keine separate Runtime-Validierungsinstanz; Environment-Feedback/HTML dient zur Aktualisierung; ORM LLM filtert synthetische Trajektorien in der Datengenerierung; Benchmark-Erfolg binär geprüft | R2: Ja | S2: Nach jeder EXECUTOR-Aktion bzw. Iteration; Trigger ist aktueller Environment-State/HTML plus vorherige Pläne und Aktionen; adressiert dynamische Inhalte und unerwartete Ausführungszustände | T2: HTML-/Environment-Observationen; vorherige Pläne und Aktionen; ORM-Bewertung erfolgreicher Trajektorien; Benchmark-Success-Labels | U2: Success Rate / Accuracy; WebArena-Lite 57.58% mit CoT; WebArena 45.7% Llama-70B und 48.15% QWQ-32B; WebVoyager 58.08% Llama-3.1-8B und 81.36% QWQ-32B | V2: Nicht berichtet für Tokenkosten | W2: Keine Agent-Ausführungszeit quantifiziert; Datengenerierung: 15,000 synthetische Trainingsbeispiele unter einer Stunde; Replanning nach jeder Aktion wird als potenziell ineffizient und langsam beschrieben | X2: Ablationen zu Planner/Executor-Varianten; statischer vs. dynamischer Planner; CoT-Vergleich; Success Rate nach Benchmark; keine detaillierten Token-, Runtime- oder prozessbezogenen Fehlerkosten | Y2: Explizite Trennung von Planung und Ausführung verbessert Long-Horizon-Webnavigation; synthetisch trainierter Planner ist zentral; Dynamic Replanning steigert WebArena-Lite von 43.63% auf 53.94%; CoT steigert weiter auf 57.58%; Planqualität wird als wichtiger Engpass gegenüber reiner Action-Trajectory-Vermehrung gezeigt | Z2: Abhängigkeit von Basisagent für erfolgreiche Trajektoriensammlung; bei Datensätzen ohne Trainingsdaten wie WebVoyager Abhängigkeit von Base Model; Replanning nach jeder Aktion kann ineffizient und langsam sein; keine Tokenkosten/Agent-Laufzeit; multimodale Inputs, RL-Planoptimierung und Memory nur als Future Work | AA2: Offen bleibt, wann validiert oder replanned werden sollte; Effizienztrade-offs von Replanning-Frequenz, Tokenkosten und Runtime werden nicht kontrolliert gemessen; adaptive Replanning-Trigger werden als zukünftige Arbeit genannt | AB2: hoch; direktes Core-Webagenten-Paper für Planner-Executor-Architekturen, Long-Horizon Planning, Replanning und Benchmark-Success-Rates | AC2: mittel | AD2: Liefert Arbeitsverständnis zu Language Agents, Web Agents und Long-Horizon Tasks, aber keine systematische Definitionstaxonomie | AE2: hoch | AF2: Klare Planner-Executor-Architektur mit getrennten Komponenten für Planung und Ausführung | AG2: hoch | AH2: Explizite Planung, Subgoal-Erzeugung, synthetisches Planner-Training und Einbindung in Ausführung | AI2: hoch | AJ2: Dynamic Replanning nach jeder Aktion; Validierung nur teilweise über Environment-Feedback und ORM | AK2: hoch | AL2: Starke Benchmark- und Success-Rate-Evidenz; Tokenkosten und Laufzeit fehlen | AM2: Core Webagent; Architektur; Planung --> Planner-Executor; Planungshorizont -- Long-Horizon Planning; Replanning --> Replanning; Evaluation --> Success Rate; Research Gap | AN2: Abstract; Figure 1; Figure 2; Section 3.1-3.4; Section 4.1-4.3; Table 1; Table 3; Table 4; Limitations | AO2: Screening-Notiz plausibel: Include; hohe Relevanz für RQ2-RQ5 und Gap; kein Widerspruch gefunden; arXiv:2503.09572v3; wissenschaftliche Datenbank / Preprint
A3: S002 | B3: C002 | C3: wangWhyReasoningFails2026 | D3: Why Reasoning Fails to Plan: A Planning-Centric Analysis of Long-Horizon Decision Making in LLM Agents | E3: Wang et al. 2026 | F3: Preprint / arXiv | G3: Nein | H3: KGQA mit CWQ, WebQSP und GrailQA; ALFWorld via AgentGym als Tool-Use-Umgebung; kontrollierte deterministische Umgebungen mit expliziten Zuständen, Transitionen und Evaluationssignalen; Frameworks: Think-on-Graph, Plan-on-Graph, ReAct, Reflexion | I3: LLM-Agenten; Long-Horizon Decision Making; Knowledge-Graph-Question-Answering; Tool Use; Methodology/Background für Webagenten | J3: LLM-basierter Agent mit planungszentriertem Entscheidungsmechanismus; kein Core-Webagent | K3: FLARE mit explicit lookahead; Monte-Carlo-Tree-Search; action pruning; trajectory-level evaluation; trajectory memory; backward value propagation; receding-horizon commitment; Vergleich mit single step, beam search und lookahead | L3: Ja | M3: Future-aware planning; explizite Rollouts; Bewertung von Zukunftstrajektorien; Rückpropagation von Trajectory Returns; begrenzte Bindung an nur die nächste Aktion; Reasoning wird als step-wise greedy policy modelliert | N3: Required planning horizon in Analysen von 2 bis 8+; KGQA als multi-hop graph traversal; FLARE-Simulationshorizont standardmäßig H=3; ALFWorld als Long-Horizon Tool-Use-Setting | O3: Nicht als Subgoal-Hierarchie berichtet; Planung erfolgt über Zustände, Aktionen, Trajektorien, Suchbaum und Kandidaten-Futures | P3: Ja | Q3: Evaluative feedback ist zur Planungszeit verfügbar; trajectory-level reward/return; LLM-basierte relative Bewertung mehrerer Trajektorien; Benchmark-Evaluation über Hits@1 und Success Rate | R3: Ja | S3: Receding-horizon replanning nach jeder Transition; FLARE commitet nur zur nächsten Aktion und plant nach Zustandswechsel neu | T3: Explizite State Transitions; evaluative signal r̂; LLM trajectory scoring; gespeicherte Trajectory Memory; Benchmark-Ground-Truth | U3: KGQA: Hits@1; Table 1 zeigt FLARE Average CWQ 71.8, WebQSP 89.9, GrailQA 87.8; ALFWorld: Success Rate, ReAct+FLARE 77.8%; Reflexion+FLARE laut Figure 4 82% | V3: Explizite Tokenbudgets berichtet; Figure 3 Performance-Budget-Trade-off; Table 4: FLARE Full 74.9 Hits@1 bei 21k Tokens; w/o Pruning Hits@1-aligned 75.4 bei 61k Tokens; w/o Memory 74.6 bei 34k Tokens; Token-Aligned ohne Memory 72.7 bei 22k Tokens | W3: Keine Wall-Clock-Laufzeit berichtet; theoretische Komplexität im Appendix; FLARE tauscht zusätzliche Berechnung gegen Lookahead und Value Propagation | X3: First-step trap selection; first-error step; recovery after first error; correct decision prefixes; Table 3: FLARE Trap@1 17.8%, First-Error Step 3.2, Recovery@First-Error 29.7%; Single Step Trap@1 55.6%, First-Error Step 1.6, Recovery 5.4% | Y3: Reasoning ist nicht gleich Planning; step-wise reasoning führt zu myopischen frühen Commitments; Beam Search erhöht Breite, löst aber das strukturelle Problem nicht; Lookahead und Value Propagation verbessern Long-Horizon-Stabilität; FLARE verbessert Accuracy, Recoverability und Token-Effizienz gegenüber reasoning-basierten Strategien | Z3: Empirie fokussiert auf kontrollierte deterministische Umgebungen mit strukturierten Action Spaces; Annahme eines Evaluationssignals zur Planungszeit; KGQA ist kein offenes Websetting; stochastische Dynamiken, Partial Observability, Non-Stationarity und gelernte World Models nicht abgedeckt; stärkere Planung kann Safety-Risiken erhöhen | AA3: Offen bleibt, wie future-aware planning in offenen Webumgebungen mit partieller Beobachtbarkeit, unsicherem Feedback, Laufzeitkosten und Safety Constraints umgesetzt wird; Trade-off zwischen Lookahead, Replanning-Frequenz, Tokenbudget und realer Ausführungszeit bleibt für Webagenten experimentell zu prüfen | AB3: hoch; wichtiges Methodology-/Background-Paper für Planung, Replanning, Prozessmetriken, Tokenkosten und Gap-Ableitung; nicht als Core-Webagent codieren | AC3: mittel | AD3: Begrenzt LLM reasoning, planning und long-horizon decision making klar voneinander ab; keine spezifische Webagenten-Definition | AE3: niedrig | AF3: Keine Webagentenarchitektur im engeren Sinn; liefert aber allgemeine Agenten- und Planning-Komponenten | AG3: hoch | AH3: Planung wird formal, empirisch und mechanistisch als future-aware lookahead mit value propagation analysiert | AI3: hoch | AJ3: Receding-horizon replanning nach jeder Transition; Fehlererkennung über first-error, trap selection und recovery metrics | AK3: hoch | AL3: Breite Evaluation mit Hits@1, Success Rate, Tokenbudget und Prozessmetriken; keine Wall-Clock-Laufzeit | AM3: Methodology; Planungshorizont -- Long-Horizon Planning; Replanning --> Replanning; Evaluation --> Success Rate; Kosten; Fehler/ Prozess; Research Gap | AN3: Abstract; Section 2; Figure 1; Figure 2; Section 3.1-3.3; Section 4; Table 1; Table 3; Figure 3; Table 4; Table 5; Limitations and Scope | AO3: Screening-Notiz plausibel: Include für RQ3, RQ4, RQ5 und Gap; nicht als Core-Webagent, sondern als planungszentriertes Methodology-/Background-Paper codieren; arXiv:2601.22311v1; wissenschaftliche Datenbank
A4: S003 | B4: C003 | C4: xieRevealingBarriersLanguage2025 | D4: Revealing the Barriers of Language Agents in Planning | E4: Xie et al. 2025 | F4: Conference Paper | G4: Ja | H4: BlocksWorld; TravelPlanner im Sole-Planning-Modus; NAACL-HLT 2025; Evaluierung über 9 Modelle und mehrere Strategien | I4: Domänenübergreifende Language-Agent-Planung; klassische Planung; Travel Planning; Methodik/Diagnose | J4: LLM-basierter Language Agent; kein Core-Webagent; Planning-Modul innerhalb allgemeiner Agentenarchitektur | K4: Konzeptuelle Agentenkomponenten: Memory Module, Tool-use Module, Planning Module; untersuchte Strategien: Direct Prompting, Episodic Memory Updating, Parametric Memory Updating; Feature-Attribution-Analyse von Constraints und Questions | L4: Ja | M4: Planung als Generierung einer Aktions- bzw. Reiseplansequenz; umfasst Goal Decomposition, Constraint Consideration und Foresight; Fokus auf interne Planungsfähigkeit statt Tool Use | N4: Planning Horizon über Anzahl generierter BlocksWorld-Schritte bzw. TravelPlanner-Tage operationalisiert; Leistung und Question-Attribution sinken mit wachsendem Horizont | O4: Ja; indirekt über Goal/Question, Constraints und Aktionssequenz; keine explizite hierarchische Subgoal-Architektur | P4: Teilweise | Q4: Keine Runtime-Validierung; Constraints und Questions werden als zentrale Planungsinformationen analysiert; Benchmark-Evaluator prüft Accuracy/Pass Rate; Permutation Feature Importance misst, ob Informationen tatsächlich den Plan beeinflussen | R4: Nein | S4: Nicht berichtet; Episodic Memory Updating nutzt vergangene Versuche/Feedback, ist aber kein Runtime-Replanning während der Ausführung | T4: Prompt-Komponenten; Constraint Descriptions; Questions; Episodic Memory Insights; Ground Truth Plans; Solver-/Evaluator-Feedback; Benchmark-Evaluator | U4: BlocksWorld Accuracy; TravelPlanner Final Pass Rate; Commonsense Micro/Macro; Hard Constraint Micro/Macro; OpenAI o1 erreicht nur 15.6% auf TravelPlanner; Direct Prompting bleibt meist deutlich unter Human-Level | V4: Nicht berichtet; keine Tokenkosten; hoher Rechenaufwand für Attribution und Fine-tuning erwähnt | W4: Keine Laufzeitmetriken berichtet; Training/Inference teils auf 8xA100; TravelPlanner-Kontext als rechenintensiv beschrieben | X4: Permutation Feature Importance Attribution Scores; Constraint Attribution; Question Attribution über Planungsschritte/Tage; Episodic Memory Attribution; Performance nach Planungshorizont; Commonsense- und Hard-Constraint-Erfüllung | Y4: Language Agents berücksichtigen Constraints zu wenig; Constraint Attribution bleibt deutlich unter dominantem Einfluss; Question-Einfluss nimmt mit Planungshorizont ab; Episodic Memory verbessert globale Constraint-Nutzung, aber nicht fine-grained Referenzierung; Parametric Memory stärkt Question-Einfluss, löst Horizon-Degradation aber nicht; Strategien ähneln Shortcut Learning | Z4: Keine direkte Webagentenstudie; keine Tokenkosten oder Laufzeit; keine Attribution für GPT-Modelle wegen API-Einschränkungen; nur BlocksWorld und TravelPlanner; Memory-Strategien lösen dynamische Constraints und Long-Horizon-Fokus nicht vollständig | AA4: Offen bleibt, wie Agenten Constraints dauerhaft, fein granular und über lange Planungshorizonte hinweg berücksichtigen können; Übertragung auf Webagenten mit dynamischem DOM/GUI-Feedback, Validierungszeitpunkten, Kosten und Laufzeit bleibt ungeklärt | AB4: hoch; sehr relevant für Methodik, Planungshorizont, Planungsgrenzen, Constraint-Nutzung, Prozessmetriken und Gap-Ableitung; nicht als Core-Webagent codieren | AC4: mittel | AD4: Liefert Definition und Abgrenzung von Planning als Aktionssequenz mit Goal Decomposition, Constraint Consideration und Foresight; keine Webagenten-Definition | AE4: mittel | AF4: Beschreibt allgemeine Language-Agent-Komponenten mit Memory, Tool Use und Planning; keine konkrete Webagentenarchitektur | AG4: hoch | AH4: Zentrale Analyse von Planungsbarrieren, Constraints, Questions, Memory Updating und Horizon-Effekten | AI4: niedrig | AJ4: Keine echte Runtime-Validierung oder Replanning-Architektur; nur indirekte Analyse über Constraints, Feedback und Memory Updating | AK4: hoch | AL4: Starke Benchmark-, Metrik- und Diagnose-Evidenz mit Accuracy, Pass Rate, Constraint-/Question-Attribution und Horizon-Analyse | AM4: Methodik; Planung; Planungshorizont; Evaluation; Fehler/ Prozess; Research Gap | AN4: Abstract; Section 1; Section 2.1; Section 3; Figure 2; Figure 3; Figure 5; Figure 6; Table 1; Table 2; Table 3; Limitations | AO4: Screening-Notiz plausibel: Include für RQ2, RQ3, RQ5, Gap und Methodik; kein Core-Webagent; wichtig für Planungsgrenzen und Evaluationsmethodik; DOI 10.18653/v1/2025.naacl-long.93; wissenschaftliche Datenbank
A5: S004 | B5: C004 | C5: huTREEPLANNEREFFICIENTCLOSELOOP2024 | D5: TREE-PLANNER: Efficient Close-loop Task Planning with Large Language Models | E5: Hu et al. 2024 | F5: Conference Paper | G5: Ja | H5: VirtualHome; 4 Szenen; 35 hochwertige Household Tasks; 71 annotierte Task-Scene-Kombinationen vor Qualitätsfilterung; GPT-3.5 text-davinci-003; Settings mit und ohne Error Correction | I5: Closed-loop Task Planning; embodied household task planning; robotische/virtuelle Umgebungen; nicht direkt Webagent | J5: LLM-basierter Closed-loop Task Planner; kein Core-Webagent | K5: Plan Sampling; Action Tree Construction; Grounded Deciding; sampled plans als prior knowledge; Action Tree als aggregierter Suchraum; online Auswahl anhand von Observation, History und Error Information; Backtracking bei fehlgeschlagenen Aktionen | L5: Ja | M5: LLM erzeugt vor Ausführung mehrere mögliche Pläne; diese werden zu einem Action Tree aggregiert; während der Ausführung wählt der LLM aus gültigen Kindknoten environment-grounded die nächste Aktion | N5: Planlängen im Datensatz: durchschnittlich 8.13 Aktionen, Maximum 23 Aktionen; komplexe Tasks typischerweise mehrstufig; Anzahl gesampelter Pläne N=25 oder N=50 | O5: Ja; High-level Task wird in Mid-level Actions/Skills zerlegt; gemeinsame Planpräfixe werden im Action Tree gebündelt | P5: Ja | Q5: Grounded Deciding nutzt aktuelle Observation, History und Error Information; fehlgeschlagene Aktionen werden als invalid markiert; Umgebungsausführung prüft, ob Aktionen ausführbar sind | R5: Ja | S5: Bei Ausführungsfehlern: failed node und Subtree werden invalidiert; Backtracking zum letzten gültigen Fork; inverse Aktionen zur Zustandsrückführung; erneute Entscheidung am Fork statt vollständigem Global Replan | T5: Environment Observation; Action Execution Success/Failure; Error Information; History ausgeführter Aktionen; Goal Conditions in VirtualHome | U5: Executability EXEC.; Success Rate SR; Goal Conditions Recall GCR; TREE-PLANNER N=50 mit Correction: SR 41.58, GCR 59.55, EXEC 88.26; ohne Correction: N=25 SR 28.33, GCR 38.96, EXEC 55.74 | V5: $COST als OpenAI-basierte Tokenkosten; ohne Correction reduziert TREE-PLANNER Kosten gegenüber Iterative-Planner um 53.29%; mit Correction Reduktion gegenüber Local Replan um 74.36% und gegenüber Global Replan um 92.24% | W5: Keine direkte Wall-Clock-Laufzeit berichtet; Zeit-/Effizienzargument über Tokenkosten, Replanning-Aufwand und NO.EC; Backtracking reduziert unnötiges vollständiges Neuplanen | X5: NO.EC; GCRmax/GCRavg für Plan Sampling; Error-Type-Analyse; Missing Correct Plans 54.5%; Grounded Deciding Error 45.5%; NO.EC mit Correction bei TREE-PLANNER N=50: 2.04 vs Local Replan 3.29 und Global Replan 3.43 | Y5: TREE-PLANNER verbindet einmaliges Plan Sampling mit online Grounded Deciding; Action Tree reduziert wiederholte Promptkosten und erlaubt flexiblere Fehlerkorrektur; erreicht bessere oder vergleichbare Performance bei deutlich niedrigeren Kosten und weniger Error Corrections | Z5: Evaluation nur in VirtualHome; kein direkter Webagenten-Benchmark; GPT-3.5 als Backbone; Performance hängt von Qualität der gesampelten Pläne ab; Missing Correct Plans bleibt wichtigster Fehleranteil; keine systematische Variation von Validierungsintervallen oder Wall-Clock-Laufzeit | AA5: Offen bleibt, wie sich Action-Tree-basierte Planung auf Webagenten mit HTML/GUI/DOM-Feedback übertragen lässt; adaptive Validierungs- und Replanning-Zeitpunkte sowie reale Laufzeitkosten bleiben ungeklärt | AB5: hoch; sehr relevant für Closed-loop Planning, Replanning, Validierung, Kostenmetriken, Prozessmetriken und Gap-Ableitung | AC5: hoch | AD5: Liefert klare Definition und Abgrenzung von Open-loop vs Closed-loop Task Planning sowie POMDP-Formalisierung | AE5: hoch | AF5: Starke Architektur mit Plan Sampling, Action Tree Construction und Grounded Deciding | AG5: hoch | AH5: Explizite Planung über gesampelte Kandidatenpläne und Action-Tree-Suchraum; Long-Horizon-Aufgaben mit mehrstufigen Skills | AI5: hoch | AJ5: Sehr relevant für Validierung und Replanning durch Observation-grounded Decision, Error Information, Backtracking und Neuauswahl | AK5: hoch | AL5: Umfangreiche Evaluation mit EXEC, SR, GCR, $COST, NO.EC, Ablationen und Error Analysis | AM5: Definition; Architektur; Planung; Planungshorizont; Validierung; Replanning; Evaluation; Kosten; Fehler/ Prozess; Research Gap | AN5: Abstract; Figure 2; Section 2; Section 3.1-3.3; Section 4.1-4.2; Table 1; Section 5.1-5.4; Table 2; Table 3; Figure 5 | AO5: Screening-Notiz plausibel: Include für RQ1-RQ5 und Gap; nicht als Core-Webagent, sondern als Closed-loop-Planning-/Embodied-Agent-Paper codieren; Schlüssel: huTREEPLANNEREFFICIENTCLOSELOOP2024
A6: S005 | B6: C005 | C6: maherLLMPCLargeLanguage2025 | D6: LLMPC: Large Language Model Predictive Control | E6: Maher 2025 | F6: Preprint / arXiv | G6: Nein | H6: Mass-Spring-Control; Natural Plan Trip Planning; Natural Plan Meeting Planning; GPT-4o / GPT-4o-mini; iterative LLMPC mit Plan-Sampling und Feedback | I6: LLM-Planung; Model Predictive Control; Trip Planning; Meeting Planning; constraint-based Planning; Methodik/Background | J6: LLM-basierter Plan-Sampler mit externer Kosten-/Constraint-Evaluation; kein Core-Webagent | K6: LLM generiert K Kandidatenpläne bzw. Kontrollsequenzen; externe Objective-/Cost-/Constraint-Funktion bewertet Kandidaten; bester Plan wird ausgewählt; Teilplan wird ausgeführt; mit aktualisiertem Zustand/Feedback wird neu geplant | L6: Ja | M6: Receding-horizon / MPC-artige Planung; Sampling mehrerer Kandidatenpläne; Auswahl über externe Kostenfunktion; iterative Refinement-Schleife mit Feedback zu unerfüllten Constraints | N6: Planungshorizont H im Control-Beispiel H=3, davon werden 2 von 3 Schritten ausgeführt; Trip/Meeting Planning über Iterationsbudget T und Plananzahl K; Komplexität steigt mit Anzahl Städte bzw. Meetings | O6: Teilweise; Aufgaben werden in Reise-/Meeting-Sequenzen bzw. Kontrollaktionen zerlegt; keine explizite Subgoal-Hierarchie | P6: Ja | Q6: Constraint-based externe Evaluation: unerfüllte Constraints werden identifiziert und als Feedback in die nächste Planiteration gegeben; bei Control wird objective cost berechnet | R6: Ja | S6: Nach Teil-Ausführung bzw. nach jeder Iteration mit aktualisiertem Zustand oder Feedback; im Trip/Meeting Planning iterative Verbesserung über T Runden; kein adaptiver Trigger berichtet | T6: Externe Kostenfunktion; Constraint-Checker; Feedback zu unmet constraints; aktueller Zustand; vorheriger Plan; Benchmark-Erfolg | U6: Mean Objective Ratio; Success Rate; Trip Planning: GPT-4o 0.145 vs LLMPC T=7 0.446; Meeting Planning: GPT-4o 0.525 vs LLMPC T=9,K=3 0.67; Spring-Mass Objective Ratio sinkt von 8.21 bei K=1 auf 1.30 bei K=15 | V6: Nicht systematisch berichtet; Plananzahl K und Iterationsbudget T implizieren höhere LLM-Aufrufe, aber keine Tokenkosten oder $COST | W6: Keine Laufzeitmetriken berichtet | X6: Iteration Budget T; Plans per Iteration K; Objective Ratio; Success Rate nach Anzahl Cities/Meetings; Constraint Feedback; keine Replan-Anzahl oder Prozessfehlerklassifikation | Y6: LLMs können als approximative Optimierer von Planungskostenfunktionen verstanden werden; Sampling mehrerer Pläne und Auswahl über externe Objectives verbessert Planung; iterative Refinement-/Replanning-Schleifen erhöhen Success Rate besonders bei komplexeren Trip- und Meeting-Planning-Problemen | Z6: Preprint; keine direkte Webagenten-Evaluation; kein Tokenkosten-/Laufzeitvergleich; keine systematische Messung von Replan-Anzahl oder Validierungsintervallen; externe Cost-/Constraint-Funktionen müssen verfügbar sein; Evaluation begrenzt auf Control, Trip Planning und Meeting Planning | AA6: Offen bleibt, wie LLMPC auf Webagenten mit dynamischem HTML/GUI-Feedback übertragen werden kann; Tokenkosten, reale Laufzeit, Validierungsfrequenz, Replan-Anzahl und adaptive Trigger bleiben ungeklärt | AB6: hoch; sehr relevant für Planung als MPC/receding horizon, externe Validierung, Replanning und Gap zu Kosten/Laufzeit/Validierungsintervallen | AC6: niedrig | AD6: Keine zentrale Definition von Webagenten oder Language-Agent-Architektur; liefert aber MPC-Definition für Planung | AE6: mittel | AF6: Architektur ist eher methodischer MPC-Zyklus als Agentenarchitektur; trotzdem klare Komponenten aus Plan-Sampling, externer Bewertung und Replanning | AG6: hoch | AH6: Zentrale Relevanz für LLM-Planung als Sampling und Optimierung über externe Kosten-/Constraint-Funktionen | AI6: hoch | AJ6: Validierung über externe Constraint-/Cost-Evaluation und Replanning mit aktualisiertem Feedback ist zentral | AK6: hoch | AL6: Evaluation mit Objective Ratio und Success Rate; Kosten, Laufzeit und Prozessmetriken fehlen | AM6: Methodik; Planung; Planungshorizont; Validierung; Replanning; Evaluation; Kosten; Laufzeit; Research Gap | AN6: Abstract; Section 2; Section 3; Section 4.1-4.3; Table 1; Table 2; Figure 3; Table 3; Figure 4; Conclusion | AO6: Screening-Notiz plausibel: Include für RQ3, RQ4, RQ5 und Gap; nicht als Core-Webagent, sondern als methodisches Planning-/MPC-Paper codieren; arXiv:2501.02486v2; wissenschaftliche Datenbank
A7: S006 | B7: C006 | C7: hanTokenBudgetAwareLLMReasoning2025 | D7: Token-Budget-Aware LLM Reasoning | E7: Han et al. 2025 | F7: Preprint / arXiv | G7: Nein | H7: GSM8K; GSM8K-Zero; MathBench-Arithmetic; MathBench-Middle; MathBench-High; MathBench-College; Modelle: GPT-4o-mini, GPT-4o, Yi-lightning, o3-mini, Llama-3.1-8B-Instruct | I7: LLM-Reasoning; Chain-of-Thought; Tokenkosten; Reasoning-Budget; keine interaktive Agentenumgebung | J7: Kein Agentensystem; LLM-Reasoning-Methode mit Budget Estimator und Token-Budget-Prompting/Post-Training | K7: TALE-EP: Budget Estimator schätzt Reasoning-Tokenbudget und setzt es im Prompt; TALE-PT: SFT/DPO internalisiert token-budget-aware Reasoning; Budget Search mit Token Elasticity | L7: Teilweise | M7: Keine agentische Planung; CoT-Reasoning wird über Tokenbudget komprimiert; Methode steuert Länge des Reasoning-Prozesses | N7: Kein Planungshorizont im Agentensinn; Budget bezieht sich auf Reasoning-Länge bzw. Output Tokens | O7: Nein; keine Subgoal- oder Planhierarchie | P7: Nein | Q7: Keine Runtime-Validierung; Korrektheit wird über Ground-Truth-Antworten und Accuracy geprüft; Budget Search prüft Feasibility über Antwortkorrektheit | R7: Nein | S7: Nicht vorhanden; keine interaktive Umgebung und kein Replanning | T7: Prompt mit Tokenbudget; Budget Estimator; Ground-Truth-Antworten; Accuracy; Output Token Count; Expense | U7: Accuracy; Output Tokens; Expense; TALE-EP Average Accuracy 81.03% vs Vanilla CoT 83.75%; durchschnittliche Output Tokens 148.72 vs 461.25; Expense 118.46 vs 289.78 | V7: Explizit berichtet: Output Tokens und Expense; TALE-EP reduziert Output Tokens im Durchschnitt um ca. 67% bzw. 68.64% und Expense um ca. 59%; TALE-PT reduziert Tokenverbrauch ebenfalls deutlich | W7: Keine direkte Wall-Clock-Laufzeit; längere Reasoning-Ausgaben werden als Ursache höherer Inferenzzeit und Kosten diskutiert | X7: Token Elasticity; optimale Budgetsuche; Output Tokens; Expense; Accuracy-Cost-Trade-off; keine Agentenprozessmetriken | Y7: CoT enthält häufig redundante Tokens; sinnvolle Tokenbudgets können Reasoning deutlich komprimieren, ohne Accuracy stark zu senken; zu kleine Budgets können paradoxerweise mehr Tokens erzeugen; Budgetbewusstsein kann per Prompting oder Post-Training genutzt werden | Z7: Keine Webagenten oder interaktive Planung; keine Validierung, kein Replanning, keine Umgebung; Fokus auf mathematische Reasoning-Benchmarks; multimodale Outputs nicht betrachtet | AA7: Offen bleibt, wie Token-Budgeting auf agentische Planung, Webagenten, Validierungs-/Replanning-Schritte und tool-/environment-basierte Reasoning-Prozesse übertragen werden kann; Laufzeit wird nicht direkt gemessen | AB7: mittel; als Background-Quelle für Kosten-/Effizienzdiskussion und Reasoning-Budget nützlich, aber keine Core-Agenten- oder Webagentenstudie | AC7: niedrig | AD7: Keine Definition von Webagenten oder agentischer Planung | AE7: nicht relevant | AF7: Keine Agentenarchitektur; nur Reasoning-Budget-Methode | AG7: niedrig | AH7: Indirekt relevant für CoT/Reasoning-Länge, aber keine Planungsarchitektur oder Long-Horizon-Agenten | AI7: nicht relevant | AJ7: Keine Validierung oder Replanning in interaktiver Umgebung | AK7: hoch | AL7: Sehr relevant für Tokenkosten, Accuracy-Cost-Trade-off und Effizienzmetriken | AM7: Methodik; Evaluation; Kosten; Laufzeit; Research Gap | AN7: Abstract; Section 1; Figure 1; Section 3; Section 4; Algorithm 1; Algorithm 2; Section 5; Table 2; Table 3; Table 4; Limitations | AO7: Screening-Notiz plausibel: Background statt Include-Core; Priorität C; nützlich für Effizienz-/Tokenkosten-Diskussion, aber reduzierte Extraction ausreichend; arXiv:2412.18547v4; wissenschaftliche Datenbank
A8: S007 | B8: C007 | C8: sunTHINKONGRAPHDEEPRESPONSIBLE2024 | D8: Think-on-Graph: Deep and Responsible Reasoning of Large Language Model on Knowledge Graph | E8: Sun et al. 2024 | F8: Conference Paper | G8: Ja | H8: CWQ; WebQSP; GrailQA; QALD10-en; Simple Questions; WebQuestions; T-REx; Zero-Shot RE; Creak; KGs: Freebase und Wikidata; Backbones: ChatGPT, GPT-4, Llama-2-70B | I8: Knowledge-Graph Reasoning; Multi-Hop KGQA; Open-Domain QA; Slot Filling; Fact Checking; keine direkte Webagentenstudie | J8: LLM-Agent auf Knowledge Graph; LLM⊗KG-Paradigma; kein Core-Webagent | K8: LLM als Agent zur iterativen KG-Exploration; Initial Entity Detection; Beam Search auf KG; Search/Prune-Schritte für Relationen und Entitäten; Reasoning-Sufficiency-Check; Answer Generation aus Reasoning Paths; ToG-R als kostengünstigere relation-basierte Variante | L8: Ja | M8: Strukturierte Exploration mehrerer Reasoning Paths; Beam Search mit Search und Prune; LLM bewertet relevante Relationen/Entitäten und entscheidet, ob Informationen zur Antwort reichen | N8: Suchhorizont über maximale Graph-Tiefe Dmax operationalisiert; Standard Dmax=3 und Beam Width N=3; Ablation mit Tiefen und Breiten 1 bis 4; Fokus auf Multi-Hop Reasoning | O8: Ja; Frage wird in Topic Entities, Relationen, Entitäten und mehrstufige Reasoning Paths zerlegt | P8: Ja | Q8: Iterative Reasoning-Sufficiency-Prüfung: LLM bewertet nach jeder Exploration, ob aktuelle Reasoning Paths genügend Information enthalten; Knowledge Traceability und Correctability durch explizite Pfade | R8: Ja, aber nur im Reasoning-Sinn | S8: Wenn Information nicht ausreicht, werden Exploration und Reasoning bis Dmax wiederholt; kein Replanning während realer Handlungsausführung | T8: Knowledge Graph Triples; LLM-Pruning-Scores; Reasoning Paths; Expert-/User-Feedback für Knowledge Correctability; Hits@1 Labels | U8: Hits@1 / Exact Match; ToG mit GPT-4 erreicht neue SOTA auf 6 von 9 Datasets; Beispiele: WebQSP 82.6, GrailQA 81.4, Zero-Shot RE 88.3, Creak 95.6 | V8: Token-/Call-Kosten indirekt diskutiert; ToG benötigt höchstens 2ND + D + 1 LLM Calls; ToG-R höchstens ND + D + 1; kleine LLMs mit ToG können teurere große LLMs teilweise übertreffen | W8: Keine Wall-Clock-Laufzeit berichtet; Effizienz wird über Training-free Design, LLM-Call-Anzahl, kleine Backbones und alternative Pruning Tools diskutiert | X8: Search Depth/Width Ablation; Pruning-Tool-Ablation; Prompt-Design-Ablation; Knowledge Traceability; Knowledge Correctability; explizite Reasoning Paths | Y8: LLM⊗KG verbessert tiefe Multi-Hop-Reasoning-Fähigkeit durch strukturierte KG-Exploration; explizite Pfade erhöhen Nachvollziehbarkeit und Korrigierbarkeit; ToG ist training-free, plug-and-play und erreicht starke Ergebnisse über mehrere Datensätze | Z8: Keine Webagenten- oder Browserumgebung; kein Tool-/Action-Execution-Loop; keine echte Laufzeitmessung; Qualität des KG beeinflusst Ergebnis; LLM-Call-Kosten steigen mit Suchbreite und Tiefe; keine Validierungsintervalle oder Replanning während Handlungsausführung | AA8: Offen bleibt die Übertragung von ToG-artiger strukturierter Exploration, Reasoning-Sufficiency-Prüfung und Traceability auf Webagenten mit HTML/DOM/GUI-Feedback, realer Ausführung, Replanning und Kosten-/Laufzeitmessung | AB8: hoch; wichtiges B-Supporting-Include für strukturierte Exploration, Reasoning-Pfade, Validierung durch Sufficiency-Checks, Prozessmetriken und Gap-Ableitung | AC8: niedrig | AD8: Liefert keine Webagenten-Definition, aber eine nützliche Abgrenzung von LLM-only, LLM⊕KG und LLM⊗KG | AE8: mittel | AF8: Beschreibt eine agentische LLM⊗KG-Architektur, aber keine Webagentenarchitektur | AG8: hoch | AH8: Sehr relevant für strukturierte Planung/Exploration über Reasoning Paths, Beam Search und Search/Prune-Strategien | AI8: mittel | AJ8: Relevanz über Sufficiency-Prüfung, Traceability und Correctability; kein echtes Runtime-Replanning in einer Umgebung | AK8: hoch | AL8: Starke Evaluation mit Hits@1, 9 Datensätzen, Ablationen, Kosten-/Call-Diskussion und Prozessanalyse | AM8: Methodik; Architektur; Planung; Planungshorizont; Validierung; Evaluation; Kosten; Fehler/ Prozess; Research Gap | AN8: Abstract; Figure 1; Figure 2; Section 2.1; Section 2.2; Section 3.1-3.3; Table 1; Table 2; Figure 3; Table 5; Figure 4; Conclusion | AO8: Screening-Notiz plausibel: Include als B-Supporting-Paper; keine direkte Webagentenstudie, aber stark für Methodik, strukturierte Exploration, Validierung, Kosten-/Call-Trade-offs und Traceability; ICLR 2024 / OpenReview; wissenschaftliche Datenbank
A9: S008 | B9: C008 | C9: chenPlanonGraphSelfCorrectingAdaptive2024 | D9: Plan-on-Graph: Self-Correcting Adaptive Planning of Large Language Model on Knowledge Graphs | E9: Chen et al. 2024 | F9: Conference Paper | G9: Ja | H9: CWQ; WebQSP; GrailQA; Freebase; GPT-3.5; GPT-4; Vergleich mit ToG, StructGPT, CoT, SC und fine-tuned KGQA-Baselines | I9: Knowledge-Graph Question Answering; Multi-Hop Reasoning; KG-augmented LLM; keine direkte Webagentenstudie | J9: LLM-Agent auf Knowledge Graph; selbstkorrigierender adaptiver Planner; kein Core-Webagent | K9: Task Decomposition; Path Exploration; Memory Updating; Evaluation; Guidance; Memory; Reflection; adaptive Exploration Breadth; Backtracking zu relevanten Entitäten; Self-Correction fehlerhafter Reasoning Paths | L9: Ja | M9: Adaptive KG-Exploration auf Basis von Sub-Objectives; flexible Auswahl relevanter Relationen und Entitäten; Planung als schrittweises Finden und Korrigieren von Reasoning Paths | N9: Kein fixer Webaktionshorizont; Graph-Reasoning über iterative Exploration; Pfadlängen können variieren; Exploration läuft bis ausreichende Information gefunden ist | O9: Ja; Frage wird in Sub-Objectives zerlegt, die Bedingungen der Frage explizit repräsentieren | P9: Ja | Q9: Evaluation prüft, ob Memory, Reasoning Paths und Sub-Objective Status ausreichend sind, um eine Antwort abzuleiten; Reflection prüft bei unzureichender Information, ob aktuelle Pfade korrigiert werden müssen | R9: Ja | S9: Bei insufficient information reflektiert PoG, ob aktuelle Pfade falsch sind; falls ja, Backtracking zu Kandidatenentitäten aus Memory und neue Exploration; kein Replanning während realer Web-/Tool-Ausführung | T9: Knowledge Graph Triples; Reasoning Paths; Sub-Objective Status; Memory; Reflection Reason; LLM-basierte Auswahl; Hits@1 Labels | U9: Hits@1; PoG mit GPT-3.5: CWQ 63.2, WebQSP 82.0, GrailQA 76.5; PoG mit GPT-4: CWQ 75.0, WebQSP 87.3, GrailQA 84.7 | V9: Input Tokens; Output Tokens; Total Tokens; LLM Calls; PoG reduziert LLM Calls und Tokenverbrauch gegenüber ToG deutlich, z. B. CWQ Total Tokens 8,156.2 vs 9,669.4 und Output Tokens 353.2 vs 1,486.4 | W9: Wall-Clock-Time berichtet: CWQ 23.3s vs ToG 96.5s; WebQSP 16.8s vs 63.1s; GrailQA 11.5s vs 50.2s | X9: LLM Calls; Input/Output/Total Tokens; Time; Ablationen zu Guidance, Memory, Reflection und Adaptive Breadth; Case Study zu Self-Correction und fehlerhaften Pfaden | Y9: PoG verbessert KGQA durch adaptive Planung, Memory und Reflection; Self-Correction verhindert Fortsetzung falscher Reasoning Paths; Memory hilft gegen Vergessen von Teilbedingungen; PoG ist effektiver und effizienter als ToG | Z9: Keine Webagenten- oder Browserumgebung; keine reale Tool-/UI-Ausführung; beschränkt auf KGQA; Topic Entities sind in Datensätzen vorverlinkt; externe KG-Qualität bleibt Voraussetzung; keine Success Rate für interaktive Aufgaben | AA9: Offen bleibt, wie adaptive Path Exploration, Memory, Reflection und Backtracking auf Webagenten mit DOM/GUI-Feedback, Tool-Ausführung, Validierungszeitpunkten und realen Replanning-Triggern übertragen werden können | AB9: hoch; starkes B-Supporting-Include für adaptive Planung, Validierung, Replanning, Memory, Reflection, Kosten, Laufzeit und Prozessmetriken | AC9: niedrig | AD9: Keine Webagenten-Definition; liefert aber Hintergrund zu KGQA und Reasoning Paths | AE9: mittel | AF9: Starke agentische KG-Architektur mit Guidance, Memory und Reflection, aber keine Webagentenarchitektur | AG9: hoch | AH9: Zentrale Relevanz für adaptive Planung, Task Decomposition und Path Exploration | AI9: hoch | AJ9: Reflection, Evaluation, Self-Correction und Backtracking sind zentrale Mechanismen | AK9: hoch | AL9: Sehr starke Evaluation mit Hits@1, LLM Calls, Tokens, Laufzeit, Ablationen und Case Study | AM9: Methodik; Architektur; Planung; Planungshorizont; Validierung; Replanning; Evaluation; Kosten; Laufzeit; Fehler/ Prozess; Research Gap | AN9: Abstract; Figure 1; Figure 2; Section 3.1-3.4; Table 1; Table 2; Table 3; Table 4; Figure 3; Conclusion | AO9: Screening-Notiz plausibel: Include als B-Supporting-Paper; keine direkte Webagentenstudie, aber stark für adaptive Planung, Reflection/Self-Correction, Memory, Effizienzmetriken und Gap-Ableitung; arXiv:2410.23875; NeurIPS 2024
A10: S009 | B10: C009 | C10: liLATCHLatencyboundedLatent2026 | D10: LATCH: latency-bounded latent lookahead for constraint-safe web agents | E10: Li et al. 2026 | F10: Preprint / Research Square | G10: Nein | H10: WebShop; Mind2Web; WebArena; textbasierte DOM-/Tool-Interfaces; shared tool schema; validators; K=40 step budget | I10: Webagenten; tool-mediated web interaction; constraint-safe web agents; latent lookahead; world-model planning | J10: LLM-basierter Webagent mit latentem World-Model-Selector; A-Core-Webagent | K10: Environment Encoder; Action Proposal Module; Hybrid SSM+Attention Dynamics; Typed Entity Memory für OBJ/LOC/CON/TOOL; calibrated Critic; Beam-/Horizon-Planner; shared validators; Execute-first-action loop | L10: Ja | M10: Simulate-then-select in latent space; open action space wird durch APM auf schema-valide top-M candidates komprimiert; Short-horizon latent rollouts bewerten Kandidaten vor Ausführung; Planner wählt erste Aktion der besten imaginären Trajektorie | N10: H=5 short-horizon rollout; Beam B=4; Candidate Set Mc=32; K=40 Interaktionsbudget; pro Entscheidung 640 Critic-/Transition-Evaluations | O10: Teilweise; keine klassische Subgoal-Hierarchie, aber typed memory stabilisiert Constraints, Entities und Tool-Facts über mehrere Schritte | P10: Ja | Q10: Constraint propagation über latent dynamics und typed memory; schema-valid candidates; shared validators reject malformed tool calls; Critic bewertet Feasibility und Success-Wahrscheinlichkeit | R10: Ja | S10: Receding-horizon-artig pro Entscheidung: nach Ausführung einer Aktion wird mit neuer Observation und Memory erneut simuliert und selektiert; kein explizites Global Replanning, sondern step-wise latent replanning | T10: Tool-/DOM-Observation; validator feedback; typed entity memory; latent transition predictions; critic scores; benchmark success labels; constraint violation labels | U10: Task Success Rate; Constraint Violation Rate; Invalid Action Rate; WebShop TSR 70.2 vs GPT-4o+ReAct 63.8; Mind2Web 56.8 vs 52.6; WebArena 53.4 vs 49.8 | V10: Tokens pro Step; latent evaluations; LLM Calls indirekt; LATCH nutzt 406 tokens pro Step und 640 latent evaluations; CVR-Reduktion gegenüber GPT-4o+ReAct 33-42% relativ | W10: Wall-time berichtet; latent rollout 42 ms/step; WebShop TSR bei 60s Budget 68.4 vs GPT-4o+ReAct 54.8; API-Baselines deutlich langsamer | X10: Selection Error; CVR; IAR; transition-depth accuracy; memory-slot accuracy; regression categories; failure attribution; site-holdout; stress tests; budget-matched wall-time curves | Y10: LATCH verbessert TSR, CVR und IAR gleichzeitig; der Fixed-Candidate-Control zeigt, dass der Gewinn nicht nur von besseren Kandidaten kommt, sondern von latent rollout planning; LATCH erzielt +12.8 TSR gegenüber token-matched LLM reranking bei gleichem Candidate Set | Z10: Preprint, nicht peer-reviewed; Fokus auf textbasierte tool-mediated Webinterfaces mit festen Schemas und Validators; keine multimodalen Webagenten; keine OS-/VisualWebArena-ähnliche UI-Perception; Training braucht große Offline-Trajektorien; reale Sicherheit nicht vollständig abgedeckt | AA10: Offen bleiben multimodale Webagenten, adaptive Horizon-Steuerung, Unsicherheitsmodellierung, robustere UI-Grounding-Mechanismen, Skalierung mit weniger Offline-Daten und echte Safety-Gates für irreversible Aktionen | AB10: sehr hoch; A-Core-Include für Webagenten, Latency-bounded Planning, Validierung, Replanning, Kosten, Laufzeit und Prozessmetriken | AC10: hoch | AD10: Liefert klare Problemdefinition für Webagenten unter Interaktionsbudgets, Validators und Constraints | AE10: hoch | AF10: Sehr klare Webagentenarchitektur mit Proposal, Encoder, Dynamics, Memory, Critic und Planner | AG10: hoch | AH10: Zentrale Methode ist latent lookahead planning mit simulate-then-select und bounded candidate evaluation | AI10: hoch | AJ10: Sehr relevant für Constraint-Validierung, schema-valide Kandidaten, shared validators und per-step replanning | AK10: hoch | AL10: Starke Evaluation mit TSR, CVR, IAR, Tokens, latent evaluations, wall-time, selection error und Robustness-Diagnostik | AM10: Definition; Architektur; Planung; Planungshorizont; Validierung; Replanning; Evaluation; Kosten; Laufzeit; Fehler/ Prozess; Research Gap | AN10: Abstract; Background; Figure 1; Section 2.1; Table 1; Figure 2; Table 2; Section 2.3; Section 3; Section 4.1-4.4; Limitations | AO10: Screening-Notiz plausibel: A-Core-Include; sehr relevant für Webagenten und Thesis-Metriken; Preprint-Status unbedingt markieren; DOI 10.21203/rs.3.rs-8912469/v1; Research Square
